Workbook

Sheet Dashboard
A1: To pay back | F1: Monthly payment | L1: Trả chị Diễm
A2: Owner | C2: Amount (N) | F2: Name | H2: Amount (N) | I2: Charge date | L2: Đợt | M2: Số tiền | N2: Ngày
F3: Shinhan | H3: 1700 | I3: 1 | L3: 1 | M3: 5000 | N3: 46053
F4: YouTube Premium | H4: 52 | I4: 12 | L4: 2 | M4: 2000 | N4: 46081
F5: Gonsa | H5: 5000 | I5: 15 | L5: 3 | M5: 1000 | N5: 46112
F6: Vinaphone 4G | H6: 70 | I6: 26 | L6: 4 | M6: 500 | N6: 46116
L7: 5 | M7: 1000 | N7: 46142
A8: To earn back | L8: 6 | M8: 500 | N8: 46147
A9: Debtors | C9: Amount (N) | D9: Reason | L9: 7 | M9: 1000 | N9: 46233
A10: Khôi | C10: 2750 | D10: Lost | L10: 8
A11: Nguyệt | C11: 3000 | D11: Lost | L11: 9
A12: Bảo | C12: 400 | L12: 10
L13: 11
L14: 12
L15: 13
L16: 14
L17: 15
L18: 16
L19: 17
L20: Tổng | M20: =SUM(M3:M19) -> 11000 | N20: / 50000

Sheet T102026
A1: DATE | B1: SPENT FOR | C1: AMOUNT | D1: TYPE | F1: DATE | G1: EARN BY | H1: AMOUNT
A2: 46294 | B2: Trả Thiên | C2: 1000 | D2: Trả tiền mượn sinh hoạt | F2: 46294 | G2: Lương T9 + Dư T9 | H2: =24357+'T92026'!G18 -> 24485
B3: Trả A Khoa | C3: 2000 | D3: Trả tiền mượn sinh hoạt | H3: 5500
B4: Help Bảo | C4: 300 | D4: Support
B5: Trả tín dụng | C5: 1000 | D5: Trả tín dụng
B6: Trả Phúc | C6: 550 | D6: Trả tiền mượn sinh hoạt
B7: Đổ xăng | C7: 70 | D7: Thiết yếu
B8: Lê Trang | C8: 57 | D8: Living expense
B9: Cho Má | C9: 3000 | D9: Tiền ăn ba má
B10: Tạp hóa | C10: 89 | D10: Living expense
B11: Claude Code | C11: 600 | D11: Công việc
B12: Trả cô Ánh | C12: 800 | D12: Trả tiền mượn sinh hoạt
A13: 46295 | B13: HBO Max | C13: 135 | D13: Credit | F13: Total earn | G13: =SUM(H2:H12) -> 29985
B14: Ăn trưa | C14: 60 | D14: Living expense | F14: Total spent | G14: =SUMPRODUCT(((D2:D233<>"Credit")*(D2:D233<>"Quỹ Shinhan"))*C2:C233) + G15 -> 12623
B15: Sửa xe | C15: 75 | D15: Thiết yếu | F15: Untrack spent | G15: =39 -> 39
B16: Bún riêu | C16: 25 | D16: Living expense | F16: Saving | G16: 0
A17: 46296 | B17: Shinhan | C17: 1700 | D17: Shinhan
B18: Nước ngọt | C18: 16 | D18: Living expense | F18: Remaining | G18: =G13-G14-J26 -> 5318
B19: Cơm gà Lê Trang | C19: 45 | D19: Living expense | F19: Remaining (- liabilities) | G19: =G13-G14 -> 17362
B20: Nước bình | C20: 160 | D20: Thiết yếu
B21: Grab | C21: 20 | D21: Living expense | F21: Category | G21: Estimated | H21: Actual
A22: 46297 | B22: Grab | C22: 14 | D22: Living expense | F22: Living expense | G22: 8000 | H22: =SUMIF(D2:D156, "=Living expense",C2:C174)+G15 -> 412
B23: Ăn trưa | C23: 38 | D23: Living expense
B24: Tiền điện Trà Vinh | C24: 10 | D24: Tiền nhà | F24: Planned/actual spend per category of this month
B25: Tiền điện Cần Thơ | C25: 646 | D25: Tiền nhà | F25: Category | G25: Estimated | H25: Actual | I25: Finalize | J25: Reserve
B26: Trả Ly | C26: 300 | D26: Special | F26: Sum | G26: =SUM(G27:G111) -> 23530 | H26: =SUM(H27:H111) -> 10706 | J26: =SUM(J27:J111) -> 12044
B27: Hủ tiếu | C27: 30 | D27: Living expense | F27: Tiền nhà | G27: 7200 | H27: =IFERROR(__xludf.DUMMYFUNCTION("SUMIF($D$2:$D$532, TO_TEXT(F27) ,$C$2:$C$532)"),656.0) -> 656 | I27: FALSE | J27: =IF(I27=TRUE,0,MAX(G27-H27,0)) -> 6544
B28: Nước ngọt | C28: 24 | D28: Living expense | F28: Gonsa | G28: 5000 | H28: =IFERROR(__xludf.DUMMYFUNCTION("SUMIF($D$2:$D$532, TO_TEXT(F28) ,$C$2:$C$532)"),0.0) -> 0 | I28: FALSE | J28: =IF(I28=TRUE,0,MAX(G28-H28,0)) -> 5000
B29: Toàn HBO Max | C29: -45 | D29: Living expense | F29: Trả tiền mượn sinh hoạt | G29: =2000+1000+550+800 -> 4350 | H29: =IFERROR(__xludf.DUMMYFUNCTION("SUMIF($D$2:$D$532, TO_TEXT(F29) ,$C$2:$C$532)"),4350.0) -> 4350 | I29: TRUE | J29: =IF(I29=TRUE,0,MAX(G29-H29,0)) -> 0
D30: Living expense | F30: Trả tín dụng | G30: 1000 | H30: =IFERROR(__xludf.DUMMYFUNCTION("SUMIF($D$2:$D$532, TO_TEXT(F30) ,$C$2:$C$532)"),1000.0) -> 1000 | I30: TRUE | J30: =IF(I30=TRUE,0,MAX(G30-H30,0)) -> 0
D31: Living expense | F31: Shinhan | G31: 1700 | H31: =IFERROR(__xludf.DUMMYFUNCTION("SUMIF($D$2:$D$532, TO_TEXT(F31) ,$C$2:$C$532)"),1700.0) -> 1700 | I31: TRUE | J31: =IF(I31=TRUE,0,MAX(G31-H31,0)) -> 0
D32: Living expense | F32: Tiền ăn ba má | G32: 3000 | H32: =IFERROR(__xludf.DUMMYFUNCTION("SUMIF($D$2:$D$532, TO_TEXT(F32) ,$C$2:$C$532)"),3000.0) -> 3000 | I32: TRUE | J32: =IF(I32=TRUE,0,MAX(G32-H32,0)) -> 0
D33: Living expense | F33: Sức khỏe | G33: 500 | H33: =IFERROR(__xludf.DUMMYFUNCTION("SUMIF($D$2:$D$532, TO_TEXT(F33) ,$C$2:$C$532)"),0.0) -> 0 | I33: FALSE | J33: =IF(I33=TRUE,0,MAX(G33-H33,0)) -> 500
D34: Living expense | F34: Dịch vụ | G34: =600+180 -> 780 | H34: =IFERROR(__xludf.DUMMYFUNCTION("SUMIF($D$2:$D$532, TO_TEXT(F34) ,$C$2:$C$532)"),0.0) -> 0 | I34: TRUE | J34: =IF(I34=TRUE,0,MAX(G34-H34,0)) -> 0
D35: Living expense
D36: Living expense
D37: Living expense
D38: Living expense
D39: Living expense
D40: Living expense
D41: Living expense
D42: Living expense
D43: Living expense
D44: Living expense
D45: Living expense
D46: Living expense
... D92: Living expense

Sheet T92026
A1: DATE | B1: SPENT FOR | C1: AMOUNT | D1: TYPE | F1: DATE | G1: EARN BY | H1: AMOUNT
A2: 46262 | B2: Ăn trưa | C2: 38 | D2: Living expense | F2: 46261 | G2: Lương T8 + Dư T8 | H2: =24357+'T82026'!G18 -> 27917
B3: Nước ngọt | C3: 16 | D3: Living expense | G3: A Bảo support | H3: 1000
B4: Jolibee | C4: 93 | D4: Living expense | F4: 46280 | G4: Thiên Help | H4: 1000
B5: Cơm cho Má | C5: 63 | D5: Living expense | G5: Má cho mượn | H5: 2000
B6: Trả Khang | C6: 2000 | D6: Trả Khang | G6: A Khoa cho mượn | H6: 2000
A7: 46263 | B7: Khám bệnh cho Má | C7: =100+218 -> 318 | D7: Sức khỏe | F7: 46281 | G7: A Bảo support | H7: 500
B8: Highland | C8: 60 | D8: Living expense | F8: 46288 | G8: Má cho | H8: 50
B9: Ăn sáng | C9: 28 | D9: Living expense | F9: 46288 | G9: Má mượn cho | H9: 500
B10: Ăn chiều | C10: 70 | D10: Living expense | F10: 46289 | G10: Bảo cho | H10: 200
B11: Ăn tối | C11: 66 | D11: Living expense | F11: 46291 | G11: Phúc help | H11: 500
A12: 46264 | B12: Khám bệnh cho Ba | C12: =130+61+62 -> 253 | D12: Sức khỏe
B13: Bánh mì | C13: 19 | D13: Living expense | F13: Total earn | G13: =SUM(H2:H12) -> 35667
B14: Ăn trưa với Má | C14: 64 | D14: Living expense | F14: Total spent | G14: =SUMPRODUCT(((D2:D233<>"Credit")*(D2:D233<>"Quỹ Shinhan"))*C2:C233) + G15 -> 35539
B15: Mua sắm siêu thị | C15: 305 | D15: Living expense | F15: Untrack spent | G15: =-62+103+45-156+1+108+205+81+101+81+32+6 -> 545
B16: Tiền ăn ba má | C16: 4000 | D16: Tiền ăn ba má | F16: Saving | G16: 0
B17: Ăn tối | C17: 69 | D17: Living expense
B18: HBO Max | C18: =99+36 -> 135 | D18: Credit | F18: Remaining | G18: =G13-G14-J26 -> 128
B19: Trả tín dụng | C19: 1500 | D19: Trả tín dụng | F19: Remaining (- liabilities) | G19: =G13-G14 -> 128
A20: 46265 | B20: Taxi về quê | C20: 1002 | D20: Taxi về quê
B21: Nạp 4G cho Má | C21: 20 | D21: Parent | F21: Category | G21: Estimated | H21: Actual
B22: Bún nem nướng | C22: 89 | D22: Living expense | F22: Living expense | G22: 8000 | H22: =SUMIF(D2:D156, "=Living expense",C2:C174)+G15 -> 8122
B23: Game | C23: 45 | D23: Living expense
B24: Vé phim | C24: 127 | D24: Living expense | F24: Planned/actual spend per category of this month
A25: 46266 | B25: Cơm | C25: 25 | D25: Living expense | F25: Category | G25: Estimated | H25: Actual | I25: Finalize | J25: Reserve
B26: Trung Nguyên Vincom | C26: 53 | D26: Living expense | F26: Sum | G26: =SUM(G27:G111) -> 25000 | H26: =SUM(H27:H111) -> 26541 | J26: =SUM(J27:J111) -> 0
B27: Nước rạp phim | C27: 89 | D27: Living expense | F27: Tiền nhà | G27: 7200 | H27: =IFERROR(__xludf.DUMMYFUNCTION("SUMIF($D$2:$D$532, TO_TEXT(F27) ,$C$2:$C$532)"),7268.0) -> 7268 | I27: TRUE | J27: =IF(I27=TRUE,0,MAX(G27-H27,0)) -> 0
B28: Bún nem nướng | C28: 89 | D28: Living expense | F28: Gonsa | G28: 5000 | H28: =IFERROR(__xludf.DUMMYFUNCTION("SUMIF($D$2:$D$532, TO_TEXT(F28) ,$C$2:$C$532)"),5000.0) -> 5000 | I28: TRUE | J28: =IF(I28=TRUE,0,MAX(G28-H28,0)) -> 0
B29: Shinhan | C29: 1700 | D29: Shinhan | F29: Help Ly | G29: 2000 | H29: =IFERROR(__xludf.DUMMYFUNCTION("SUMIF($D$2:$D$532, TO_TEXT(F29) ,$C$2:$C$532)"),2000.0) -> 2000 | I29: TRUE | J29: =IF(I29=TRUE,0,MAX(G29-H29,0)) -> 0
B30: Bánh mì | C30: 20 | D30: Living expense | F30: Trả tín dụng | G30: 1500 | H30: =IFERROR(__xludf.DUMMYFUNCTION("SUMIF($D$2:$D$532, TO_TEXT(F30) ,$C$2:$C$532)"),1500.0) -> 1500 | I30: TRUE | J30: =IF(I30=TRUE,0,MAX(G30-H30,0)) -> 0
A31: 46267 | B31: Ăn sáng | C31: 35 | D31: Living expense | F31: Shinhan | G31: 1700 | H31: =IFERROR(__xludf.DUMMYFUNCTION("SUMIF($D$2:$D$532, TO_TEXT(F31) ,$C$2:$C$532)"),1700.0) -> 1700 | I31: TRUE | J31: =IF(I31=TRUE,0,MAX(G31-H31,0)) -> 0
B32: Cafe | C32: 35 | D32: Living expense | F32: Tiền ăn ba má | G32: 3000 | H32: =IFERROR(__xludf.DUMMYFUNCTION("SUMIF($D$2:$D$532, TO_TEXT(F32) ,$C$2:$C$532)"),3000.0) -> 3000 | I32: TRUE | J32: =IF(I32=TRUE,0,MAX(G32-H32,0)) -> 0
B33: Genshin | C33: 129 | D33: Credit | F33: Sức khỏe | G33: 600 | H33: =IFERROR(__xludf.DUMMYFUNCTION("SUMIF($D$2:$D$532, TO_TEXT(F33) ,$C$2:$C$532)"),2216.0) -> 2216 | I33: TRUE | J33: =IF(I33=TRUE,0,MAX(G33-H33,0)) -> 0
B34: Net | C34: 50 | D34: Living expense | F34: Trả Khang | G34: 2000 | H34: =IFERROR(__xludf.DUMMYFUNCTION("SUMIF($D$2:$D$532, TO_TEXT(F34) ,$C$2:$C$532)"),2000.0) -> 2000 | I34: TRUE | J34: =IF(I34=TRUE,0,MAX(G34-H34,0)) -> 0
B35: Đồ chiên | C35: 50 | D35: Living expense | F35: Taxi về quê | G35: 2000 | H35: =IFERROR(__xludf.DUMMYFUNCTION("SUMIF($D$2:$D$532, TO_TEXT(F35) ,$C$2:$C$532)"),1857.0) -> 1857 | I35: TRUE | J35: =IF(I35=TRUE,0,MAX(G35-H35,0)) -> 0
B36: Tiền điện Trà Vinh | C36: 10 | D36: Tiền nhà
B37: Taxi | C37: 855 | D37: Taxi về quê
A38: 46268 | B38: Trà | C38: 20 | D38: Living expense
B39: Tiền điện Cần Thơ | C39: 769 | D39: Tiền nhà
B40: Tiền Wifi | C40: 240 | D40: Tiền nhà
B41: Đặt cơm | C41: =148-59-43 -> 46 | D41: Living expense
B42: Fahasha | C42: 175 | D42: Living expense
B43: Ăn tối | C43: 73 | D43: Living expense
A44: 46269 | B44: Ăn trưa | C44: =198-38-40-40-40 -> 40 | D44: Living expense
B45: Nước ngọt | C45: 16 | D45: Living expense
B46: Help Ly | C46: 2000 | D46: Help Ly
B47: Ăn chiều cơm gà | C47: =153-41-59 -> 53 | D47: Living expense
B48: Nước ngọt | C48: 15 | D48: Living expense
A49: 46270 | B49: Ăn trưa | C49: 30 | D49: Living expense
B50: Nước ngọt | C50: 30 | D50: Living expense
B51: Ăn tối | C51: 57 | D51: Living expense
A52: 46271 | B52: Chi tiêu ngày sinh nhật | C52: 1034 | D52: Living expense
A53: 46272 | B53: Ăn sáng | C53: 15 | D53: Living expense
B54: Ăn trưa | C54: 63 | D54: Living expense
B55: Nước | C55: 22 | D55: Living expense
B56: Tiền ăn ba má | C56: -1000 | D56: Tiền ăn ba má
A57: 46273 | B57: Ăn tối | C57: =90-35 -> 55 | D57: Living expense
B58: Đổ xăng | C58: 50 | D58: Living expense
A59: 46274 | B59: Nước ngọt | C59: 22 | D59: Living expense
B60: Ăn chiều | C60: 43 | D60: Living expense
B61: Đồ chiên | C61: 40 | D61: Living expense
B62: Áo Rocket | C62: 156 | D62: Special
A63: 46275 | B63: Ăn sáng | C63: 15 | D63: Living expense
B64: Order ăn chiều | C64: =127-58 -> 69 | D64: Living expense
B65: Nước ngọt | C65: 22 | D65: Living expense
A66: 46276 | B66: Ăn sáng BV | C66: 47 | D66: Living expense
A67: 46277 | B67: Order ăn trưa | C67: 76 | D67: Living expense
B68: YouTube Premium | C68: 87 | D68: Living expense
B69: Netflix | C69: 231 | D69: Living expense
B70: Ăn tối | C70: 30 | D70: Living expense
A71: 46278 | B71: Ăn sáng (trường CNTT) | C71: 62 | D71: Living expense
B72: The 80s | C72: 70 | D72: Living expense
B73: Cơm phần | C73: 145 | D73: Living expense
B74: Tiền kết lễ | C74: 30 | D74: Living expense
B75: Bột chiên | C75: 65 | D75: Living expense
B76: HIghland | C76: 107 | D76: Living expense
A77: 46279 | B77: Ăn sáng | C77: 37 | D77: Living expense
B78: Súp | C78: 25 | D78: Living expense
B79: Jolibee | C79: 67 | D79: Living expense
A80: 46280 | B80: Khám bệnh cho Má | C80: =100+1500+45 -> 1645 | D80: Sức khỏe
B81: Tiền nhà | C81: 6000 | D81: Tiền nhà
B82: Gonsa | C82: 5000 | D82: Gonsa
B83: Súp | C83: 35 | D83: Living expense
B84: Bánh | C84: 30 | D84: Living expense
B85: Ăn tối Jollibee | C85: 102 | D85: Living expense
B86: Nước bình | C86: 160 | D86: Tiền nhà
B87: Tiền nước Cần Thơ | C87: 89 | D87: Tiền nhà
A88: 46281 | B88: Súp | C88: 37 | D88: Living expense
B89: Ăn tối | C89: =35 -> 35 | D89: Living expense
A90: 46282 | B90: Cà phê | C90: 18 | D90: Living expense
B91: Sâm | C91: 17 | D91: Living expense
B92: Gởi Má | C92: 700 | D92: Parent
A93: 46283 | B93: Ăn trưa | C93: 60 | D93: Living expense
B94: Sinh tố | C94: 40 | D94: Living expense
B95: Ăn chiều | C95: 62 | D95: Living expense
B96: Pizza | C96: 195 | D96: Living expense
A97: 46284 | B97: Ăn sáng | C97: 30 | D97: Living expense
B98: Đi chợ | C98: 91 | D98: Living expense
B99: Ăn tối | C99: =139-56 -> 83 | D99: Living expense
B100: Phúc trả tiền ăn | C100: -150 | D100: Living expense
...

Sheet T82026
A1: DATE | B1: SPENT FOR | C1: AMOUNT | D1: TYPE | F1: DATE | G1: EARN BY | H1: AMOUNT
A2: 46233 | B2: Ăn trưa | C2: 30 | D2: Living expense | F2: 46233 | G2: Lương T7 + Dư T7 | H2: =24357+'T72026'!G18 -> 24468
B3: Sữa | C3: 14 | D3: Living expense | F3: 46239 | G3: Lương Ba | H3: 5500
B4: Trả Khang | C4: 2000 | D4: Trả Khang | F4: 46240 | G4: Má gởi | H4: 200
B5: Trả tín dụng | C5: 1000 | D5: Trả tín dụng | G5: Bảo gởi | H5: 100
B6: Cơm gà | C6: =218-56-41-33-45 -> 43 | D6: Living expense | F6: 46254 | G6: Khang help | H6: 2000
B7: Sữa | C7: 26 | D7: Living expense | F7: 46255 | G7: Tiền thưởng của Ba | H7: 650
B8: Bún riêu cho Má | C8: 30 | D8: Parent | F8: 46258 | G8: Lương Ba | H8: 5580
B9: Gởi Má | C9: 4500 | D9: Tiền ăn ba má
B10: Trả chị Diễm | C10: 1000 | D10: Trả chị Diễm
A11: 46234 | B11: Ăn trưa | C11: 40 | D11: Living expense
B12: Sữa | C12: 14 | D12: Living expense
B13: Ăn chiều | C13: 57 | D13: Living expense | F13: Total earn | G13: =SUM(H2:H12) -> 38498
B14: Bột chiên | C14: 54 | D14: Living expense | F14: Total spent | G14: =SUMPRODUCT(((D2:D231<>"Credit")*(D2:D231<>"Quỹ Shinhan"))*C2:C231) + G15 -> 34938
A15: 46235 | B15: Khám bệnh | C15: =100+100+68+70 -> 338 | D15: Sức khỏe | F15: Untrack spent | G15: =-2+62+3+77+224+412+76+47 -> 899
B16: Highland | C16: 59 | D16: Living expense | F16: Saving | G16: 0
B17: Nước ngọt | C17: 24 | D17: Living expense
B18: Shinhan | C18: 1700 | D18: Shinhan | F18: Remaining | G18: =G13-G14-J26 -> 3560
B19: Help Ly | C19: 1500 | D19: Help Ly | F19: Remaining (- liabilities) | G19: =G13-G14 -> 3560
A20: 46236 | B20: Ăn trưa | C20: 60 | D20: Living expense
B21: Tiền điện | C21: 786 | D21: Tiền nhà | F21: Category | G21: Estimated | H21: Actual
B22: WiFi | C22: 189 | D22: Tiền nhà | F22: Living expense | G22: 8000 | H22: =SUMIF(D2:D154, "=Living expense",C2:C172)+G15 -> 7814
B23: Tiền kết | C23: 20 | D23: Living expense
B24: Bò kho | C24: 80 | D24: Living expense | F24: Planned/actual spend per category of this month
B25: GO | C25: 603 | D25: Credit | F25: Category | G25: Estimated | H25: Actual | I25: Finalize | J25: Reserve
B26: Sách | C26: 220 | D26: Living expense | F26: Sum | G26: =SUM(G27:G109) -> 26700 | H26: =SUM(H27:H109) -> 25612 | J26: =SUM(J27:J109) -> 0
B27: Sữa | C27: 26 | D27: Living expense | F27: Tiền nhà | G27: 7200 | H27: =IFERROR(__xludf.DUMMYFUNCTION("SUMIF($D$2:$D$530, TO_TEXT(F27) ,$C$2:$C$530)"),7074.0) -> 7074 | I27: TRUE | J27: =IF(I27=TRUE,0,MAX(G27-H27,0)) -> 0
A28: 46237 | B28: Trà | C28: 18 | D28: Living expense | F28: Gonsa | G28: 5000 | H28: =IFERROR(__xludf.DUMMYFUNCTION("SUMIF($D$2:$D$530, TO_TEXT(F28) ,$C$2:$C$530)"),5000.0) -> 5000 | I28: TRUE | J28: =IF(I28=TRUE,0,MAX(G28-H28,0)) -> 0
B29: Trả tiền ăn cty | C29: 290 | D29: Living expense | F29: Help Ly | G29: 3000 | H29: =IFERROR(__xludf.DUMMYFUNCTION("SUMIF($D$2:$D$530, TO_TEXT(F29) ,$C$2:$C$530)"),3000.0) -> 3000 | I29: TRUE | J29: =IF(I29=TRUE,0,MAX(G29-H29,0)) -> 0
B30: Đặt vé phim | C30: =401-85-85-85-85 -> 61 | D30: Living expense | F30: Trả tín dụng | G30: 1000 | H30: =IFERROR(__xludf.DUMMYFUNCTION("SUMIF($D$2:$D$530, TO_TEXT(F30) ,$C$2:$C$530)"),1000.0) -> 1000 | I30: TRUE | J30: =IF(I30=TRUE,0,MAX(G30-H30,0)) -> 0
B31: Ăn chiều | C31: 50 | D31: Living expense | F31: Shinhan | G31: 1700 | H31: =IFERROR(__xludf.DUMMYFUNCTION("SUMIF($D$2:$D$530, TO_TEXT(F31) ,$C$2:$C$530)"),1700.0) -> 1700 | I31: TRUE | J31: =IF(I31=TRUE,0,MAX(G31-H31,0)) -> 0
B32: Sữa | C32: 26 | D32: Living expense | F32: Tiền ăn ba má | G32: 5000 | H32: =IFERROR(__xludf.DUMMYFUNCTION("SUMIF($D$2:$D$530, TO_TEXT(F32) ,$C$2:$C$530)"),4500.0) -> 4500 | I32: TRUE | J32: =IF(I32=TRUE,0,MAX(G32-H32,0)) -> 0
B33: Bột chiên | C33: 70 | D33: Living expense | F33: Sức khỏe | G33: 800 | H33: =IFERROR(__xludf.DUMMYFUNCTION("SUMIF($D$2:$D$530, TO_TEXT(F33) ,$C$2:$C$530)"),338.0) -> 338 | I33: TRUE | J33: =IF(I33=TRUE,0,MAX(G33-H33,0)) -> 0
A34: 46238 | B34: Trà | C34: 18 | D34: Living expense | F34: Trả Khang | G34: 2000 | H34: =IFERROR(__xludf.DUMMYFUNCTION("SUMIF($D$2:$D$530, TO_TEXT(F34) ,$C$2:$C$530)"),2000.0) -> 2000 | I34: TRUE | J34: =IF(I34=TRUE,0,MAX(G34-H34,0)) -> 0
B35: Sữa | C35: 14 | D35: Living expense | F35: Trả chị Diễm | G35: 1000 | H35: =IFERROR(__xludf.DUMMYFUNCTION("SUMIF($D$2:$D$530, TO_TEXT(F35) ,$C$2:$C$530)"),1000.0) -> 1000 | I35: TRUE | J35: =IF(I35=TRUE,0,MAX(G35-H35,0)) -> 0
B36: Cơm gà | C36: =107-42 -> 65 | D36: Living expense
B37: Nước rạp phim | C37: =79-20-20 -> 39 | D37: Living expense
B38: Sữa | C38: 26 | D38: Living expense
A39: 46239 | B39: Trà | C39: 18 | D39: Living expense
B40: Bò kho | C40: 40 | D40: Living expense
B41: Đổ xăng | C41: 50 | D41: Living expense
B42: Nước ngọt | C42: 24 | D42: Living expense
B43: Pizza | C43: 131 | D43: Living expense
A44: 46240 | B44: Ăn trưa | C44: 32 | D44: Living expense
B45: Nước ngọt | C45: 16 | D45: Living expense
B46: Cơm chiều | C46: 52 | D46: Living expense
A47: 46241 | B47: Cơm trưa | C47: 28 | D47: Living expense
B48: Trà | C48: 18 | D48: Living expense
B49: Bò kho | C49: 40 | D49: Living expense
B50: Ăn tối | C50: 53 | D50: Living expense
A51: 46242 | B51: Cơm | C51: 30 | D51: Living expense
B52: Sửa xe | C52: 80 | D52: Living expense
B53: Hớt tóc | C53: 249 | D53: Living expense
B54: Hủ tiếu | C54: 45 | D54: Living expense
B55: Bánh | C55: 100 | D55: Living expense
A56: 46243 | B56: Cơm | C56: 30 | D56: Living expense
B57: Sữa | C57: 28 | D57: Living expense
B58: Ăn cơm với Má | C58: 60 | D58: Living expense
A59: 46244 | B59: Trà | C59: 18 | D59: Living expense
B60: Cơm gà Lê Trang | C60: 41 | D60: Living expense
B61: Sữa | C61: 26 | D61: Living expense
B62: Pizza | C62: 164 | D62: Living expense
A63: 46245 | B63: Nước ngọt | C63: 16 | D63: Living expense
B64: Bò kho | C64: 40 | D64: Living expense
B65: Circle K | C65: 37 | D65: Living expense
A66: 46246 | B66: Trà | C66: 18 | D66: Living expense
B67: Bún bò | C67: 57 | D67: Living expense
B68: Circle K | C68: 37 | D68: Living expense
B69: Help Ly | C69: 1500 | D69: Help Ly
B70: Help Bảo | C70: 0 | D70: Support
B71: Ăn Há Cảo | C71: 50 | D71: Living expense
A72: 46247 | B72: Trà | C72: 18 | D72: Living expense
B73: YouTube Premium | C73: 79 | D73: Credit
B74: Cơm bò Lê Trang | C74: 53 | D74: Living expense
A75: 46248 | B75: Ăn trưa | C75: =218-22-49-49-49 -> 49 | D75: Living expense
B76: Nước ngọt | C76: 16 | D76: Living expense
B77: Bún bò | C77: 40 | D77: Living expense
B78: Đổ xăng | C78: 50 | D78: Living expense
B79: Bún nem nướng | C79: 25 | D79: Living expense
A80: 46249 | B80: Tiền nước | C80: 99 | D80: Tiền nhà
B81: Tiền nhà | C81: 6000 | D81: Tiền nhà
B82: Gonsa | C82: 5000 | D82: Gonsa
A83: 46250 | B83: Bún riêu | C83: 25 | D83: Living expense
B84: Cháo cho Ba | C84: 22 | D84: Parent
B85: Cơm | C85: 30 | D85: Living expense
B86: Bột chiên | C86: 27 | D86: Living expense
B87: Nước ngọt | C87: 24 | D87: Living expense
A88: 46251 | B88: Ăn trưa | C88: 32 | D88: Living expense
B89: Trà | C89: =18+19-19 -> 18 | D89: Living expense
B90: Fake chat | C90: 99 | D90: Credit
A91: 46253 | B91: Tiêu dùng | C91: 252 | D91: Living expense
B92: Grok | C92: 846 | D92: Credit
B93: Bánh bao | C93: 25 | D93: Special
B94: Vé xe | C94: 185 | D94: Special
B95: Nạp 4G cho Má | C95: 20 | D95: Special
A96: 46254 | B96: Ăn sáng | C96: 28 | D96: Special
B97: Cháo cho Ba | C97: 22 | D97: Special
B98: Claude Pro | C98: 597 | D98: Credit
A99: 46255 | B99: Xe ghép | C99: 190 | D99: Living expense
B100: Ăn trưa | C100: 27 | D100: Living expense
...

Sheet T72026
A1: DATE | B1: SPENT FOR | C1: AMOUNT | D1: TYPE | F1: DATE | G1: EARN BY | H1: AMOUNT
A2: 46202 | B2: Mua vé Supergirl | C2: =271-75-75 -> 121 | D2: Living expense | F2: 46202 | G2: Lương T6 + Dư T6 | H2: =24357+42 -> 24399
B3: Help Ly sinh hoạt | C3: 2000 | D3: Help Ly | F3: 46205 | G3: Lương Ba | H3: 5545
B4: Bún cá T6 | C4: 55 | D4: Living expense | F4: 46218 | G4: Bảo gởi Gonsa | H4: 2000
B5: Nước ngọt | C5: 16 | D5: Living expense | G5: Khang support | H5: 2000
B6: Milo | C6: 48 | D6: Living expense | F6: 46224 | G6: Phúc | H6: 500
B7: Cho Má | C7: 5000 | D7: Tiền ăn ba má | F7: 46227 | G7: Bảo support | H7: 500
B8: Cơm trưa | C8: 37 | D8: Living expense | F8: 46228 | G8: Bảo support | H8: 300
B9: Order gỏi cuốn | C9: =111-25-24 -> 62 | D9: Living expense | G9: Mà cho | H9: 300
A10: 46203 | B10: Klara and The Sun Book | C10: 183 | D10: Living expense | F10: 46229 | G10: Mà cho | H10: 100
B11: Nước bình | C11: 160 | D11: Tiền nhà | F11: 46230 | G11: Rút tín dụng | H11: 1000
B12: KFC | C12: 111 | D12: Living expense
A13: 46204 | B13: Shinhan | C13: 1700 | D13: Shinhan | F13: Total earn | G13: =SUM(H2:H12) -> 36644
B14: Nước ngọt | C14: 16 | D14: Living expense | F14: Total spent | G14: =SUMPRODUCT(((D2:D231<>"Credit")*(D2:D231<>"Quỹ Shinhan"))*C2:C231) + G15 -> 36533
B15: Order gỏi cuốn | C15: =147-25-32-32 -> 58 | D15: Living expense | F15: Untrack spent | G15: =2+223+16+6+36+2+77+284-89+37+4 -> 598
A16: 46205 | B16: Milo | C16: 16 | D16: Living expense | F16: Saving | G16: 0
B17: Trả tín dụng | C17: 3000 | D17: Trả tín dụng
B18: Internet | C18: 164 | D18: Tiền nhà | F18: Remaining | G18: =G13-G14-J26 -> 111
B19: Tiền điện | C19: 805 | D19: Tiền nhà | F19: Remaining (- liabilities) | G19: =G13-G14 -> 111
A20: 46206 | B20: Ăn trưa | C20: 38 | D20: Living expense
B21: Relax Coffee | C21: 18 | D21: Living expense | F21: Category | G21: Estimated | H21: Actual
B22: Bò kho | C22: 40 | D22: Living expense | F22: Living expense | G22: 8000 | H22: =SUMIF(D2:D154, "=Living expense",C2:C172)+G15 -> 7335
B23: Circle K | C23: 30 | D23: Living expense
A24: 46207 | B24: Ăn trưa | C24: 245 | D24: Living expense | F24: Planned/actual spend per category of this month
B25: Khám bệnh Ba Má | C25: =200+76+68 -> 344 | D25: Sức khỏe | F25: Category | G25: Estimated | H25: Actual | I25: Finalize | J25: Reserve
B26: Ăn cơm với Má | C26: 78 | D26: Living expense | F26: Sum | G26: =SUM(G27:G108) -> 24900 | H26: =SUM(H27:H108) -> 27327 | J26: =SUM(J27:J108) -> 0
A27: 46208 | B27: Pizza | C27: 149 | D27: Living expense | F27: Tiền nhà | G27: 7200 | H27: =IFERROR(__xludf.DUMMYFUNCTION("SUMIF($D$2:$D$530, TO_TEXT(F27) ,$C$2:$C$530)"),7448.0) -> 7448 | I27: TRUE | J27: =IF(I27=TRUE,0,MAX(G27-H27,0)) -> 0
B28: Circle K | C28: 58 | D28: Living expense | F28: Gonsa | G28: 3000 | H28: =IFERROR(__xludf.DUMMYFUNCTION("SUMIF($D$2:$D$530, TO_TEXT(F28) ,$C$2:$C$530)"),5000.0) -> 5000 | I28: TRUE | J28: =IF(I28=TRUE,0,MAX(G28-H28,0)) -> 0
B29: Bún đậu | C29: 109 | D29: Living expense | F29: Help Ly | G29: 3500 | H29: =IFERROR(__xludf.DUMMYFUNCTION("SUMIF($D$2:$D$530, TO_TEXT(F29) ,$C$2:$C$530)"),3650.0) -> 3650 | I29: TRUE | J29: =IF(I29=TRUE,0,MAX(G29-H29,0)) -> 0
B30: Sách | C30: 251 | D30: Buy | F30: Trả tín dụng | G30: 3000 | H30: =IFERROR(__xludf.DUMMYFUNCTION("SUMIF($D$2:$D$530, TO_TEXT(F30) ,$C$2:$C$530)"),3000.0) -> 3000 | I30: TRUE | J30: =IF(I30=TRUE,0,MAX(G30-H30,0)) -> 0
A31: 46209 | B31: Ăn sáng | C31: 20 | D31: Living expense | F31: Shinhan | G31: 1700 | H31: =IFERROR(__xludf.DUMMYFUNCTION("SUMIF($D$2:$D$530, TO_TEXT(F31) ,$C$2:$C$530)"),1700.0) -> 1700 | I31: TRUE | J31: =IF(I31=TRUE,0,MAX(G31-H31,0)) -> 0
B32: Ăn trưa | C32: 32 | D32: Living expense | F32: Tiền ăn ba má | G32: 5000 | H32: =IFERROR(__xludf.DUMMYFUNCTION("SUMIF($D$2:$D$530, TO_TEXT(F32) ,$C$2:$C$530)"),5000.0) -> 5000 | I32: TRUE | J32: =IF(I32=TRUE,0,MAX(G32-H32,0)) -> 0
B33: Nước ngọt | C33: 16 | D33: Living expense | F33: Sức khỏe | G33: 1500 | H33: =IFERROR(__xludf.DUMMYFUNCTION("SUMIF($D$2:$D$530, TO_TEXT(F33) ,$C$2:$C$530)"),1529.0) -> 1529 | I33: TRUE | J33: =IF(I33=TRUE,0,MAX(G33-H33,0)) -> 0
B34: Order gỏi cuốn | C34: =108-36-36 -> 36 | D34: Living expense
B35: GO | C35: 1133 | D35: Living expense
B36: Nước ngọt | C36: 26 | D36: Living expense
A37: 46210 | B37: Ăn trưa | C37: 32 | D37: Living expense
B38: Trà đường | C38: 18 | D38: Living expense
B39: Order cơm chiều | C39: =132-30-30 -> 72 | D39: Living expense
A40: 46211 | B40: Ăn trưa | C40: 32 | D40: Living expense
B41: Trà đường | C41: 18 | D41: Living expense
B42: Grok | C42: 846 | D42: Credit
B43: Order gỏi cuốn | C43: =177-44-31-40 -> 62 | D43: Living expense
B44: Thuốc | C44: 117 | D44: Living expense
A45: 46212 | B45: Ăn trưa | C45: 32 | D45: Living expense
B46: Trả tiền sủi cầu | C46: 20 | D46: Living expense
B47: Trà đường | C47: 18 | D47: Living expense
B48: Order cơm chiều | C48: =78-35 -> 43 | D48: Living expense
B49: Mua vé Phương Trang cho Má | C49: 185 | D49: Sức khỏe
B50: Circle K | C50: 43 | D50: Living expense
A51: 46213 | B51: Pizza ăn khuya | C51: 105 | D51: Living expense
B52: Ăn trưa | C52: 60 | D52: Living expense
B53: Ăn buffet với Huy | C53: 678 | D53: Credit
B54: Huy trả Buffet | C54: -340 | D54: Living expense
B55: Cho Má khám bệnh | C55: 1000 | D55: Sức khỏe
B56: Bánh bao | C56: 25 | D56: Living expense
B57: Coffee | C57: 35 | D57: Living expense
A58: 46214 | B58: Ăn sáng | C58: 45 | D58: Living expense
B59: Ăn trưa | C59: 30 | D59: Living expense
B60: Nước ngọt | C60: 30 | D60: Living expense
B61: Cháo | C61: 42 | D61: Living expense
B62: Help Bảo | C62: 450 | D62: Support
B63: Net | C63: =88+20 -> 108 | D63: Living expense
A64: 46215 | B64: Tiền nhà cho Ly | C64: 1650 | D64: Help Ly
B65: Bò né với Má | C65: 113 | D65: Living expense
B66: Jolibee | C66: 140 | D66: Living expense
B67: YouTube Premium | C67: 54 | D67: Credit
A68: 46216 | B68: Trà đường | C68: 18 | D68: Living expense
B69: Thuốc | C69: 22 | D69: Living expense
B70: Bánh | C70: 27 | D70: Living expense
B71: Ăn chiều | C71: 57 | D71: Living expense
B72: Uống nước | C72: =35+20 -> 55 | D72: Living expense
A73: 46217 | B73: Nước ngọt | C73: 16 | D73: Living expense
B74: Bún đậu | C74: 83 | D74: Living expense
A75: 46218 | B75: Tiền nước | C75: 119 | D75: Tiền nhà
B76: Tiền nhà T7 | C76: 6000 | D76: Tiền nhà
B77: Ăn cơm | C77: 32 | D77: Living expense
B78: Trà đường | C78: 18 | D78: Living expense
B79: Bảo trả | C79: -500 | D79: Support
B80: GS25 | C80: =50-12 -> 38 | D80: Living expense
B81: Bột chiên | C81: 68 | D81: Living expense
B82: Trả Gonsa | C82: 5000 | D82: Gonsa
A83: 46219 | B83: Trà đường | C83: 18 | D83: Living expense
B84: Cơm gà Kim | C84: 61 | D84: Living expense
A85: 46220 | B85: Bún bò | C85: 40 | D85: Living expense
B86: Cơm sườn | C86: 42 | D86: Living expense
A87: 46221 | B87: Ăn cơm trưa | C87: 30 | D87: Living expense
B88: Súp + Thuốc cho Má | C88: =12+49 -> 61 | D88: Living expense
B89: Lẩu cua | C89: 420 | D89: Living expense
A90: 46222 | B90: Ăn sáng | C90: 20 | D90: Living expense
B91: Súp + Thuốc cho Má | C91: =20+22 -> 42 | D91: Living expense
B92: Vé phim | C92: 441 | D92: Credit
B93: Ăn chiều | C93: 80 | D93: Living expense
B94: Discord Nitro | C94: 113 | D94: Buy
A95: 46223 | B95: Red Bull | C95: 16 | D95: Living expense
B96: Ăn chiều | C96: =89-35 -> 54 | D96: Living expense
A97: 46224 | B97: Vệ sinh máy giặt | C97: 200 | D97: Tiền nhà
B98: Red Bull | C98: 16 | D98: Living expense
B99: Cơm trưa | C99: 32 | D99: Living expense
B100: Mì | C100: 35 | D100: Living expense
...

Sheet T62026
A1: DATE | B1: SPENT FOR | C1: AMOUNT | D1: TYPE | F1: DATE | G1: EARN BY | H1: AMOUNT
A2: 46171 | B2: Cho Má | C2: 300 | D2: Living expense | F2: 46141 | G2: Lương T5 | H2: =24357 -> 24357
B3: Trả quỹ Shinhan | C3: 1000 | D3: Trả quỹ Shinhan | F3: 46177 | G3: Lương Ba | H3: 5545
B4: GS25 | C4: 16 | D4: Living expense | F4: 46178 | G4: Bảo trả Gonsa | H4: 1000
B5: Ăn trưa | C5: 32 | D5: Living expense | F5: 46180 | G5: Mượn quỹ Shinhan | H5: 2500
B6: Bún riêu cho Má | C6: 30 | D6: Parent | F6: 46188 | G6: Bảo gởi Gonsa | H6: 1500
B7: Circle K (khăn giấy, nước ngọt) | C7: 69 | D7: Living expense | F7: 46189 | G7: Gộp quỹ Shinhan | H7: =876+5850 -> 6726
B8: Trả Khang | C8: 2000 | D8: Trả Khang | G8: Futa hoàn tiền | H8: 864
B9: Trả tín dụng | C9: 3000 | D9: Trả tín dụng | F9: 46200 | G9: Bảo support | H9: 200
B10: Cho Má tiền ăn | C10: 5000 | D10: Tiền ăn ba má
A11: 46172 | B11: Xe ghép | C11: 190 | D11: Living expense
B12: Cơm Tuần Cường | C12: 27 | D12: Living expense
B13: Thùng xốp + gởi đồ cho Ly | C13: =120+280 -> 400 | D13: Support | F13: Total earn | G13: =SUM(H2:H12) -> 42692
B14: Bún bò | C14: 82 | D14: Living expense | F14: Total spent | G14: =SUMPRODUCT(((D2:D229<>"Credit")*(D2:D229<>"Quỹ Shinhan"))*C2:C229) + G15 -> 42650
B15: Taxi | C15: 96 | D15: Living expense | F15: Untrack spent | G15: =20+2+1749+36+146+122+124+119+52+75 -> 2445
B16: Nước | C16: 23 | D16: Living expense | F16: Saving | G16: 0
B17: Đồ chiên | C17: 50 | D17: Living expense
B18: Circle K | C18: 20 | D18: Living expense | F18: Remaining | G18: =G13-G14-J26 -> 42
A19: 46173 | B19: Ăn cơm trưa | C19: 30 | D19: Living expense | F19: Remaining (- liabilities) | G19: =G13-G14 -> 42
B20: Trà sữa | C20: 54 | D20: Living expense
B21: Đổ xăng | C21: 65 | D21: Living expense | F21: Category | G21: Estimated | H21: Actual
B22: Đổ xăng cho Ly | C22: 65 | D22: Support | F22: Living expense | G22: 8000 | H22: =SUMIF(D2:D152, "=Living expense",C2:C170)+G15 -> 10532
B23: GO | C23: 565 | D23: Credit
B24: Tiền kết | C24: 20 | D24: Living expense | F24: Planned/actual spend per category of this month
B25: Ăn chay | C25: 112 | D25: Living expense | F25: Category | G25: Estimated | H25: Actual | I25: Finalize | J25: Reserve
A26: 46174 | B26: GS25 | C26: 14 | D26: Living expense | F26: Sum | G26: =SUM(G27:G108) -> 25200 | H26: =SUM(H27:H108) -> 26789 | J26: =SUM(J27:J108) -> 0
B27: Order cơm chiều | C27: =108-36-36 -> 36 | D27: Living expense | F27: Tiền nhà | G27: 7000 | H27: =IFERROR(__xludf.DUMMYFUNCTION("SUMIF($D$2:$D$528, TO_TEXT(F27) ,$C$2:$C$528)"),6840.0) -> 6840 | I27: TRUE | J27: =IF(I27=TRUE,0,MAX(G27-H27,0)) -> 0
A28: 46175 | B28: Shinhan | C28: 1700 | D28: Shinhan | F28: Gonsa | G28: 3000 | H28: =IFERROR(__xludf.DUMMYFUNCTION("SUMIF($D$2:$D$528, TO_TEXT(F28) ,$C$2:$C$528)"),5000.0) -> 5000 | I28: TRUE | J28: =IF(I28=TRUE,0,MAX(G28-H28,0)) -> 0
B29: Tiền điện | C29: 990 | D29: Tiền nhà | F29: Trả Khang | G29: 2000 | H29: =IFERROR(__xludf.DUMMYFUNCTION("SUMIF($D$2:$D$528, TO_TEXT(F29) ,$C$2:$C$528)"),2000.0) -> 2000 | I29: TRUE | J29: =IF(I29=TRUE,0,MAX(G29-H29,0)) -> 0
B30: Party Rocket | C30: 231 | D30: Living expense | F30: Trả tín dụng | G30: 3000 | H30: =IFERROR(__xludf.DUMMYFUNCTION("SUMIF($D$2:$D$528, TO_TEXT(F30) ,$C$2:$C$528)"),3000.0) -> 3000 | I30: TRUE | J30: =IF(I30=TRUE,0,MAX(G30-H30,0)) -> 0
B31: Ăn chiều | C31: 442 | D31: Living expense | F31: Shinhan | G31: 1700 | H31: =IFERROR(__xludf.DUMMYFUNCTION("SUMIF($D$2:$D$528, TO_TEXT(F31) ,$C$2:$C$528)"),1700.0) -> 1700 | I31: TRUE | J31: =IF(I31=TRUE,0,MAX(G31-H31,0)) -> 0
B32: Circle K | C32: 92 | D32: Living expense | F32: Tiền ăn ba má | G32: 5000 | H32: =IFERROR(__xludf.DUMMYFUNCTION("SUMIF($D$2:$D$528, TO_TEXT(F32) ,$C$2:$C$528)"),5000.0) -> 5000 | I32: TRUE | J32: =IF(I32=TRUE,0,MAX(G32-H32,0)) -> 0
A33: 46176 | B33: Ăn trưa | C33: 32 | D33: Living expense | F33: Sức khỏe | G33: 1500 | H33: =IFERROR(__xludf.DUMMYFUNCTION("SUMIF($D$2:$D$528, TO_TEXT(F33) ,$C$2:$C$528)"),1249.0) -> 1249 | I33: TRUE | J33: =IF(I33=TRUE,0,MAX(G33-H33,0)) -> 0
B34: Nước ngọt | C34: 16 | D34: Living expense | F34: Trả quỹ Shinhan | G34: 1000 | H34: =IFERROR(__xludf.DUMMYFUNCTION("SUMIF($D$2:$D$528, TO_TEXT(F34) ,$C$2:$C$528)"),1000.0) -> 1000 | I34: TRUE | J34: =IF(I34=TRUE,0,MAX(G34-H34,0)) -> 0
B35: Order há cảo | C35: =183-61-61 -> 61 | D35: Living expense | F35: Trả quỹ Shinhan | G35: 1000 | H35: =IFERROR(__xludf.DUMMYFUNCTION("SUMIF($D$2:$D$528, TO_TEXT(F35) ,$C$2:$C$528)"),1000.0) -> 1000 | I35: TRUE | J35: =IF(I35=TRUE,0,MAX(G35-H35,0)) -> 0
B36: Ăn tối w/ Ly | C36: 96 | D36: Living expense
B37: Mua Aseprite tặng Ly (QP) | C37: 188 | D37: Credit
A38: 46177 | B38: Red Bull | C38: 24 | D38: Living expense
B39: Ăn chiều w/ Ly | C39: 60 | D39: Living expense
B40: Bánh tráng | C40: 37 | D40: Living expense
B41: Thuốc cho Ly | C41: 83 | D41: Support
B42: Ăn tối | C42: 56 | D42: Living expense
B43: Gởi má Khám bệnh | C43: 1000 | D43: Sức khỏe
A44: 46178 | B44: Ăn sáng (+ba, ly) | C44: 60 | D44: Living expense
B45: Lê Trang | C45: 83 | D45: Living expense
B46: Bột chiên | C46: 65 | D46: Living expense
A47: 46179 | B47: Vé xe | C47: 960 | D47: Quỹ Shinhan
B48: Tiền nhà cho Ly | C48: 3500 | D48: Quỹ Shinhan
B49: Khám bệnh cho Ba | C49: =100+76+73 -> 249 | D49: Sức khỏe
B50: 30Shine | C50: 389 | D50: Living expense
B51: Ăn bún chả | C51: 171 | D51: Living expense
B52: Chợ đêm | C52: =105+30+30+17 -> 182 | D52: Living expense
A53: 46180 | B53: Nước bình | C53: 160 | D53: Living expense
B54: Ăn chiều | C54: 30 | D54: Living expense
B55: Nước ngọt | C55: 12 | D55: Living expense
B56: Popeyes | C56: 108 | D56: Living expense
A57: 46181 | B57: Nước ngọt | C57: 16 | D57: Living expense
B58: Cacao | C58: 25 | D58: Living expense
B59: Bánh | C59: 38 | D59: Living expense
B60: Truyện Doraemon | C60: 88 | D60: Living expense
B61: Bò kho | C61: 40 | D61: Living expense
A62: 46182 | B62: Ăn tối | C62: 83 | D62: Living expense
B63: GS25 | C63: 16 | D63: Living expense
B64: Order ăn chiều | C64: =173-43-43-43-14 -> 30 | D64: Living expense
A65: 46183 | B65: Ăn sáng | C65: 20 | D65: Living expense
B66: Cà phê | C66: 17 | D66: Living expense
B67: Ăn tối w/ nhà | C67: 315 | D67: Living expense
B68: Truyện Doraemon | C68: 88 | D68: Living expense
B69: Gởi xe máy cho Ly | C69: 389 | D69: Quỹ Shinhan
B70: Circle K | C70: 26 | D70: Living expense
B71: WiFi | C71: 55 | D71: Living expense
A72: 46184 | B72: Ăn trưa | C72: 38 | D72: Living expense
B73: Nước ngọt | C73: 16 | D73: Living expense
B74: CellphoneS (tai nghe cho Ly, chống sốc) | C74: 902 | D74: Credit
B75: Jolibee | C75: =183+35 -> 218 | D75: Living expense
B76: Nước ngọt | C76: 15 | D76: Living expense
B77: Vé xe | C77: 370 | D77: Quỹ Shinhan
A78: 46185 | B78: Ăn trưa | C78: 30 | D78: Living expense
B79: Bột chiên | C79: 81 | D79: Living expense
B80: Thuốc say xe | C80: 70 | D80: Living expense
B81: Cho Má | C81: 1500 | D81: Parent
A82: 46186 | B82: Hủ tiếu | C82: 18 | D82: Living expense
B83: Circle K | C83: 94 | D83: Living expense
B84: Taxi ra bx | C84: 84 | D84: Living expense
B85: Khách sạn | C85: 100 | D85: Living expense
B86: Trạm dừng chân | C86: =164+32+29 -> 225 | D86: Living expense
B87: Nước ngọt | C87: 35 | D87: Living expense
B88: Ăn cơm chiều | C88: 120 | D88: Living expense
B89: Mua đồ cho Ly | C89: 1400 | D89: Quỹ Shinhan
B90: Bánh canh tối | C90: 60 | D90: Living expense
B91: Bách hóa Xanh | C91: 41 | D91: Living expense
B92: Khẩu trang | C92: 15 | D92: Living expense
B93: Gà rán | C93: 55 | D93: Living expense
B94: Tiền trọ | C94: 2500 | D94: Quỹ Shinhan
B95: Phí cầu đường | C95: 486 | D95: Quỹ Shinhan
B96: Cho Ly | C96: 1500 | D96: Quỹ Shinhan
A97: 46187 | B97: Đi Lâm Đồng | C97: 0 | D97: Living expense
A98: 46188 | B98: Đi Lâm Đồng | C98: 0 | D98: Living expense
B99: Tiền nhà | C99: 5850 | D99: Tiền nhà
A100: 46189 | B100: Gonsa | C100: 5000 | D100: Gonsa
...

Sheet T52026
A1: DATE | B1: SPENT FOR | C1: AMOUNT | D1: TYPE | F1: DATE | G1: EARN BY | H1: AMOUNT
A2: 46140 | B2: Milo | C2: 20 | D2: Living expense | F2: 46140 | G2: Lương T4 + dư cuối T4 | H2: ='T42026'!G18+26920 -> 26989
B3: Ăn trưa | C3: 27 | D3: Living expense | G3: Lương Ba | H3: 5550
B4: Cơm | C4: 61 | D4: Living expense | F4: 46141 | G4: Thầy tặng | H4: 2000
B5: Cho Má | C5: 5000 | D5: Parent | G5: Má gởi lại | H5: 1000
A6: 46141 | B6: Help Bảo | C6: 2000 | D6: Help Bảo | F6: 46164 | G6: Bảo trả Gonsa | H6: 1000
B7: Trả Khang | C7: 3000 | D7: Trả Khang | G7: Mượn Quỹ Shinhan | H7: 3820
B8: Trả tín dụng | C8: 3000 | D8: Trả tín dụng
B9: Ăn trưa | C9: 28 | D9: Living expense
B10: Nước ngọt | C10: 16 | D10: Living expense
B11: Ăn chiều | C11: =107+10 -> 117 | D11: Living expense
A12: 46142 | B12: Jolibee | C12: 110 | D12: Living expense
B13: Trả chị Diễm | C13: 1000 | D13: Trả chị Diễm | F13: Total earn | G13: =SUM(H2:H12) -> 40359
B14: Trả tín dụng | C14: 1000 | D14: Trả tín dụng | F14: Total spent | G14: =SUMPRODUCT(((D2:D230<>"Credit")*(D2:D230<>"Qũy Shinhan"))*C2:C230) + G15 -> 40359
B15: Mua máy cạo | C15: 525 | D15: Buy | F15: Untrack spent | G15: =1+245+383+38+92-37+1+77 -> 800
B16: Ăn tối | C16: =30+52 -> 82 | D16: Living expense | F16: Saving | G16: 0
A17: 46143 | B17: Ăn chiều | C17: =30+20 -> 50 | D17: Living expense
B18: Cháo cho Ba | C18: 17 | D18: Living expense | F18: Remaining | G18: =G13-G14-J26 -> 0
A19: 46144 | B19: Gởi Má khám bệnh | C19: 3000 | D19: Khám bệnh cho Má | F19: Remaining (- liabilities) | G19: =G13-G14 -> 0
B20: Ăn trưa | C20: 30 | D20: Living expense
B21: Circle K | C21: 14 | D21: Living expense | F21: Category | G21: Estimated | H21: Actual
B22: Cháo cho Ba | C22: 22 | D22: Living expense | F22: Living expense | G22: 8000 | H22: =SUMIF(D2:D153, "=Living expense",C2:C171)+G15 -> 7440
B23: Jolibee | C23: 85 | D23: Living expense
B24: Pizza | C24: 103 | D24: Living expense | F24: Planned/actual spend per category of this month
B25: Tiền điện | C25: =26+845 -> 871 | D25: Tiền nhà | F25: Category | G25: Estimated | H25: Actual | I25: Finalize | J25: Reserve
A26: 46145 | B26: Cơm cho Má | C26: 40 | D26: Living expense | F26: Sum | G26: =SUM(G27:G108) -> 25871 | H26: =SUM(H27:H108) -> 31116 | J26: =SUM(J27:J108) -> 0
B27: Salon | C27: 315 | D27: Living expense | F27: Tiền nhà | G27: 6871 | H27: =IFERROR(__xludf.DUMMYFUNCTION("SUMIF($D$2:$D$529, TO_TEXT(F27) ,$C$2:$C$529)"),6980.0) -> 6980 | I27: TRUE | J27: =IF(I27=TRUE,0,MAX(G27-H27,0)) -> 0
B28: Rửa xe | C28: 30 | D28: Living expense | F28: Gonsa | G28: 3000 | H28: =IFERROR(__xludf.DUMMYFUNCTION("SUMIF($D$2:$D$529, TO_TEXT(F28) ,$C$2:$C$529)"),5000.0) -> 5000 | I28: TRUE | J28: =IF(I28=TRUE,0,MAX(G28-H28,0)) -> 0
B29: Bách hóa Xanh | C29: 117 | D29: Living expense | F29: Trả Khang | G29: 3000 | H29: =IFERROR(__xludf.DUMMYFUNCTION("SUMIF($D$2:$D$529, TO_TEXT(F29) ,$C$2:$C$529)"),3000.0) -> 3000 | I29: TRUE | J29: =IF(I29=TRUE,0,MAX(G29-H29,0)) -> 0
B30: Tiền kết | C30: 20 | D30: Living expense | F30: Trả tín dụng | G30: 3000 | H30: =IFERROR(__xludf.DUMMYFUNCTION("SUMIF($D$2:$D$529, TO_TEXT(F30) ,$C$2:$C$529)"),4000.0) -> 4000 | I30: TRUE | J30: =IF(I30=TRUE,0,MAX(G30-H30,0)) -> 0
B31: Bột chiên | C31: 60 | D31: Living expense | F31: Parent | G31: 5000 | H31: =IFERROR(__xludf.DUMMYFUNCTION("SUMIF($D$2:$D$529, TO_TEXT(F31) ,$C$2:$C$529)"),5636.0) -> 5636 | I31: TRUE | J31: =IF(I31=TRUE,0,MAX(G31-H31,0)) -> 0
A32: 46146 | B32: Ăn khuya | C32: 80 | D32: Living expense | F32: Trả chị Diễm | G32: 1000 | H32: =IFERROR(__xludf.DUMMYFUNCTION("SUMIF($D$2:$D$529, TO_TEXT(F32) ,$C$2:$C$529)"),1500.0) -> 1500 | I32: TRUE | J32: =IF(I32=TRUE,0,MAX(G32-H32,0)) -> 0
B33: Ăn trưa | C33: 27 | D33: Living expense | F33: Khám bệnh cho Má | G33: 3000 | H33: =IFERROR(__xludf.DUMMYFUNCTION("SUMIF($D$2:$D$529, TO_TEXT(F33) ,$C$2:$C$529)"),3000.0) -> 3000 | I33: TRUE | J33: =IF(I33=TRUE,0,MAX(G33-H33,0)) -> 0
B34: Sữa milo | C34: 20 | D34: Living expense | F34: Help Bảo | G34: 1000 | H34: =IFERROR(__xludf.DUMMYFUNCTION("SUMIF($D$2:$D$529, TO_TEXT(F34) ,$C$2:$C$529)"),2000.0) -> 2000 | I34: TRUE | J34: =IF(I34=TRUE,0,MAX(G34-H34,0)) -> 0
B35: Bột chiên | C35: 54 | D35: Living expense
A36: 46147 | B36: Ăn trưa | C36: 38 | D36: Living expense
B37: Milo | C37: 20 | D37: Living expense
B38: Bún riêu cho Má | C38: 30 | D38: Parent
B39: Jolibee | C39: 96 | D39: Living expense
B40: Trả chị Diễm | C40: 500 | D40: Trả chị Diễm
A41: 46148 | B41: Ăn trưa | C41: 27 | D41: Living expense
B42: Nước ngọt | C42: 14 | D42: Living expense
B43: Bột chiên | C43: 54 | D43: Living expense
A44: 46149 | B44: Grok | C44: 846 | D44: Credit
B45: Ăn trưa | C45: 42 | D45: Living expense
B46: Bò kho | C46: 40 | D46: Living expense
B47: Bánh tráng | C47: 40 | D47: Living expense
A48: 46150 | B48: Ăn trưa | C48: 27 | D48: Living expense
B49: Milo | C49: 20 | D49: Living expense
B50: Jolibee | C50: 80 | D50: Living expense
B51: Bò kho | C51: 40 | D51: Parent
B52: Help Ly | C52: 500 | D52: Support
B53: Phim | C53: 105 | D53: Living expense
A54: 46151 | B54: Milo | C54: 59 | D54: Living expense
B55: Bánh | C55: 20 | D55: Living expense
B56: Cơm cho Má | C56: 40 | D56: Living expense
B57: Cơm | C57: 30 | D57: Living expense
B58: Bột chiên | C58: 73 | D58: Living expense
A59: 46152 | B59: Circle K | C59: 61 | D59: Living expense
B60: Ăn sáng | C60: 40 | D60: Living expense
B61: Donate | C61: 22 | D61: Living expense
B62: Ăn trưa | C62: 30 | D62: Living expense
B63: Tiền kết | C63: 10 | D63: Living expense
B64: Bún riêu | C64: 66 | D64: Living expense
B65: Circle K | C65: 58 | D65: Living expense
A66: 46153 | B66: Ăn khuya | C66: 57 | D66: Living expense
B67: Ăn trưa | C67: 27 | D67: Living expense
B68: Milo | C68: 20 | D68: Living expense
B69: Bánh tráng cho Má | C69: 20 | D69: Living expense
B70: Jolibee | C70: 100 | D70: Living expense
A71: 46154 | B71: YouTube | C71: 54 | D71: Credit
B72: Ăn tối | C72: =91-35 -> 56 | D72: Living expense
B73: Sao kê | C73: 11 | D73: Living expense
B74: Xem phim w/ Phúc | C74: =40+160+160+118 -> 478 | D74: Buy
A75: 46155 | B75: Ăn chiều | C75: =122-56 -> 66 | D75: Living expense
B76: Ăn | C76: 33 | D76: Living expense
A77: 46156 | B77: Ăn cơm trưa | C77: 28 | D77: Living expense
B78: GS25 | C78: 48 | D78: Living expense
B79: Đánh cầu | C79: =3+38 -> 41 | D79: Living expense
B80: Circle K | C80: =65 -> 65 | D80: Living expense
A81: 46157 | B81: Tiền nhà | C81: 6000 | D81: Tiền nhà
B82: Trả Cô Hai giùm A Bảo | C82: 5000 | D82: Qũy Shinhan
B83: Gonsa | C83: 5000 | D83: Gonsa
B84: Ăn Hào | C84: 106 | D84: Living expense
B85: Ăn vặt bến Ninh Kiều | C85: =10+30+40 -> 80 | D85: Living expense
A86: 46158 | B86: Hủ tiếu mức | C86: =145-92 -> 53 | D86: Living expense
B87: Đổ xăng | C87: 60 | D87: Living expense
B88: Ăn trưa | C88: =150-55 -> 95 | D88: Living expense
B89: Ăn chiều | C89: =126-62 -> 64 | D89: Living expense
B90: Cơm tối | C90: 42 | D90: Living expense
B91: Winmart+ (nước, bàn chải, bánh) | C91: 102 | D91: Living expense
B92: Nước Cần Thơ | C92: 109 | D92: Tiền nhà
A93: 46159 | B93: Trả cầu lông thứ 5 | C93: 33 | D93: Living expense
B94: Ăn chiều | C94: 30 | D94: Living expense
B95: Jolibee | C95: =66+10 -> 76 | D95: Living expense
A96: 46160 | B96: GS25 | C96: 15 | D96: Living expense
B97: Ăn chay với Má | C97: 64 | D97: Living expense
B98: Help Ly | C98: 500 | D98: Qũy Shinhan
B99: Mua vé Phương Trang | C99: 960 | D99: Qũy Shinhan
A100: 46161 | B100: Thuốc cho Má | C100: 85 | D100: Living expense
...

Sheet T42026
A1: DATE | B1: SPENT FOR | C1: AMOUNT | D1: TYPE | F1: DATE | G1: EARN BY | H1: AMOUNT
A2: 46111 | B2: Cơm gà Lê Trang | C2: =131-38-34 -> 59 | D2: Living expense | F2: 46111 | G2: Lương T3 + dư cuối T3 | H2: =24357+'T32026'!G18 -> 24646
B3: Help Nhi | C3: 100 | D3: Living expense | G3: Má gởi | H3: 50
B4: Trả Tú pizza, nước | C4: 82 | D4: Living expense | F4: 46116 | G4: Lương Ba | H4: 5590
B5: Gym | C5: 30 | D5: Living expense | F5: 46129 | G5: Khang help | H5: 1000
B6: Bún riêu | C6: 25 | D6: Living expense | F6: 46130 | G6: Bảo trả | H6: 500
B7: Trả tín dụng | C7: 2500 | D7: Trả tín dụng | F7: 46134 | G7: Bảo trả | H7: 500
B8: Trả Khang | C8: 3000 | D8: Trả Khang | F8: 46136 | G8: Thầy Thái gởi thuế | H8: 3000
B9: Cho Má | C9: 4000 | D9: Parent | F9: 46137 | G9: Khang help | H9: 1000
A10: 46112 | B10: Cà phê | C10: 22 | D10: Living expense
B11: Order gỏi cuốn | C11: =147-35-42-35 -> 35 | D11: Living expense
B12: Siêu thị | C12: 834 | D12: Living expense
B13: Texas | C13: 123 | D13: Living expense | F13: Total earn | G13: =SUM(H2:H12) -> 36286
B14: Cơm trưa | C14: 38 | D14: Living expense | F14: Total spent | G14: =SUMIF(D2:D228, "<>Credit", C2:C536) + G15 -> 36217
B15: Trả chị Diễm | C15: 1000 | D15: Trả chị Diễm | F15: Untrack spent | G15: =282+43-71+42+3+7+170 -> 476
A16: 46113 | B16: GS25 | C16: 15 | D16: Living expense | F16: Saving | G16: 0
B17: Cơm | C17: 38 | D17: Living expense
B18: Order cơm gà | C18: =179-33-44-33-35 -> 34 | D18: Living expense | F18: Remaining | G18: =G13-G14-J26 -> 69
B19: Kem | C19: 40 | D19: Living expense | F19: Remaining (- liabilities) | G19: =G13-G14 -> 69
A20: 46114 | B20: GS25 | C20: 15 | D20: Living expense
B21: Cơm trưa | C21: 38 | D21: Living expense | F21: Category | G21: Estimated | H21: Actual
B22: Tiền điện | C22: 497 | D22: Tiền nhà | F22: Living expense | G22: 8000 | H22: =SUMIF(D2:D151, "=Living expense",C2:C169)+G15 -> 9287
B23: Tiền kết | C23: 13 | D23: Living expense
B24: Jolibee | C24: 110 | D24: Living expense | F24: Planned/actual spend per category of this month
B25: Đổ xăng | C25: 50 | D25: Living expense | F25: Category | G25: Estimated | H25: Actual | I25: Finalize | J25: Reserve
A26: 46115 | B26: Help Ly | C26: 1000 | D26: Living expense | F26: Sum | G26: =SUM(G27:G107) -> 20000 | H26: =SUM(H27:H107) -> 23577 | J26: =SUM(J27:J107) -> 0
B27: Ăn trưa | C27: 35 | D27: Living expense | F27: Tiền nhà | G27: 6500 | H27: =IFERROR(__xludf.DUMMYFUNCTION("SUMIF($D$2:$D$527, TO_TEXT(F27) ,$C$2:$C$527)"),6606.0) -> 6606 | I27: TRUE | J27: =IF(I27=TRUE,0,MAX(G27-H27,0)) -> 0
B28: GS25 | C28: 15 | D28: Living expense | F28: Gonsa | G28: 3000 | H28: =IFERROR(__xludf.DUMMYFUNCTION("SUMIF($D$2:$D$527, TO_TEXT(F28) ,$C$2:$C$527)"),5000.0) -> 5000 | I28: TRUE | J28: =IF(I28=TRUE,0,MAX(G28-H28,0)) -> 0
B29: Ăn tối | C29: 114 | D29: Living expense | F29: Trả Khang | G29: 3000 | H29: =IFERROR(__xludf.DUMMYFUNCTION("SUMIF($D$2:$D$527, TO_TEXT(F29) ,$C$2:$C$527)"),3000.0) -> 3000 | I29: TRUE | J29: =IF(I29=TRUE,0,MAX(G29-H29,0)) -> 0
B30: FShare | C30: 90 | D30: Living expense | F30: Trả tín dụng | G30: 2500 | H30: =IFERROR(__xludf.DUMMYFUNCTION("SUMIF($D$2:$D$527, TO_TEXT(F30) ,$C$2:$C$527)"),2500.0) -> 2500 | I30: TRUE | J30: =IF(I30=TRUE,0,MAX(G30-H30,0)) -> 0
B31: Circle K | C31: 70 | D31: Living expense | F31: Parent | G31: 4000 | H31: =IFERROR(__xludf.DUMMYFUNCTION("SUMIF($D$2:$D$527, TO_TEXT(F31) ,$C$2:$C$527)"),4971.0) -> 4971 | I31: TRUE | J31: =IF(I31=TRUE,0,MAX(G31-H31,0)) -> 0
A32: 46116 | B32: Cơm | C32: 30 | D32: Living expense | F32: Trả chị Diễm | G32: 1000 | H32: =IFERROR(__xludf.DUMMYFUNCTION("SUMIF($D$2:$D$527, TO_TEXT(F32) ,$C$2:$C$527)"),1500.0) -> 1500 | I32: TRUE | J32: =IF(I32=TRUE,0,MAX(G32-H32,0)) -> 0
B33: Hớt tóc | C33: 235 | D33: Living expense
B34: Phim | C34: 145 | D34: Living expense
B35: Texas | C35: 119 | D35: Living expense
B36: Trả chị Diễm | C36: 500 | D36: Trả chị Diễm
A37: 46117 | B37: Tiền kết | C37: 20 | D37: Living expense
B38: Ăn tối | C38: 110 | D38: Living expense
A39: 46118 | B39: Remote | C39: 200 | D39: Tiền nhà
B40: Bún đậu | C40: 107 | D40: Living expense
B41: Winmart+ | C41: 234 | D41: Living expense
A42: 46119 | B42: Cà phê | C42: 18 | D42: Living expense
B43: Jolibee | C43: 113 | D43: Living expense
A44: 46120 | B44: Ăn trưa | C44: 27 | D44: Living expense
B45: Cà phê | C45: 18 | D45: Living expense
B46: Order súp | C46: =140-27-27-27 -> 59 | D46: Living expense
B47: Kem | C47: 30 | D47: Living expense
A48: 46121 | B48: Ăn trưa | C48: 27 | D48: Living expense
B49: Cà phê | C49: 18 | D49: Living expense
B50: Order | C50: 0 | D50: Living expense
B51: Order | C51: =151-38-35-32 -> 46 | D51: Living expense
A52: 46122 | B52: Ăn trưa | C52: 27 | D52: Living expense
B53: Cà phê | C53: 18 | D53: Living expense
B54: Đổ xăng | C54: 55 | D54: Living expense
B55: Hủ tiếu chay | C55: 64 | D55: Living expense
B56: Circle K | C56: 95 | D56: Living expense
B57: Resource pack | C57: 178 | D57: Credit
A58: 46123 | B58: Cơm niêu | C58: 170 | D58: Living expense
B59: Cây lau nhà | C59: 130 | D59: Living expense
B60: Jolibee | C60: 101 | D60: Living expense
B61: Khám bênh cho Ba | C61: 221 | D61: Parent
A62: 46124 | B62: Hớt tóc cho Ba | C62: 40 | D62: Living expense
B63: Ăn chiều | C63: 132 | D63: Living expense
A64: 46125 | B64: Ăn trưa | C64: 38 | D64: Living expense
B65: Cà phê | C65: 18 | D65: Living expense
B66: Order cơm gà | C66: =123-35-35 -> 53 | D66: Living expense
A67: 46126 | B67: Ăn trưa | C67: 27 | D67: Living expense
B68: Cà phê | C68: 18 | D68: Living expense
B69: Order cơm gà | C69: =281-54-49-33-33-54-11 -> 47 | D69: Living expense
B70: Thuốc | C70: 293 | D70: Living expense
B71: Trà sữa | C71: 52 | D71: Living expense
A72: 46127 | B72: Cà phê | C72: 18 | D72: Living expense
B73: Tiền nhà | C73: 5800 | D73: Tiền nhà
B74: Gonsa | C74: 5000 | D74: Gonsa
B75: Order gỏi cuốn | C75: =163-23-28-17-28-11-28 -> 28 | D75: Living expense
B76: Kem | C76: 40 | D76: Living expense
A77: 46128 | B77: Xin lễ | C77: 200 | D77: Living expense
B78: Nước ngọt | C78: 16 | D78: Living expense
B79: Order cơm gà | C79: =170-49-56-13 -> 52 | D79: Living expense
B80: Há cảo | C80: 58 | D80: Living expense
A81: 46129 | B81: Tiền nước | C81: 109 | D81: Tiền nhà
B82: Ăn trưa | C82: 27 | D82: Living expense
B83: Cà phê | C83: 22 | D83: Living expense
B84: Help Ly | C84: 1000 | D84: Support
B85: Kem | C85: 20 | D85: Living expense
A86: 46130 | B86: Ăn trưa | C86: 50 | D86: Living expense
B87: Nước | C87: 12 | D87: Living expense
B88: Kem | C88: 40 | D88: Living expense
B89: Trả party Rocket | C89: 295 | D89: Living expense
A90: 46131 | B90: Trả đồ nướng | C90: 211 | D90: Living expense
B91: Nước bình | C91: 140 | D91: Living expense
B92: Sinh tố | C92: 63 | D92: Living expense
B93: Sửa xe | C93: 70 | D93: Living expense
B94: Ăn chiều | C94: 64 | D94: Living expense
B95: Đổ xăng | C95: 60 | D95: Living expense
B96: Tiền kết | C96: 20 | D96: Living expense
B97: Bách hóa Xanh | C97: 103 | D97: Living expense
A98: 46132 | B98: Cà phê | C98: 18 | D98: Living expense
B99: Thuốc cho Má | C99: 10 | D99: Living expense
B100: Jolibee | C100: 110 | D100: Living expense
...

Sheet T32026
A1: DATE | B1: SPENT FOR | C1: AMOUNT | D1: TYPE | F1: DATE | G1: EARN BY | H1: AMOUNT
A2: 46080 | B2: ShopeeFood | C2: 0 | D2: Living expense | F2: 46080 | G2: Lương T2 + dư cuối T1 | H2: =57+24357+146-200 -> 24360
B3: Ăn cơm trưa | C3: 50 | D3: Living expense | G3: A Trung lì xì | H3: 200
B4: Ăn cơm chiều | C4: 60 | D4: Living expense | F4: 46081 | G4: Shopee hoàn tiền | H4: 281
B5: Cho Má | C5: 5000 | D5: Parent | F5: 46084 | G5: Papaya hoàn tiền | H5: 3150
B6: Bò kho | C6: 80 | D6: Living expense | F6: 46086 | G6: Lương của Ba | H6: 5545
B7: Thuốc | C7: 183 | D7: Living expense | F7: 46096 | G7: Khang support | H7: 3000
B8: Circle K | C8: 182 | D8: Living expense | F8: 46102 | G8: Khang support | H8: 3000
B9: Help Ly | C9: 500 | D9: Support | G9: Bảo trả | H9: =500+1300 -> 1800
A10: 46081 | B10: Cơm niêu | C10: 205 | D10: Living expense | F10: 46108 | G10: Bảo support | H10: 200
B11: LEGO | C11: 938 | D11: Living expense
B12: Trả tín dung | C12: 4292 | D12: Trả tín dụng
B13: Trả Khang | C13: 2945 | D13: Trả Khang | F13: Total earn | G13: =SUM(H2:H12) -> 41536
B14: Siêu thị | C14: =50+180+620+590 -> 1440 | D14: Living expense | F14: Total spent | G14: =SUMIF(D2:D228, "<>Credit", C2:C536) + G15 -> 41247
B15: Mua quạt | C15: 390 | D15: Living expense | F15: Untrack spent | G15: =69 -> 69
B16: Trả chị Diễm | C16: 2000 | D16: Trả chị Diễm | F16: Saving | G16: 0
A17: 46082 | B17: Đổ xăng | C17: 50 | D17: Living expense
B18: 30Shine | C18: 459 | D18: Living expense | F18: Remaining | G18: =G13-G14-J26 -> 289
B19: Tiền kết | C19: 20 | D19: Living expense | F19: Remaining (- liabilities) | G19: =G13-G14 -> 289
B20: Hot dog | C20: 30 | D20: Living expense
B21: Netflix | C21: 273 | D21: Living expense | F21: Category | G21: Estimated | H21: Actual
A22: 46083 | B22: Sữa milo | C22: 20 | D22: Living expense | F22: Living expense | G22: 8000 | H22: =SUMIF(D2:D151, "=Living expense",C2:C169)+G15 -> 10930
B23: Order há cảo | C23: 73 | D23: Living expense
A24: 46084 | B24: Tiền điện Trà Vinh | C24: 19 | D24: Tiền nhà | F24: Planned/actual spend per category of this month
B25: Tiền điện Cần Thơ | C25: 312 | D25: Tiền nhà | F25: Category | G25: Estimated | H25: Actual | I25: Finalize | J25: Reserve
B26: GS25 | C26: 18 | D26: Living expense | F26: Sum | G26: =SUM(G27:G107) -> 23737 | H26: =SUM(H27:H107) -> 29717 | J26: =SUM(J27:J107) -> 0
B27: Ăn tối với Má | C27: 235 | D27: Living expense | F27: Tiền nhà | G27: 6500 | H27: =IFERROR(__xludf.DUMMYFUNCTION("SUMIF($D$2:$D$527, TO_TEXT(F27) ,$C$2:$C$527)"),6431.0) -> 6431 | I27: TRUE | J27: =IF(I27=TRUE,0,MAX(G27-H27,0)) -> 0
B28: Order cơm ếch | C28: =145-45-50 -> 50 | D28: Living expense | F28: Gonsa | G28: 3000 | H28: =IFERROR(__xludf.DUMMYFUNCTION("SUMIF($D$2:$D$527, TO_TEXT(F28) ,$C$2:$C$527)"),5000.0) -> 5000 | I28: TRUE | J28: =IF(I28=TRUE,0,MAX(G28-H28,0)) -> 0
A29: 46085 | B29: Ăn trưa | C29: 45 | D29: Living expense | F29: Trả Khang | G29: 2945 | H29: =IFERROR(__xludf.DUMMYFUNCTION("SUMIF($D$2:$D$527, TO_TEXT(F29) ,$C$2:$C$527)"),2945.0) -> 2945 | I29: TRUE | J29: =IF(I29=TRUE,0,MAX(G29-H29,0)) -> 0
B30: GS25 | C30: 10 | D30: Living expense | F30: Trả tín dụng | G30: 4292 | H30: =IFERROR(__xludf.DUMMYFUNCTION("SUMIF($D$2:$D$527, TO_TEXT(F30) ,$C$2:$C$527)"),4292.0) -> 4292 | I30: TRUE | J30: =IF(I30=TRUE,0,MAX(G30-H30,0)) -> 0
B31: Jolibee | C31: 103 | D31: Living expense | F31: Parent | G31: 5000 | H31: =IFERROR(__xludf.DUMMYFUNCTION("SUMIF($D$2:$D$527, TO_TEXT(F31) ,$C$2:$C$527)"),9049.0) -> 9049 | I31: TRUE | J31: =IF(I31=TRUE,0,MAX(G31-H31,0)) -> 0
A32: 46086 | B32: Thuốc | C32: 41 | D32: Living expense | F32: Trả chị Diễm | G32: 2000 | H32: =IFERROR(__xludf.DUMMYFUNCTION("SUMIF($D$2:$D$527, TO_TEXT(F32) ,$C$2:$C$527)"),2000.0) -> 2000 | I32: TRUE | J32: =IF(I32=TRUE,0,MAX(G32-H32,0)) -> 0
B33: GS25 | C33: 38 | D33: Living expense
B34: Mua đồ lăn lông áo | C34: 118 | D34: Living expense
B35: Bún riêu | C35: 25 | D35: Living expense
B36: Sandwich | C36: 31 | D36: Living expense
A37: 46087 | B37: Minecraft cards | C37: 232 | D37: Living expense
B38: Ăn trưa | C38: =90-30-30 -> 30 | D38: Living expense
B39: GS25 | C39: 43 | D39: Living expense
B40: Order há cáo | C40: =172-30-30-23-46 -> 43 | D40: Living expense
B41: Circle K | C41: 81 | D41: Living expense
B42: Winmart+ | C42: 237 | D42: Living expense
A43: 46088 | B43: Cơm niêu | C43: 160 | D43: Living expense
B44: GO | C44: =286+50+100 -> 436 | D44: Living expense
B45: Order shopee | C45: 35 | D45: Living expense
A46: 46089 | B46: Đổ xăng | C46: 65 | D46: Living expense
B47: Circle K | C47: 30 | D47: Living expense
B48: TH True Milk | C48: 22 | D48: Living expense
B49: Tiền kết | C49: 20 | D49: Living expense
B50: Bún riêu | C50: 25 | D50: Living expense
A51: 46090 | B51: GS25 | C51: 12 | D51: Living expense
B52: Đồ chiên | C52: 40 | D52: Living expense
A53: 46091 | B53: GS25 | C53: 68 | D53: Living expense
B54: Jolibee | C54: 60 | D54: Living expense
B55: Circle K | C55: 104 | D55: Living expense
A56: 46092 | B56: GS25 | C56: 15 | D56: Living expense
B57: Order há cảo | C57: =111-35-35 -> 41 | D57: Living expense
B58: Circle K | C58: 53 | D58: Living expense
A59: 46093 | B59: Hủ tiếu | C59: 65 | D59: Living expense
B60: Circle K | C60: 48 | D60: Living expense
A61: 46094 | B61: Ăn trưa | C61: 47 | D61: Living expense
B62: Cà phê | C62: 17 | D62: Living expense
B63: Order cơm | C63: =126-35-40 -> 51 | D63: Living expense
A64: 46095 | B64: Pizza | C64: 215 | D64: Living expense
B65: Patreon | C65: 137 | D65: Credit
B66: Hàu | C66: 260 | D66: Living expense
B67: Nươc ngọt | C67: 30 | D67: Living expense
B68: Khám bệnh cho Ba | C68: =100+66+74 -> 240 | D68: Living expense
B69: Nước Cần Thơ | C69: 100 | D69: Tiền nhà
B70: AI | C70: 25 | D70: Living expense
A71: 46096 | B71: Sinh tố | C71: 33 | D71: Living expense
B72: Tiền nhà | C72: 6000 | D72: Tiền nhà
B73: Tiền kết | C73: 10 | D73: Living expense
B74: Bún riêu | C74: 54 | D74: Living expense
B75: Đổ xăng | C75: 60 | D75: Living expense
B76: Gonsa | C76: 5000 | D76: Gonsa
B77: Vé xe | C77: 495 | D77: Credit
A78: 46097 | B78: GS25 | C78: 10 | D78: Living expense
B79: Cơm gà Kim | C79: 56 | D79: Living expense
A80: 46098 | B80: GS25 | C80: 42 | D80: Living expense
B81: Há cảo | C81: =80-37 -> 43 | D81: Living expense
B82: Circle K | C82: 40 | D82: Living expense
B83: Jolibee | C83: 48 | D83: Living expense
A84: 46099 | B84: GS25 | C84: 46 | D84: Living expense
B85: Jolibee | C85: 60 | D85: Living expense
B86: Súp | C86: 12 | D86: Living expense
A87: 46100 | B87: GS25 | C87: 15 | D87: Living expense
B88: Ăn trưa | C88: 40 | D88: Living expense
B89: Circle K | C89: 66 | D89: Living expense
B90: Kem | C90: 20 | D90: Living expense
A91: 46101 | B91: Cơm niêu | C91: 155 | D91: Living expense
B92: Circle K | C92: 75 | D92: Living expense
B93: Bánh xèo | C93: 154 | D93: Living expense
B94: Bách hóa xanh | C94: 93 | D94: Living expense
A95: 46102 | B95: Cháo | C95: 125 | D95: Living expense
B96: Nhà nghỉ | C96: 180 | D96: Parent
B97: Viện phí BV Tâm Anh | C97: =3000+1705 -> 4705 | D97: Parent
B98: Bảo lãnh | C98: -2336 | D98: Parent
B99: Cơm phần | C99: 120 | D99: Living expense
B100: Trạm dừng chân | C100: =45+25 -> 70 | D100: Living expense
...

Sheet T22026
A1: DATE | B1: SPENT FOR | C1: AMOUNT | D1: TYPE | F1: DATE | G1: EARN BY | H1: AMOUNT
A2: 46051 | B2: Trà | C2: 12 | D2: Living expense | F2: 46051 | G2: Lương T1 | H2: =21691+65 -> 21756
B3: Ăn chiều | C3: 65 | D3: Living expense | F3: 46053 | G3: JICA Bonus | H3: 4000
B4: Cho Má | C4: 3000 | D4: Cho Má + lì xì | F4: 46054 | G4: Bảo trả | H4: 300
A5: 46052 | B5: Ăn trưa quán nước | C5: 0 | D5: Living expense | F5: 46058 | G5: Lương thưởng | H5: 21235
B6: Đám cưới anh Nghĩa | C6: 500 | D6: Đám cưới | F6: 46060 | G6: Lương Ba | H6: 5545
B7: Jolibee | C7: 83 | D7: Living expense | F7: 46064 | G7: Rút tín dụng | H7: 12000
B8: Trả tín dụng | C8: 2500 | D8: Tín dụng | F8: 46068 | G8: Bảo gởi | H8: 1500
B9: Trả máy hút bụi | C9: 500 | D9: Trả máy hút bụi | F9: 46069 | G9: Bạn của Ba giúp | H9: 1800
B10: Giúp chi hội | C10: 1000 | D10: Giúp chi hội | F10: 46070 | G10: Lì xì | H10: 100
B11: Trả Khang | C11: 1000 | D11: Trả Khang | F11: 46074 | G11: Rút tín dụng | H11: 1500
A12: 46053 | B12: Khám bệnh cho Má | C12: =120+2000+539+640 -> 3299 | D12: Khám bệnh cho Má | F12: 46076 | G12: A Ngộ lì xì | H12: 100
B13: Ăn phở | C13: 100 | D13: Living expense | F13: Total earn | G13: =SUM(H2:H12) -> 69836
B14: Bún đậu | C14: 109 | D14: Living expense | F14: Total spent | G14: =SUMIF(D2:D221, "<>Credit", C2:C529) + G15 -> 69779
B15: Bánh tráng | C15: 65 | D15: Living expense | F15: Untrack spent | G15: =5+359+57-37+5+541+41 -> 971
B16: Winmart+ | C16: 548 | D16: Living expense | F16: Saving | G16: 0
B17: Sâm bổ | C17: 110 | D17: Living expense
B18: Trả chị Diễm | C18: 5000 | D18: Trả chị Diễm | F18: Remaining | G18: =G13-G14-J26 -> 57
B19: Dây đồng hồ | C19: 26 | D19: Living expense | F19: Remaining (- liabilities) | G19: =G13-G14 -> 57
A20: 46054 | B20: Help Nguyệt | C20: 3000 | D20: Support
B21: Cơm niêu | C21: 205 | D21: Living expense | F21: Category | G21: Estimated | H21: Actual
B22: Đổ xăng | C22: 50 | D22: Living expense | F22: Living expense | G22: 8000 | H22: =SUMIF(D2:D144, "=Living expense",C2:C162)+G15 -> 12898
B23: Winmart | C23: 572 | D23: Credit
B24: Minecraft mod | C24: 219 | D24: Living expense | F24: Planned/actual spend per category of this month
B25: Ăn tối | C25: 60 | D25: Living expense | F25: Category | G25: Estimated | H25: Actual | I25: Finalize | J25: Reserve
A26: 46055 | B26: Nước | C26: 7 | D26: Living expense | F26: Sum | G26: =SUM(G27:G104) -> 32620 | H26: =SUM(H27:H104) -> 50662 | J26: =SUM(J27:J104) -> 0
B27: Điện Trà Vinh | C27: 15 | D27: Tiền nhà | F27: Tiền nhà | G27: 6400 | H27: =IFERROR(__xludf.DUMMYFUNCTION("SUMIF($D$2:$D$520, TO_TEXT(F27) ,$C$2:$C$520)"),6424.0) -> 6424 | I27: TRUE | J27: =IF(I27=TRUE,0,MAX(G27-H27,0)) -> 0
B28: Điện Cần Thơ | C28: 300 | D28: Tiền nhà | F28: Cho Má + lì xì | G28: 7000 | H28: =IFERROR(__xludf.DUMMYFUNCTION("SUMIF($D$2:$D$520, TO_TEXT(F28) ,$C$2:$C$520)"),7330.0) -> 7330 | I28: TRUE | J28: =IF(I28=TRUE,0,MAX(G28-H28,0)) -> 0
B29: Trả a Khoa | C29: 16 | D29: Living expense | F29: Trả chị Diễm | G29: 5000 | H29: =IFERROR(__xludf.DUMMYFUNCTION("SUMIF($D$2:$D$520, TO_TEXT(F29) ,$C$2:$C$520)"),5000.0) -> 5000 | I29: TRUE | J29: =IF(I29=TRUE,0,MAX(G29-H29,0)) -> 0
B30: Trả Toàn | C30: 33 | D30: Living expense | F30: Gonsa | G30: 4500 | H30: =IFERROR(__xludf.DUMMYFUNCTION("SUMIF($D$2:$D$520, TO_TEXT(F30) ,$C$2:$C$520)"),5000.0) -> 5000 | I30: TRUE | J30: =IF(I30=TRUE,0,MAX(G30-H30,0)) -> 0
B31: Ăn chiều | C31: 52 | D31: Living expense | F31: Tín dụng | G31: 2500 | H31: =IFERROR(__xludf.DUMMYFUNCTION("SUMIF($D$2:$D$520, TO_TEXT(F31) ,$C$2:$C$520)"),17500.0) -> 17500 | I31: TRUE | J31: =IF(I31=TRUE,0,MAX(G31-H31,0)) -> 0
A32: 46056 | B32: Ăn trưa | C32: 30 | D32: Living expense | F32: Lì xì | G32: 2000 | H32: =IFERROR(__xludf.DUMMYFUNCTION("SUMIF($D$2:$D$520, TO_TEXT(F32) ,$C$2:$C$520)"),2300.0) -> 2300 | I32: TRUE | J32: =IF(I32=TRUE,0,MAX(G32-H32,0)) -> 0
A33: 46057 | B33: KitKat | C33: 24 | D33: Living expense | F33: Khám bệnh cho Ba | G33: 1000 | H33: =IFERROR(__xludf.DUMMYFUNCTION("SUMIF($D$2:$D$520, TO_TEXT(F33) ,$C$2:$C$520)"),89.0) -> 89 | I33: TRUE | J33: =IF(I33=TRUE,0,MAX(G33-H33,0)) -> 0
B34: Order há cáo | C34: =184-33-33-37-37 -> 44 | D34: Living expense | F34: Trả Khang | G34: 1000 | H34: =IFERROR(__xludf.DUMMYFUNCTION("SUMIF($D$2:$D$520, TO_TEXT(F34) ,$C$2:$C$520)"),1000.0) -> 1000 | I34: TRUE | J34: =IF(I34=TRUE,0,MAX(G34-H34,0)) -> 0
B35: Jolibee | C35: 83 | D35: Living expense | F35: Giúp chi hội | G35: 1000 | H35: =IFERROR(__xludf.DUMMYFUNCTION("SUMIF($D$2:$D$520, TO_TEXT(F35) ,$C$2:$C$520)"),1000.0) -> 1000 | I35: TRUE | J35: =IF(I35=TRUE,0,MAX(G35-H35,0)) -> 0
B36: WiFi | C36: 720 | D36: Wifi | F36: Wifi | G36: 720 | H36: =IFERROR(__xludf.DUMMYFUNCTION("SUMIF($D$2:$D$520, TO_TEXT(F36) ,$C$2:$C$520)"),720.0) -> 720 | I36: TRUE | J36: =IF(I36=TRUE,0,MAX(G36-H36,0)) -> 0
A37: 46058 | B37: Sữa trái cây | C37: 12 | D37: Living expense | F37: Trả máy hút bụi | G37: 500 | H37: =IFERROR(__xludf.DUMMYFUNCTION("SUMIF($D$2:$D$520, TO_TEXT(F37) ,$C$2:$C$520)"),500.0) -> 500 | I37: TRUE | J37: =IF(I37=TRUE,0,MAX(G37-H37,0)) -> 0
B38: Bách hóa Xanh | C38: 40 | D38: Living expense | F38: Phụ mua đồ ăn nhà mợ Hai | G38: 500 | H38: =IFERROR(__xludf.DUMMYFUNCTION("SUMIF($D$2:$D$520, TO_TEXT(F38) ,$C$2:$C$520)"),0.0) -> 0 | I38: TRUE | J38: =IF(I38=TRUE,0,MAX(G38-H38,0)) -> 0
B39: Súp | C39: 30 | D39: Living expense | F39: Đám cưới | G39: 500 | H39: =IFERROR(__xludf.DUMMYFUNCTION("SUMIF($D$2:$D$520, TO_TEXT(F39) ,$C$2:$C$520)"),500.0) -> 500 | I39: TRUE | J39: =IF(I39=TRUE,0,MAX(G39-H39,0)) -> 0
B40: Thuốc cho Má | C40: 112 | D40: Living expense | F40: Khám bệnh cho Má | G40: 0 | H40: =IFERROR(__xludf.DUMMYFUNCTION("SUMIF($D$2:$D$520, TO_TEXT(F40) ,$C$2:$C$520)"),3299.0) -> 3299 | I40: TRUE | J40: =IF(I40=TRUE,0,MAX(G40-H40,0)) -> 0
A41: 46059 | B41: Help Bảo | C41: 300 | D41: Living expense
B42: Tiền nhà | C42: 6000 | D42: Tiền nhà
B43: Nước suối | C43: 7 | D43: Living expense
B44: Khoai mỡ | C44: 30 | D44: Living expense
A45: 46060 | B45: Nạp vinaphone | C45: 50 | D45: Living expense
B46: Bún đậu | C46: 109 | D46: Living expense
B47: Mua bàn | C47: 1050 | D47: Buy
B48: Cháo | C48: 40 | D48: Living expense
B49: Nước Saigon Water | C49: 325 | D49: Living expense
B50: Bò né | C50: 112 | D50: Living expense
B51: Circle K | C51: 58 | D51: Living expense
B52: Trả Toàn | C52: 30 | D52: Living expense
B53: Trả tín dụng | C53: 15000 | D53: Tín dụng
A54: 46061 | B54: Ăn sáng | C54: 55 | D54: Living expense
B55: Cho Má | C55: 1000 | D55: Cho Má + lì xì
B56: 30Shine | C56: 479 | D56: Buy
B57: Sửa đt cho Ba | C57: 700 | D57: Buy
B58: Ốp lưng | C58: 85 | D58: Living expense
B59: Bò lá lốt | C59: 70 | D59: Living expense
B60: Đổ xăng | C60: 50 | D60: Living expense
B61: Deal shopee food | C61: 57 | D61: Living expense
B62: Ăn tối | C62: 86 | D62: Living expense
A63: 46062 | B63: Cơm cho Má | C63: 40 | D63: Living expense
B64: Cơm | C64: 30 | D64: Living expense
B65: Ăn chiều | C65: =67-65 -> 2 | D65: Living expense
A66: 46063 | B66: Cà phê | C66: 18 | D66: Living expense
B67: Cơm | C67: 30 | D67: Living expense
B68: Ăn chiều | C68: =110-55 -> 55 | D68: Living expense
A69: 46064 | B69: Cà phê | C69: 18 | D69: Living expense
B70: Nước | C70: 29 | D70: Living expense
B71: Cơm | C71: 30 | D71: Living expense
B72: Bún riêu | C72: 70 | D72: Living expense
B73: Thuốc | C73: 139 | D73: Living expense
A74: 46065 | B74: Youtube | C74: 54 | D74: Credit
B75: Cho Má | C75: 1400 | D75: Cho Má + lì xì
B76: Hớt tóc cho Ba | C76: 40 | D76: Living expense
B77: Ốp lưng cho Má | C77: 94 | D77: Living expense
B78: Kính cho Má | C78: 930 | D78: Cho Má + lì xì
B79: Bún thái | C79: 95 | D79: Living expense
B80: Nước Cần Thơ | C80: 109 | D80: Tiền nhà
A81: 46066 | B81: Ăn trưa | C81: 94 | D81: Living expense
B82: Nệm | C82: 990 | D82: Buy
B83: Đổ xăng | C83: 50 | D83: Living expense
B84: Cho Má | C84: 1000 | D84: Cho Má + lì xì
A85: 46067 | B85: Taxi | C85: =69 -> 69 | D85: Khám bệnh cho Ba
B86: Ăn trưa | C86: 193 | D86: Living expense
B87: Thuốc | C87: 124 | D87: Living expense
B88: Ăn hào | C88: 220 | D88: Living expense
A89: 46068 | B89: Nạp Viettel | C89: 20 | D89: Khám bệnh cho Ba
B90: Taxi về Trà Vinh | C90: 1204 | D90: Credit
B91: GO | C91: 193 | D91: Credit
B92: Gonsa | C92: 5000 | D92: Gonsa
B93: Cho Má | C93: 500 | D93: Living expense
A94: 46069 | B94: Thuốc | C94: 44 | D94: Living expense
B95: Bún nước lèo | C95: 185 | D95: Living expense
B96: Đồ chiên | C96: 65 | D96: Living expense
B97: Trái cây | C97: 20 | D97: Living expense
A98: 46070 | B98: Lì xì | C98: 1300 | D98: Lì xì
B99: Phở | C99: 30 | D99: Living expense
B100: Cho Út, cho Sáu | C100: 1000 | D100: Lì xì
...

Sheet T12026
A1: DATE | B1: SPENT FOR | C1: AMOUNT | D1: TYPE | F1: DATE | G1: EARN BY | H1: AMOUNT
A2: 46021 | B2: Trả party Rocket | C2: 200 | D2: Living expense | F2: 45991 | G2: Lương T12 | H2: =23419 -> 23419
B3: Trả Credit | C3: 8000 | D3: Credit debt | F3: 46024 | G3: Lương Ba | H3: 5540
B4: Trả Khang | C4: 2000 | D4: Khang debt | F4: 46034 | G4: Credit | H4: 11000
B5: Cho Má | C5: 3000 | D5: Parent | F5: 46038 | G5: Lương Ba | H5: 5550
B6: Ăn tối | C6: 64 | D6: Living expense | F6: 46042 | G6: Bảo gởi | H6: 200
A7: 46022 | B7: Nước ngọt | C7: 14 | D7: Living expense | F7: 46044 | G7: Bảo gởi | H7: 300
B8: Trả a Khoa | C8: 36 | D8: Living expense | F8: 46045 | G8: Bảo gởi | H8: 130
B9: Gỏi cuốn | C9: 35 | D9: Living expense | F9: 46046 | G9: Bảo gởi | H9: 370
B10: Fahasha | C10: 340 | D10: Buy | F10: 46049 | G10: Bảo gởi | H10: 400
B11: Jolibee | C11: 138 | D11: Living expense
A12: 46023 | B12: Taxi | C12: 1266 | D12: Travel
B13: Fahasha | C13: 19 | D13: Living expense | F13: Total earn | G13: =SUM(H2:H12) -> 46909
B14: Thuốc cho Ba | C14: 489 | D14: Parent | F14: Total spent | G14: =SUMIF(D2:D225, "<>Credit", C2:C533) + G15 -> 46844
B15: Help Ly | C15: 2000 | D15: Help Ly | F15: Untrack spent | G15: =242+50+22+257+62+262 -> 895
B16: Jolibee | C16: =176+17 -> 193 | D16: Living expense | F16: Saving | G16: 0
A17: 46024 | B17: Ăn sáng | C17: 60 | D17: Living expense
B18: Vớ | C18: 50 | D18: Living expense | F18: Remaining | G18: =G13-G14-J33 -> 65
B19: Winmart | C19: 202 | D19: Parent | F19: Remaining (- liabilities) | G19: =G13-G14 -> 65
B20: Dép cho Má | C20: 225 | D20: Parent
B21: Massage | C21: 150 | D21: Living expense | F21: Category | G21: Estimated | H21: Actual
B22: Massage Má | C22: 150 | D22: Parent | F22: Living expense | G22: 5000 | H22: =SUMIF(D2:D148, "=Living expense",C2:C166)+G15 -> 6674
B23: Bột chiên | C23: 30 | D23: Living expense
B24: Nhanh Thạch | C24: 100 | D24: Living expense | F24: Planned/actual spend per category of this month
B25: Hớt tóc cho Ba | C25: 35 | D25: Parent | F25: Category | G25: Estimated | H25: Actual | I25: Finalize | J25: Reserve
B26: Ăn cơm với Má | C26: 50 | D26: Living expense | F26: Gonsa | G26: 3000 | H26: =IFERROR(__xludf.DUMMYFUNCTION("SUMIF($D$2:$D$524, TO_TEXT(F26) ,$C$2:$C$524)"),5000.0) -> 5000 | I26: TRUE | J26: =IF(I26=TRUE,0,MAX(G26-H26,0)) -> 0
A27: 46025 | B27: Cơm gà | C27: 25 | D27: Living expense | F27: Rent | G27: 6600 | H27: =IFERROR(__xludf.DUMMYFUNCTION("SUMIF($D$2:$D$524, TO_TEXT(F27) ,$C$2:$C$524)"),6622.0) -> 6622 | I27: TRUE | J27: =IF(I27=TRUE,0,MAX(G27-H27,0)) -> 0
B28: Đổ xăng | C28: 42 | D28: Living expense | F28: Parent | G28: 3000 | H28: =IFERROR(__xludf.DUMMYFUNCTION("SUMIF($D$2:$D$524, TO_TEXT(F28) ,$C$2:$C$524)"),8754.0) -> 8754 | I28: TRUE | J28: =IF(I28=TRUE,0,MAX(G28-H28,0)) -> 0
B29: Cà phê | C29: 47 | D29: Living expense | F29: Credit debt | G29: 18000 | H29: =IFERROR(__xludf.DUMMYFUNCTION("SUMIF($D$2:$D$524, TO_TEXT(F29) ,$C$2:$C$524)"),11000.0) -> 11000 | I29: TRUE | J29: =IF(I29=TRUE,0,MAX(G29-H29,0)) -> 0
B30: Taxi | C30: =103+34+98 -> 235 | D30: Travel | F30: Travel | G30: 2000 | H30: =IFERROR(__xludf.DUMMYFUNCTION("SUMIF($D$2:$D$524, TO_TEXT(F30) ,$C$2:$C$524)"),2468.0) -> 2468 | I30: TRUE | J30: =IF(I30=TRUE,0,MAX(G30-H30,0)) -> 0
B31: Thuốc cho Má | C31: 17 | D31: Parent | F31: Khang debt | G31: 2000 | H31: =IFERROR(__xludf.DUMMYFUNCTION("SUMIF($D$2:$D$524, TO_TEXT(F31) ,$C$2:$C$524)"),2000.0) -> 2000 | I31: TRUE | J31: =IF(I31=TRUE,0,MAX(G31-H31,0)) -> 0
B32: Nhanh Thạch | C32: 15 | D32: Living expense | F32: Help Ly | G32: 2000 | H32: =IFERROR(__xludf.DUMMYFUNCTION("SUMIF($D$2:$D$524, TO_TEXT(F32) ,$C$2:$C$524)"),3000.0) -> 3000 | I32: TRUE | J32: =IF(I32=TRUE,0,MAX(G32-H32,0)) -> 0
B33: Tiền điện | C33: 533 | D33: Rent | F33: Sum | G33: =SUM(G27:G30) -> 29600 | H33: =SUM(H27:H29) -> 26376 | J33: =SUM(J26:J32) -> 0
A34: 46026 | B34: Thuốc đau đầu | C34: 17 | D34: Living expense
B35: Thuốc huyết áp | C35: 27 | D35: Living expense
B36: Taxi | C36: 967 | D36: Travel
B37: Cơm chiều | C37: 25 | D37: Living expense
B38: Cháo | C38: 30 | D38: Living expense
A39: 46027 | B39: Súp | C39: 11 | D39: Living expense
B40: Đổ xăng | C40: 48 | D40: Living expense
B41: Bánh canh | C41: 50 | D41: Living expense
A42: 46028 | B42: Nước ngọt | C42: 14 | D42: Living expense
B43: Ăn chiều | C43: 47 | D43: Living expense
A44: 46029 | B44: Khám bệnh cho Má | C44: =120+485+2 -> 607 | D44: Parent
B45: Help Ly | C45: 1000 | D45: Help Ly
B46: Cafe | C46: 20 | D46: Living expense
B47: Cơm chiều | C47: 77 | D47: Living expense
B48: Súp | C48: 12 | D48: Living expense
A49: 46030 | B49: Nước ngọt | C49: 14 | D49: Living expense
B50: Cơm chiều | C50: 60 | D50: Living expense
A51: 46031 | B51: Khám bệnh cho Ba | C51: =40+369+104 -> 513 | D51: Parent
B52: Taxi | C52: =226+230 -> 456 | D52: Parent
B53: Trả tín dụng | C53: 3000 | D53: Credit debt
B54: Jolibee | C54: 120 | D54: Living expense
A55: 46032 | B55: Fahasha (Giá đỡ lịch, móc dán, đồ chơi) | C55: =147+44 -> 191 | D55: Buy
B56: Lịch cuốn | C56: 44 | D56: Buy
B57: Tua vít | C57: 25 | D57: Living expense
B58: Bún riêu | C58: 55 | D58: Living expense
B59: Tiền kết | C59: 10 | D59: Living expense
A60: 46033 | B60: Làm tóc | C60: 524 | D60: Buy
B61: Siêu thị | C61: 1295 | D61: Credit
B62: Cho Má | C62: 1500 | D62: Parent
A63: 46034 | B63: YouTube Premium | C63: 54 | D63: Credit
B64: Cà phê | C64: 20 | D64: Living expense
B65: Pizza | C65: 229 | D65: Living expense
A66: 46035 | B66: Cà phê | C66: 16 | D66: Living expense
B67: Nạp game | C67: 27 | D67: Buy
A68: 46036 | B68: Cà phê | C68: 20 | D68: Living expense
B69: Bún riêu | C69: 80 | D69: Living expense
A70: 46037 | B70: Tiền nhà | C70: 6000 | D70: Rent
B71: Lẩu bò | C71: 260 | D71: Living expense
B72: Gonsa | C72: 5000 | D72: Gonsa
A73: 46038 | B73: Tiền nước | C73: 89 | D73: Rent
B74: Nước ngọt | C74: 15 | D74: Living expense
B75: Taxi | C75: 61 | D75: Living expense
B76: Jolibee | C76: 103 | D76: Living expense
B77: Cho Má | C77: 1500 | D77: Parent
A78: 46039 | B78: Taxi | C78: =71+60 -> 131 | D78: Living expense
B79: Khám bệnh cho Ba | C79: =100+929 -> 1029 | D79: Living expense
B80: Ăn chiều w/ Má | C80: 233 | D80: Living expense
B81: Circle K | C81: 73 | D81: Living expense
B82: Ăn trưa | C82: 70 | D82: Living expense
A83: 46040 | B83: Ăn trưa | C83: 60 | D83: Living expense
B84: Rửa xe + cà phê | C84: =25+32 -> 57 | D84: Living expense
B85: Tiền kết | C85: 5 | D85: Living expense
B86: Hủ tiếu | C86: 60 | D86: Living expense
B87: Máy hút bụi | C87: 500 | D87: Credit
A88: 46041 | B88: Nước ngọt | C88: 15 | D88: Living expense
A89: 46042 | B89: Trà oolong | C89: 12 | D89: Living expense
B90: Vinaphone | C90: 50 | D90: Living expense
B91: Jolibee | C91: 108 | D91: Living expense
B92: Cơm chiều | C92: 36 | D92: Living expense
A93: 46043 | B93: Nước ngọt | C93: 15 | D93: Living expense
B94: Cơm chiều | C94: 52 | D94: Living expense
B95: Gemini | C95: 73 | D95: Living expense
B96: Quỹ Rocket | C96: 100 | D96: Living expense
A97: 46044 | B97: Cơm | C97: 38 | D97: Living expense
B98: Gỏi cuốn | C98: 25 | D98: Living expense
B99: Đồ chiên | C99: 40 | D99: Living expense
A100: 46045 | B100: Chơ cho Má | C100: 40 | D100: Living expense
...

Sheet T122025
A1: DATE | B1: SPENT FOR | C1: AMOUNT | D1: TYPE | F1: DATE | G1: EARN BY | H1: AMOUNT
A2: 45988 | B2: Sữa | C2: 11 | D2: Living expense | F2: 45988 | G2: Cuối T11 | H2: ='T112025'!G19 -> 419
B3: Trả Khang | C3: 1000 | D3: Khang debt | G3: Lương T11 | H3: 23500
B4: Quà tặng thầy Thái | C4: 275 | D4: Khang debt | F4: 45989 | G4: Bảo gởi tiền cưới | H4: 1000
B5: Ăn tối | C5: 50 | D5: Living expense | F5: 46000 | G5: Khang support | H5: 3000
B6: Thuốc | C6: 101 | D6: Living expense | G6: Credit | H6: 5000
B7: Cho Má | C7: 4000 | D7: Parent | F7: 46002 | G7: Credit | H7: 10000
B8: Trả Credit Kienlong Bank | C8: 5040 | D8: Credit debt | F8: 46006 | G8: Khang support | H8: 2000
A9: 45989 | B9: Taxi | C9: 1266 | D9: Travel | F9: 46007 | G9: Bảo | H9: 1000
B10: Đổ xăng | C10: 40 | D10: Living expense | F10: 46010 | G10: Bảo | H10: 1000
B11: Cơm | C11: 100 | D11: Living expense | F11: 23-24-28/12/2025 | G11: Bảo | H11: =1000+200 -> 1200
B12: Đồ chiên | C12: 20 | D12: Living expense
B13: Cà phê | C13: 32 | D13: Living expense | F13: Total earn | G13: =SUM(H2:H12) -> 48119
B14: Sữa ensure | C14: 438 | D14: Credit | F14: Total spent | G14: =SUMIF(D2:D219, "<>Credit", C2:C527) + G15 -> 47857
A15: 45990 | B15: Ăn sáng | C15: 5 | D15: Living expense | F15: Untrack spent | G15: =550+2+45+182+10 -> 789
B16: Help Ly | C16: 500 | D16: Help people | F16: Saving | G16: 0
B17: Taxi | C17: =102+93 -> 195 | D17: Living expense
B18: Bánh canh | C18: 26 | D18: Living expense | F18: Estimate remaining | G18: =G13-G14-J34 -> 262
B19: Cà phê | C19: 32 | D19: Living expense | F19: Remaining without cost | G19: =G13-G14 -> 262
A20: 45991 | B20: Phở | C20: 79 | D20: Living expense
B21: Nước | C21: 27 | D21: Living expense | F21: Category | G21: Estimated | H21: Actual
B22: Taxi | C22: 967 | D22: Travel | F22: Living expense | G22: 5000 | H22: =SUMIF(D2:D142, "=Living expense",C2:C160)+G15 -> 6503
B23: Jolibee | C23: 128 | D23: Living expense
A24: 45992 | B24: Nước ngọt | C24: 14 | D24: Living expense | F24: Planned/actual spend per category of this month
B25: Đưa má tiền đám cưới | C25: 1000 | D25: Other | F25: Category | G25: Estimated | H25: Actual | I25: Finalize | J25: Reserve
B26: Đồ chiên | C26: 50 | D26: Living expense | F26: Gonsa | G26: 3000 | H26: =IFERROR(__xludf.DUMMYFUNCTION("SUMIF($D$2:$D$518, TO_TEXT(F26) ,$C$2:$C$518)"),5000.0) -> 5000 | I26: TRUE | J26: =IF(I26=TRUE,0,MAX(G26-H26,0)) -> 0
B27: Circle K | C27: 49 | D27: Living expense | F27: Rent | G27: 6609 | H27: =IFERROR(__xludf.DUMMYFUNCTION("SUMIF($D$2:$D$518, TO_TEXT(F27) ,$C$2:$C$518)"),6609.0) -> 6609 | I27: TRUE | J27: =IF(I27=TRUE,0,MAX(G27-H27,0)) -> 0
B28: Ăn tối | C28: 65 | D28: Living expense | F28: Help people | G28: 2000 | H28: =IFERROR(__xludf.DUMMYFUNCTION("SUMIF($D$2:$D$518, TO_TEXT(F28) ,$C$2:$C$518)"),1500.0) -> 1500 | I28: TRUE | J28: =IF(I28=TRUE,0,MAX(G28-H28,0)) -> 0
A29: 45993 | B29: Tiền điện | C29: 520 | D29: Rent | F29: Parent | G29: 3000 | H29: =IFERROR(__xludf.DUMMYFUNCTION("SUMIF($D$2:$D$518, TO_TEXT(F29) ,$C$2:$C$518)"),6848.0) -> 6848 | I29: TRUE | J29: =IF(I29=TRUE,0,MAX(G29-H29,0)) -> 0
B30: Cơm | C30: 35 | D30: Living expense | F30: Credit debt | G30: 15250 | H30: =IFERROR(__xludf.DUMMYFUNCTION("SUMIF($D$2:$D$518, TO_TEXT(F30) ,$C$2:$C$518)"),15315.0) -> 15315 | I30: TRUE | J30: =IF(I30=TRUE,0,MAX(G30-H30,0)) -> 0
B31: Sữa | C31: 22 | D31: Living expense | F31: Travel | G31: 2000 | H31: =IFERROR(__xludf.DUMMYFUNCTION("SUMIF($D$2:$D$518, TO_TEXT(F31) ,$C$2:$C$518)"),2233.0) -> 2233 | I31: TRUE | J31: =IF(I31=TRUE,0,MAX(G31-H31,0)) -> 0
B32: Trả tiền nước cho Tú | C32: 27 | D32: Living expense | F32: Khang debt | G32: 1275 | H32: =IFERROR(__xludf.DUMMYFUNCTION("SUMIF($D$2:$D$518, TO_TEXT(F32) ,$C$2:$C$518)"),1275.0) -> 1275 | I32: TRUE | J32: =IF(I32=TRUE,0,MAX(G32-H32,0)) -> 0
B33: Ăn tối | C33: 37 | D33: Living expense | F33: Wedding | G33: 500 | H33: =IFERROR(__xludf.DUMMYFUNCTION("SUMIF($D$2:$D$518, TO_TEXT(F33) ,$C$2:$C$518)"),500.0) -> 500 | I33: TRUE | J33: =IF(I33=TRUE,0,MAX(G33-H33,0)) -> 0
A34: 45994 | B34: An trả | C34: -27 | D34: Living expense | F34: Sum | G34: =SUM(G27:G31) -> 28859 | H34: =SUM(H27:H30) -> 30272 | J34: =SUM(J26:J33) -> 0
B35: Ăn trưa | C35: 30 | D35: Living expense
B36: Ăn chiều | C36: 59 | D36: Living expense
A37: 45995 | B37: Nước ngọt | C37: 14 | D37: Living expense
B38: Thuốc cho Má | C38: 105 | D38: Living expense
B39: Circle K | C39: 90 | D39: Living expense
B40: Order gỏi cuốn | C40: =93-30-30 -> 33 | D40: Living expense
A41: 45996 | B41: Ăn trưa | C41: 39 | D41: Living expense
B42: Nước ngọt | C42: 14 | D42: Living expense
B43: Circle K | C43: 28 | D43: Living expense
B44: Cháo | C44: 84 | D44: Living expense
A45: 45997 | B45: 30Shine | C45: 389 | D45: Living expense
B46: Help cậu 2 | C46: 1000 | D46: Help people
B47: Taxi | C47: =47+50 -> 97 | D47: Buy
B48: Jolibee | C48: 127 | D48: Living expense
A49: 45998 | B49: Trả Credit Kienlong Bank | C49: 438 | D49: Parent
B50: Cà phê | C50: 20 | D50: Living expense
B51: Đi đám cưới TV | C51: 500 | D51: Wedding
B52: Circle K | C52: 37 | D52: Living expense
B53: Nước | C53: 101 | D53: Living expense
A54: 45999 | B54: Help Nhi | C54: 100 | D54: Support
B55: Fahasha | C55: 197 | D55: Buy
B56: Donation | C56: 55 | D56: Buy
B57: Trả tiền cơm a Khoa | C57: 39 | D57: Living expense
A58: 46000 | B58: Trả Credit Kienlong Bank | C58: 10250 | D58: Credit debt
B59: Sữa | C59: 11 | D59: Living expense
B60: Đồ chiên | C60: 30 | D60: Living expense
B61: Circle K | C61: 25 | D61: Living expense
A62: 46001 | B62: Quỹ Rocket | C62: 100 | D62: Living expense
B63: Cà phê | C63: 20 | D63: Living expense
B64: Ăn tối | C64: 228 | D64: Credit
A65: 46002 | B65: Trả credit | C65: 25 | D65: Credit debt
B66: Ăn chiều | C66: 52 | D66: Living expense
B67: Sữa | C67: 13 | D67: Living expense
B68: Thuốc cho Má | C68: 132 | D68: Credit
A69: 46003 | B69: Nước ngọt | C69: 14 | D69: Living expense
B70: Cơm trưa | C70: 46 | D70: Living expense
B71: Đổ xăng | C71: 50 | D71: Living expense
B72: Jolibee | C72: 128 | D72: Living expense
B73: Bò kho cho Má | C73: 25 | D73: Living expense
B74: YouTube Premium | C74: 54 | D74: Buy
A75: 46004 | B75: Taxi | C75: 71 | D75: Buy
B76: Taxi | C76: 68 | D76: Credit
B77: Khám bệnh cho Ba | C77: 210 | D77: Parent
B78: Cho Má | C78: 1000 | D78: Parent
A79: 46005 | B79: Thuốc | C79: 78 | D79: Credit
B80: Sữa Ensure | C80: 260 | D80: Credit
B81: Taxi | C81: =620+34+543+34 -> 1231 | D81: Credit
B82: Cafe | C82: 30 | D82: Living expense
B83: Jolibee | C83: 128 | D83: Living expense
B84: Tiền nước | C84: 89 | D84: Rent
A85: 46006 | B85: Tiền nhà | C85: 6000 | D85: Rent
B86: Gonsa | C86: 5000 | D86: Gonsa
B87: Ăn chiều | C87: 35 | D87: Living expense
B88: Nước ngọt | C88: 14 | D88: Living expense
B89: Help Ly | C89: 500 | D89: Support
A90: 46007 | B90: Dầu gội | C90: 73 | D90: Living expense
B91: Order cơm chiều | C91: =143-36-36-35 -> 36 | D91: Living expense
B92: Ăn tối | C92: 99 | D92: Living expense
A93: 46008 | B93: Nước ngọt | C93: 14 | D93: Living expense
B94: Ăn tối | C94: 61 | D94: Living expense
A95: 46009 | B95: Nước ngọt | C95: 14 | D95: Living expense
B96: Súp | C96: 12 | D96: Living expense
A97: 46010 | B97: Ăn trưa | C97: 32 | D97: Living expense
B98: Cho Má | C98: 1000 | D98: Parent
B99: Jolibee | C99: 138 | D99: Living expense
B100: Movie | C100: 569 | D100: Credit
...

Sheet T112025
A1: DATE | B1: SPENT FOR | C1: AMOUNT | D1: TYPE | F1: DATE | G1: EARN BY | H1: AMOUNT
A2: 45960 | B2: Trả Khang | C2: 2000 | D2: Khang debt | F2: 45930 | G2: Cuối T10 | H2: ='T102025'!G18 -> 1664
B3: GS25 | C3: 14 | D3: Living expense | G3: Lương T10 | H3: 27279
B4: Kienlong Bank | C4: 15250 | D4: Credit debt | F4: 45941 | G4: Ba | H4: =2000 -> 2000
B5: Ăn chiều | C5: =115-50 -> 65 | D5: Living expense | F5: 45944 | G5: Kienlong Bank | H5: 10000
B6: Help Nhi | C6: 500 | D6: Help people | F6: 45945 | G6: Bảo | H6: 2500
B7: Help Ly | C7: 500 | D7: Help people | F7: 45946 | G7: Kienlong Bank | H7: 5000
B8: Đồ chiên | C8: 50 | D8: Living expense | F8: 45954 | G8: Khang support | H8: 1000
B9: Sữa Ensure Gold | C9: 791 | D9: Parent | G9: Bảo support | H9: 300
A10: 45961 | B10: Ăn trưa | C10: 30 | D10: Living expense
B11: Gởi Má tiền ăn | C11: 200 | D11: Parent
B12: Ăn chiều | C12: 75 | D12: Living expense
B13: Circle K | C13: 60 | D13: Living expense | F13: Total earn | G13: =SUM(H2:H12) -> 49743
B14: Gởi Má tiền ăn | C14: 2000 | D14: Parent | F14: Total spent | G14: =SUMIF(D2:D213, "<>Credit", C2:C521) + G15 -> 49324
B15: Help Nhi TV | C15: 500 | D15: Help people | F15: Untrack spent | G15: =112+50-63+10+96+20+1+12 -> 238
B16: Help Nhi TV | C16: 100 | D16: Support | F16: Saving | G16: 0
A17: 45962 | B17: Khám bệnh cho Má | C17: =120+608 -> 728 | D17: Parent
B18: Gym | C18: 30 | D18: Living expense | F18: Estimate remaining | G18: =G13-G14-J32 -> 419
B19: Circle K | C19: 131 | D19: Living expense | F19: Remaining without cost | G19: =G13-G14 -> 419
A20: 45963 | B20: Nhi trả | C20: -100 | D20: Support
B21: Nhà thờ | C21: 25 | D21: Living expense | F21: Category | G21: Estimated | H21: Actual
B22: Circle K | C22: 28 | D22: Living expense | F22: Living expense | G22: 5000 | H22: =SUMIF(D2:D136, "=Living expense",C2:C154)+G15 -> 5889
B23: GO | C23: 320 | D23: Buy
A24: 45964 | B24: Nước ngọt | C24: 14 | D24: Living expense | F24: Planned/actual spend per category of this month
B25: Ăn chiều | C25: =108-35 -> 73 | D25: Living expense | F25: Category | G25: Estimated | H25: Actual | I25: Finalize | J25: Reserve
B26: Circle K | C26: 42 | D26: Living expense | F26: Gonsa | G26: 3000 | H26: =IFERROR(__xludf.DUMMYFUNCTION("SUMIF($D$2:$D$512, TO_TEXT(F26) ,$C$2:$C$512)"),5000.0) -> 5000 | I26: TRUE | J26: =IF(I26=TRUE,0,MAX(G26-H26,0)) -> 0
B27: Ăn khuya | C27: 107 | D27: Living expense | F27: Rent | G27: 7000 | H27: =IFERROR(__xludf.DUMMYFUNCTION("SUMIF($D$2:$D$512, TO_TEXT(F27) ,$C$2:$C$512)"),7019.0) -> 7019 | I27: TRUE | J27: =IF(I27=TRUE,0,MAX(G27-H27,0)) -> 0
A28: 45965 | B28: Nước ngọt | C28: 14 | D28: Living expense | F28: Help people | G28: 1500 | H28: =IFERROR(__xludf.DUMMYFUNCTION("SUMIF($D$2:$D$512, TO_TEXT(F28) ,$C$2:$C$512)"),1500.0) -> 1500 | I28: TRUE | J28: =IF(I28=TRUE,0,MAX(G28-H28,0)) -> 0
B29: Ăn chiều | C29: 75 | D29: Living expense | F29: Parent | G29: 3000 | H29: =IFERROR(__xludf.DUMMYFUNCTION("SUMIF($D$2:$D$512, TO_TEXT(F29) ,$C$2:$C$512)"),9063.0) -> 9063 | I29: TRUE | J29: =IF(I29=TRUE,0,MAX(G29-H29,0)) -> 0
B30: GS25 | C30: 43 | D30: Living expense | F30: Credit debt | G30: 15250 | H30: =IFERROR(__xludf.DUMMYFUNCTION("SUMIF($D$2:$D$512, TO_TEXT(F30) ,$C$2:$C$512)"),15250.0) -> 15250 | I30: TRUE | J30: =IF(I30=TRUE,0,MAX(G30-H30,0)) -> 0
B31: Tiền điện | C31: 1019 | D31: Rent | F31: Khang debt | G31: 2000 | H31: =IFERROR(__xludf.DUMMYFUNCTION("SUMIF($D$2:$D$512, TO_TEXT(F31) ,$C$2:$C$512)"),2000.0) -> 2000 | I31: TRUE | J31: =IF(I31=TRUE,0,MAX(G31-H31,0)) -> 0
B32: Ăn khuya | C32: 38 | D32: Living expense | F32: Sum | G32: =SUM(G26:G31) -> 31750 | H32: =SUM(H26:H29) -> 22582 | J32: =SUM(J26:J31) -> 0
A33: 45966 | B33: Taxi khám bệnh cho Ba | C33: =58+65 -> 123 | D33: Parent
B34: Nước ngọt | C34: 14 | D34: Living expense
B35: Ăn chiều | C35: 72 | D35: Living expense
A36: 45967 | B36: Sữa | C36: 13 | D36: Living expense
B37: Đổ xăng | C37: 55 | D37: Living expense
B38: Ăn chiều | C38: 100 | D38: Living expense
B39: Thuốc cảm, khẩu trang | C39: 88 | D39: Living expense
B40: Circle K | C40: 50 | D40: Living expense
A41: 45968 | B41: Sekiro | C41: 650 | D41: Credit
B42: Sữa | C42: 10 | D42: Living expense
B43: Ăn tối | C43: 50 | D43: Living expense
B44: Yame | C44: 273 | D44: Buy
A45: 45969 | B45: Thuốc | C45: 40 | D45: Living expense
B46: Ăn sáng | C46: 37 | D46: Living expense
B47: Sủi C | C47: 32 | D47: Living expense
B48: Help Nguyệt | C48: 1000 | D48: Support
B49: Ăn tối | C49: 154 | D49: Living expense
A50: 45970 | B50: Nhà thờ | C50: =5+20 -> 25 | D50: Living expense
B51: Ăn tối | C51: =25+258+57 -> 340 | D51: Living expense
A52: 45971 | B52: Ăn trưa | C52: 33 | D52: Living expense
B53: Nước ngọt | C53: 23 | D53: Living expense
B54: Ăn tối | C54: 18 | D54: Living expense
B55: Fahasha | C55: 294 | D55: Buy
B56: Shopee (bọc bài, thảm, lót chuột) | C56: 261 | D56: Buy
A57: 45972 | B57: Trả Credit Kienlongbank (Game) | C57: 615 | D57: Buy
B58: Ăn trưa | C58: 35 | D58: Living expense
B59: Bún bò | C59: 50 | D59: Living expense
B60: Circle K | C60: 34 | D60: Living expense
A61: 45973 | B61: Ăn trưa | C61: 40 | D61: Living expense
B62: Sữa Milo | C62: 17 | D62: Living expense
B63: Youtube | C63: 54 | D63: Living expense
A64: 45974 | B64: Ăn trưa | C64: 30 | D64: Living expense
B65: Ăn chiều | C65: =95-28 -> 67 | D65: Living expense
B66: Fahasha (Uno) | C66: 279 | D66: Living expense
B67: Uno No Mercy Steam | C67: 83 | D67: Living expense
A68: 45975 | B68: Đổ xăng | C68: 50 | D68: Living expense
B69: Bách hóa Xanh | C69: 70 | D69: Living expense
B70: Tiền nước T11 | C70: 109 | D70: Living expense
B71: Ăn chiều | C71: 52 | D71: Living expense
B72: Nước ngọt | C72: 28 | D72: Living expense
A73: 45976 | B73: Khám bệnh cho Ba | C73: =64+210+672+136+55+621+63 -> 1821 | D73: Parent
B74: Gonsa T11 | C74: 5000 | D74: Gonsa
B75: Rent | C75: 6000 | D75: Rent
B76: Khám bệnh cho Má | C76: 0 | D76: Parent | E76: 2801
B77: 30Shine | C77: 767 | D77: Buy
B78: Jolibee | C78: 103 | D78: Living expense
A79: 45977 | B79: Jolibee | C79: 66 | D79: Living expense
B80: Gởi má tiền ăn | C80: 3000 | D80: Parent
A81: 45978 | B81: Cà phê | C81: 16 | D81: Living expense
B82: Cơm | C82: =104-50 -> 54 | D82: Living expense
B83: Bò kho | C83: 35 | D83: Living expense
B84: Circle K | C84: 57 | D84: Living expense
A85: 45979 | B85: Cà phê | C85: 17 | D85: Living expense
B86: Bò kho | C86: =27+27 -> 54 | D86: Living expense
A87: 45980 | B87: Sữa | C87: 13 | D87: Living expense
B88: Bún bò | C88: 50 | D88: Living expense
B89: Nước ngọt | C89: 28 | D89: Living expense
A90: 45981 | B90: Sữa | C90: 13 | D90: Living expense
B91: Ăn tối | C91: 50 | D91: Living expense
B92: Đánh cầu | C92: =15+3 -> 18 | D92: Living expense
A93: 45982 | B93: Ăn trưa w/ team | C93: =124+81-51-46-61 -> 47 | D93: Living expense
B94: Đồ chiên | C94: 50 | D94: Living expense
A95: 45983 | B95: Khám bệnh cho Má | C95: =110+301+370+25+38+25+94 -> 963 | D95: Living expense
B96: Nước ngọt | C96: 28 | D96: Living expense
B97: Đổ xăng | C97: 55 | D97: Living expense
A98: 45984 | B98: Gemini AI | C98: 73 | D98: Buy
B99: Circle K | C99: 38 | D99: Living expense
B100: Đồ chiên | C100: 40 | D100: Living expense
...

Sheet T102025
A1: DATE | B1: SPENT FOR | C1: AMOUNT | D1: TYPE | F1: DATE | G1: EARN BY | H1: AMOUNT
A2: 45929 | B2: Trả tín dụng KienlongBank | C2: 15000 | D2: Credit debt | F2: 45929 | G2: Cuối T9 | H2: 149
B3: Trả tiền thuê xe tải | C3: 1500 | D3: Buy | G3: Lương T9 | H3: 20000
B4: Help A Bảo | C4: 2000 | D4: Support | F4: 45935 | G4: Khang support | H4: 2000
A5: 45930 | B5: Tiền điện nước Thanh Duy House | C5: 247 | D5: Living expense | F5: 45941 | G5: Credit | H5: 15000
B6: Tiền nước Rocket | C6: 93 | D6: Living expense | F6: 45942 | G6: Bảo | H6: 2000
B7: GS25 | C7: 26 | D7: Living expense | F7: 45945 | G7: Bảo | H7: 1000
B8: Ăn tối | C8: 82 | D8: Living expense | G8: Mượn Ba | H8: 5480
A9: 45931 | B9: GS25 | C9: 26 | D9: Living expense | F9: 45948 | G9: Bảo | H9: 3000
B10: GS25 trưa | C10: 14 | D10: Living expense | F10: 45951 | G10: Bảo | H10: 700
A11: 45932 | B11: GS25 | C11: 14 | D11: Living expense | F11: 45957 | G11: JICA Bonus | H11: 2000
B12: Jolibee | C12: 70 | D12: Living expense
B13: Game | C13: 365 | D13: Credit | F13: Total earn | G13: =SUM(H2:H12) -> 51329
A14: 45933 | B14: Điện Trà Vinh | C14: 279 | D14: Living expense | F14: Total spent | G14: =SUMIF(D2:D208, "<>Credit", C2:C516) + G15 -> 49665
B15: Điện | C15: 487 | D15: Living expense | F15: Untrack spent | G15: =7 -> 7
B16: Nước | C16: 49 | D16: Living expense | F16: Saving | G16: 0
B17: Ăn tối | C17: 97 | D17: Living expense
A18: 45934 | B18: Game GOW | C18: 463 | D18: Credit | F18: Estimate remaining | G18: =G13-G14-J33 -> 1664
A19: 45935 | B19: Tiền kết | C19: 10 | D19: Living expense | F19: Remaining without cost | G19: =G13-G14 -> 1664
B20: Ensure Gold | C20: 790 | D20: Credit
B21: Circle K | C21: 74 | D21: Credit | F21: Category | G21: Estimated | H21: Actual
A22: 45936 | B22: Khám bệnh cho Má | C22: =2077-1837 -> 240 | D22: Living expense | F22: Living expense | G22: 5000 | H22: =SUMIF(D2:D131, "=Living expense",C2:C149)+G15 -> 7272
B23: Circle K | C23: 14 | D23: Living expense
B24: Ăn chiều | C24: 52 | D24: Living expense | F24: Planned/actual spend per category of this month
B25: Trả a Khoa | C25: 35 | D25: Living expense | F25: Category | G25: Estimated | H25: Actual | I25: Finalize | J25: Reserve
B26: Cho Má | C26: 1000 | D26: Parent | F26: Gonsa | G26: 5000 | H26: =SUMIF($D$2:$D$507, "=Gonsa",$C$2:$C$507) -> 5000 | I26: TRUE | J26: =IF(I26=TRUE,0,MAX(G26-H26,0)) -> 0
A27: 45937 | B27: GS25 | C27: 14 | D27: Living expense | F27: Rent | G27: 5800 | H27: =SUMIF($D$2:$D$507, "=Rent",$C$2:$C$507) -> 5800 | I27: TRUE | J27: =IF(I27=TRUE,0,MAX(G27-H27,0)) -> 0
A28: 45938 | B28: GS25 | C28: 14 | D28: Living expense | F28: Rocket fund | G28: 300 | H28: =SUMIF($D$2:$D$507, "=Rocket fund",$C$2:$C$507) -> 300 | I28: TRUE | J28: =IF(I28=TRUE,0,MAX(G28-H28,0)) -> 0
B29: Order gỏi cuốn | C29: =164-25-25-57 -> 57 | D29: Living expense | F29: Donate | G29: 5000 | H29: =SUMIF($D$2:$D$507, "=Donate",$C$2:$C$507) -> 5000 | I29: TRUE | J29: =IF(I29=TRUE,0,MAX(G29-H29,0)) -> 0
A30: 45939 | B30: GS25 | C30: 40 | D30: Living expense | F30: Help friend | G30: 1000 | H30: =SUMIF($D$2:$D$507, "=Help friend",$C$2:$C$507) -> 1000 | I30: TRUE | J30: =IF(I30=TRUE,0,MAX(G30-H30,0)) -> 0
B31: Ăn chiều | C31: 68 | D31: Living expense | F31: Parent | G31: 4000 | H31: =SUMIF($D$2:$D$507, "=Parent",$C$2:$C$507) -> 5093 | I31: TRUE | J31: =IF(I31=TRUE,0,MAX(G31-H31,0)) -> 0
A32: 45940 | B32: Đổ xăng | C32: 50 | D32: Living expense | F32: Credit debt T10 | G32: 1700 | H32: =SUMIF($D$2:$D$507, "=Credit debt T10",$C$2:$C$507) -> 1700 | I32: TRUE | J32: =IF(I32=TRUE,0,MAX(G32-H32,0)) -> 0
B33: GS25 | C33: 17 | D33: Living expense | F33: Sum | G33: =SUM(G26:G32) -> 22800 | H33: =SUM(H26:H31) -> 22193 | J33: =SUM(J26:J32) -> 0
B34: Ăn trưa | C34: 35 | D34: Living expense
B35: Circle K | C35: 57 | D35: Living expense
A36: 45941 | B36: Taxi | C36: =60+72 -> 132 | D36: Living expense
B37: Viện phí (khám, xét nghiệm, thuốc) | C37: =210+978 -> 1188 | D37: Living expense
B38: Dịch vụ BV | C38: =39+120 -> 159 | D38: Living expense
B39: Sữa Ensure | C39: 790 | D39: Parent
A40: 45942 | B40: Thay kiếng xe | C40: 182 | D40: Living expense
B41: Rửa xe | C41: 25 | D41: Living expense
B42: Tiền kết | C42: 10 | D42: Living expense
B43: Help Nhi | C43: 1000 | D43: Help friend
B44: Thuốc cho Ba | C44: 490 | D44: Parent
B45: Tiền ăn ba má | C45: 1500 | D45: Parent
A46: 45943 | B46: Quỹ Rocket | C46: 300 | D46: Rocket fund
B47: Trà sữa | C47: =100-34 -> 66 | D47: Living expense
B48: Ăn tối | C48: 118 | D48: Living expense
A49: 45944 | B49: Trả credit Kienlong Bank | C49: 1700 | D49: Credit debt T10
B50: GS25 | C50: 14 | D50: Living expense
B51: Ăn sáng | C51: 20 | D51: Living expense
B52: Youtube Premium | C52: 54 | D52: Living expense
A53: 45945 | B53: GS25 | C53: 14 | D53: Living expense
B54: Gonsa | C54: 5000 | D54: Gonsa
B55: Tiền nhà T10 | C55: 5800 | D55: Rent
B56: Nước T10 | C56: 79 | D56: Living expense
B57: Ăn tối | C57: =110+59 -> 169 | D57: Living expense
A58: 45946 | B58: GS25 | C58: 14 | D58: Living expense
B59: Ăn tối | C59: =140-35 -> 105 | D59: Living expense
A60: 45947 | B60: GS25 | C60: 14 | D60: Living expense
B61: Bún w/ Rocket | C61: =90-30-30 -> 30 | D61: Living expense
B62: Circle K | C62: 34 | D62: Living expense
A63: 45948 | B63: Cafe | C63: 35 | D63: Living expense
B64: Sữa ensure | C64: 790 | D64: Parent
B65: Bàn phím | C65: 581 | D65: Living expense
B66: Khám bệnh cho Má | C66: =120+2000+174-1771 -> 523 | D66: Parent
B67: Mua lặt vặt | C67: =30+20 -> 50 | D67: Living expense
B68: Đồ chiên | C68: 60 | D68: Living expense
B69: Đổ xăng | C69: 50 | D69: Living expense
A70: 45949 | B70: 30Shine | C70: 381 | D70: Living expense
B71: Circle K | C71: 76 | D71: Living expense
A72: 45950 | B72: Nước ngọt | C72: 14 | D72: Living expense
B73: Ăn tối | C73: 136 | D73: Living expense
B74: Donate | C74: 2500 | D74: Donate
A75: 45951 | B75: GS25 | C75: 42 | D75: Living expense
B76: Ăn tối | C76: =30+53 -> 83 | D76: Living expense
A77: 45952 | B77: GS25 | C77: 11 | D77: Living expense
B78: Ăn chiều | C78: 88 | D78: Living expense
B79: Ăn tối | C79: 70 | D79: Living expense
A80: 45953 | B80: GS25 | C80: 11 | D80: Living expense
B81: Ăn chiều | C81: =131-40 -> 91 | D81: Living expense
A82: 45954 | B82: Ăn trưa | C82: 30 | D82: Living expense
B83: Sữa | C83: 13 | D83: Living expense
B84: Ăn tối | C84: 100 | D84: Living expense
A85: 45955 | B85: Ăn tối | C85: =73+50 -> 123 | D85: Living expense
A86: 45956 | B86: Ngọc Yến 3 | C86: 168 | D86: Living expense
B87: Đổ xăng | C87: 50 | D87: Living expense
A88: 45957 | B88: Circle K | C88: 58 | D88: Living expense
B89: Donate | C89: 2500 | D89: Donate
A90: 45958 | B90: Nước ngọt | C90: 14 | D90: Living expense
B91: Ăn chiều | C91: =130-60 -> 70 | D91: Living expense
B92: The 80s | C92: 35 | D92: Living expense
A93: 45959 | B93: Ăn chiều | C93: 60 | D93: Living expense
B94: Ăn trưa | C94: 40 | D94: Living expense
B95: GS25 | C95: 14 | D95: Living expense
B96: Circle K | C96: 97 | D96: Living expense

Sheet T92025
A1: DATE | B1: SPENT FOR | C1: AMOUNT | D1: TYPE | F1: DATE | G1: EARN BY | H1: AMOUNT
A2: 45897 | B2: GS25 | C2: 24 | D2: Living expense | F2: 45897 | G2: Cuối tháng 8 | H2: 433
B3: Pizza | C3: 304 | D3: Living expense | G3: Lương tháng 8 | H3: 29112
B4: Shopee Pay Later | C4: 1021 | D4: Credit debt | F4: 45911 | G4: Khang help | H4: 1500
B5: Kienlong Bank Credit | C5: 1789 | D5: Credit debt | G5: Bảo gởi Gonsa | H5: 2500
B6: Trả Khang | C6: 3000 | D6: Khang debt | G6: Credit | H6: 15000
A7: 45898 | B7: Ăn trưa | C7: 30 | D7: Living expense | F7: 45915 | G7: Bảo gởi Gonsa | H7: 3000
B8: Nước | C8: 25 | D8: Living expense | G8: Khang help | H8: 2000
B9: Cầu lông | C9: 20 | D9: Living expense | F9: 45916 | G9: Ba má support | H9: 5000
B10: Ăn tối | C10: 112 | D10: Living expense | F10: 45921 | G10: Bảo Gonsa | H10: 500
A11: 45899 | B11: Ăn trưa | C11: 30 | D11: Living expense | G11: Ba má support | H11: 1000
B12: Grab | C12: 60 | D12: Living expense | F12: 45923 | G12: Jica bonus | H12: 4000
B13: Nước ngọt | C13: 10 | D13: Living expense | F13: Total earn | G13: =SUMIF(G2:G12, "<>Credit", H2:H9) -> 49045
B14: Ăn tối | C14: 61 | D14: Living expense | F14: Total spent | G14: =SUMIF(D2:D205, "<>Credit", C2:C513) + G15 -> 48896
A15: 45900 | B15: Grab | C15: 10 | D15: Living expense | F15: Untrack spent | G15: =-7+3+2+5+8+93-51+7 -> 60
B16: Bảo dưỡng xe Hồng Đức | C16: 1883 | D16: Buy | F16: Saving | G16: 0
B17: Jolibee | C17: 65 | D17: Living expense
B18: Tiền kết nhà thờ | C18: 20 | D18: Living expense | F18: Estimate remaining | G18: =G13-G14-J31 -> 149
B19: Ăn tối | C19: 27 | D19: Living expense | F19: Remaining without cost | G19: =G13-G14 -> 149
B20: Circle K | C20: 45 | D20: Living expense
A21: 45901 | B21: Netflix | C21: 273 | D21: Living expense | F21: Category | G21: Estimated | H21: Actual
B22: Ăn khuya | C22: 61 | D22: Living expense | F22: Living expense | G22: 5000 | H22: =SUMIF(D2:D128, "=Living expense",C2:C146)+G15 -> 6866
B23: Tiền nhà | C23: 3996 | D23: Rent
B24: Cho Má | C24: 5000 | D24: Parent | F24: Planned/actual spend per category of this month
B25: Tặng cô năm | C25: 200 | D25: Parent | F25: Category | G25: Estimated | H25: Actual | I25: Finalize | J25: Reserve
B26: Ăn trưa | C26: 60 | D26: Living expense | F26: Gonsa | G26: 5000 | H26: =SUMIF($D$2:$D$504, "=Gonsa",$C$2:$C$504) -> 5000 | I26: TRUE | J26: =IF(I26=TRUE,0,MAX(G26-H26,0)) -> 0
B27: Bảo Netflix | C27: -68 | D27: Living expense | F27: Rent | G27: 4000 | H27: =SUMIF($D$2:$D$504, "=Rent",$C$2:$C$504) -> 3996 | I27: TRUE | J27: =IF(I27=TRUE,0,MAX(G27-H27,0)) -> 0
B28: Tú Netflix | C28: -68 | D28: Living expense | F28: Parent | G28: 5000 | H28: =SUMIF($D$2:$D$504, "=Parent",$C$2:$C$504) -> 8019 | I28: TRUE | J28: =IF(I28=TRUE,0,MAX(G28-H28,0)) -> 0
B29: Vé phim Mưa đỏ | C29: 200 | D29: Buy | F29: Khang debt | G29: 3000 | H29: =SUMIF($D$2:$D$504, "=Khang debt",$C$2:$C$504) -> 3000 | I29: TRUE | J29: =IF(I29=TRUE,0,MAX(G29-H29,0)) -> 0
B30: Ăn tối | C30: 60 | D30: Living expense | F30: Credit debt | G30: 8193 | H30: =SUMIF($D$2:$D$504, "=Credit debt",$C$2:$C$504) -> 8310 | I30: TRUE | J30: =IF(I30=TRUE,0,MAX(G30-H30,0)) -> 0
B31: Kim Anh Netflix | C31: -68 | D31: Living expense | F31: Sum | G31: =SUM(G25:G30) -> 25193 | H31: =SUM(H25:H28) -> 17015 | J31: =SUM(J26:J30) -> 0
A32: 45902 | B32: Ăn trưa | C32: 60 | D32: Living expense
B33: Ăn tối | C33: 118 | D33: Living expense
A34: 45903 | B34: GS25 | C34: 26 | D34: Living expense
B35: Ăn tối | C35: 30 | D35: Living expense
B36: Bắp rang | C36: 43 | D36: Living expense
B37: Circle K | C37: 45 | D37: Living expense
A38: 45904 | B38: GS25 | C38: 20 | D38: Living expense
B39: Ăn tối | C39: 83 | D39: Living expense
B40: Điện Trà Vinh | C40: 385 | D40: Parent
B41: Naruto | C41: 117 | D41: Living expense
A42: 45905 | B42: Sữa Fami | C42: 25 | D42: Living expense
B43: Ăn trưa | C43: 60 | D43: Living expense
B44: Ăn tối | C44: 77 | D44: Living expense
A45: 45906 | B45: Ăn sáng | C45: 35 | D45: Living expense
B46: Ăn trưa | C46: 42 | D46: Living expense
B47: GS25 | C47: 14 | D47: Living expense
B48: Mua ghế Ngô Gia | C48: 700 | D48: Buy
B49: Ăn tối | C49: 88 | D49: Living expense
A50: 45907 | B50: Ăn trưa | C50: 40 | D50: Living expense
B51: 30Shine | C51: 389 | D51: Living expense
B52: Help Vương | C52: 500 | D52: Support
B53: Ăn tối | C53: 66 | D53: Living expense
A54: 45908 | B54: Ăn sáng | C54: 15 | D54: Living expense
B55: Đổ xăng | C55: 50 | D55: Living expense
B56: Phạt nước Rocket | C56: 100 | D56: Living expense
B57: Vương trả | C57: -500 | D57: Support
B58: Ăn chiều | C58: 88 | D58: Living expense
B59: Ăn vặt tối | C59: 72 | D59: Living expense
A60: 45909 | B60: Ăn sáng | C60: 13 | D60: Living expense
B61: GS25 | C61: 22 | D61: Living expense
B62: Cọc tiền nhà | C62: 6000 | D62: Credit
B63: Toàn trả | C63: -140 | D63: Living expense
B64: Ăn tối | C64: 40 | D64: Living expense
A65: 45910 | B65: GS25 | C65: 11 | D65: Living expense
B66: Ăn tối | C66: 120 | D66: Living expense
A67: 45911 | B67: Ăn sáng | C67: 15 | D67: Living expense
B68: Order nước | C68: 36 | D68: Living expense
B69: Trả Kienlongbank Credit | C69: 5500 | D69: Credit debt
B70: Ăn tối | C70: 65 | D70: Living expense
B71: Minecraft Superman | C71: 200 | D71: Buy
B72: Ăn vặt | C72: 65 | D72: Living expense
A73: 45912 | B73: Ăn trưa | C73: 29 | D73: Living expense
B74: Winmart+ | C74: 48 | D74: Living expense
B75: Nước thùng | C75: 60 | D75: Living expense
B76: Trả Khang | C76: 1500 | D76: Debt
B77: Góp Trung Thu | C77: 138 | D77: Buy
B78: Help Bảo | C78: 500 | D78: Support
A79: 45913 | B79: Ăn sáng | C79: 22 | D79: Living expense
B80: YouTube Premium | C80: 54 | D80: Living expense
B81: Ăn trưa | C81: 37 | D81: Living expense
B82: Ăn chiều | C82: 120 | D82: Living expense
A83: 45914 | B83: Ăn trưa | C83: 70 | D83: Living expense
B84: Ăn tối | C84: 71 | D84: Living expense
A85: 45915 | B85: Đậu nành | C85: 14 | D85: Living expense
B86: Toàn trả | C86: -70 | D86: Living expense
B87: Ăn tối | C87: 27 | D87: Living expense
B88: Circle K | C88: 41 | D88: Living expense
B89: Đổ xăng | C89: 45 | D89: Living expense
B90: Cọc tiền nhà + tiền nhà trọ mới T9 | C90: 9000 | D90: Credit
B91: Cọc tiền nhà + tiền nhà trọ mới T9 | C91: 3000 | D91: Buy
B92: Gonsa | C92: 5000 | D92: Gonsa
A93: 45916 | B93: Thùng giấy | C93: 75 | D93: Living expense
B94: Sữa Ensure | C94: 708 | D94: Parent
B95: GS25 | C95: 35 | D95: Living expense
B96: Ăn chiều | C96: =107-54 -> 53 | D96: Living expense
B97: Circle K | C97: 93 | D97: Living expense
A98: 45917 | B98: GS25 | C98: 14 | D98: Living expense
B99: Ăn tối | C99: =198-40-40-40-32 -> 46 | D99: Living expense
B100: Ăn khuya | C100: 91 | D100: Living expense
...

Sheet T82025
A1: DATE | B1: SPENT FOR | C1: AMOUNT | D1: TYPE | F1: DATE | G1: EARN BY | H1: AMOUNT
A2: 45868 | B2: Trả Khang | C2: 1000 | D2: Khang debt | F2: 45868 | G2: Cuối tháng 7 | H2: 46
B3: Credit shopee | C3: 243 | D3: Credit debt | G3: Lương tháng 7 | H3: 20000
B4: Help Kim Anh | C4: 2000 | D4: Support | F4: 45884 | G4: JICA Bonus | H4: 2000
B5: GS25 | C5: 26 | D5: Living expense | G5: Kienlong Bank Credit | H5: 3000
B6: FE cho Bảo | C6: 3569 | D6: FE debt
B7: Kienlong Bank debt | C7: 2850 | D7: Credit debt
B8: Ăn tối w/ Kim Anh | C8: 140 | D8: Living expense
B9: Circle K | C9: 23 | D9: Living expense
B10: Ăn khuya | C10: 77 | D10: Living expense
A11: 45869 | B11: Steam game | C11: 148 | D11: Living expense
B12: GS25 | C12: 13 | D12: Living expense
B13: Thuốc | C13: 20 | D13: Living expense | F13: Total earn | G13: =SUM(H2:H12) -> 25046
B14: Cơm payback | C14: -80 | D14: Living expense | F14: Total spent | G14: =SUMIF(D2:D205, "<>Credit", C2:C513) + G15 -> 24613
B15: Order nước | C15: =105-27 -> 78 | D15: Living expense | F15: Untrack spent | G15: =79+115 -> 194
B16: Shopee | C16: 115 | D16: Credit | F16: Saving | G16: 0
B17: Đổ xăng | C17: 55 | D17: Living expense
A18: 45870 | B18: Netflix | C18: =273-68-68 -> 137 | D18: Living expense | F18: Estimate remaining | G18: =G13-G14-J32 -> 433
B19: Trả cơm chung | C19: =140-33-33-33 -> 41 | D19: Living expense | F19: Remaining without cost | G19: =G13-G14 -> 433
B20: Trả nước chung | C20: =93-20-18-19 -> 36 | D20: Living expense
B21: Trả nước Team Rocket | C21: =146-96 -> 50 | D21: Living expense | F21: Category | G21: Estimated | H21: Actual
B22: Tiền trọ | C22: 4100 | D22: Rent | F22: Living expense | G22: 5000 | H22: =SUMIF(D2:D128, "=Living expense",C2:C146)+G15 -> 4743
B23: Cơm tối | C23: 58 | D23: Living expense
A24: 45871 | B24: Ăn sáng | C24: 15 | D24: Living expense | F24: Planned/actual spend per category of this month
B25: Cà phê | C25: 16 | D25: Living expense | F25: Category | G25: Estimated | H25: Actual | I25: Finalize | J25: Reserve
B26: Tú Netflix | C26: -68 | D26: Living expense | F26: Gonsa | G26: 3000 | H26: =SUMIF($D$2:$D$504, "=Gonsa",$C$2:$C$504) -> 5000 | I26: TRUE | J26: =IF(I26=TRUE,0,MAX(G26-H26,0)) -> 0
B27: Ăn trưa Rocket | C27: =89-32-33 -> 24 | D27: Living expense | F27: Rent | G27: 4000 | H27: =SUMIF($D$2:$D$504, "=Rent",$C$2:$C$504) -> 4100 | I27: TRUE | J27: =IF(I27=TRUE,0,MAX(G27-H27,0)) -> 0
B28: Cafe trưa Rocket | C28: =82-13-24-24 -> 21 | D28: Living expense | F28: Parent | G28: 2000 | H28: =SUMIF($D$2:$D$504, "=Parent",$C$2:$C$504) -> 3108 | I28: TRUE | J28: =IF(I28=TRUE,0,MAX(G28-H28,0)) -> 0
B29: Cơm chiều | C29: 40 | D29: Living expense | F29: FE debt | G29: 3569 | H29: =SUMIF($D$2:$D$504, "=FE debt",$C$2:$C$504) -> 3569 | I29: TRUE | J29: =IF(I29=TRUE,0,MAX(G29-H29,0)) -> 0
B30: Coffee | C30: 38 | D30: Living expense | F30: Khang debt | G30: 1000 | H30: =SUMIF($D$2:$D$504, "=Khang debt",$C$2:$C$504) -> 1000 | I30: TRUE | J30: =IF(I30=TRUE,0,MAX(G30-H30,0)) -> 0
B31: Kim Anh trả | C31: -1000 | D31: Support | F31: Credit debt | G31: =2850+243 -> 3093 | H31: =SUMIF($D$2:$D$504, "=Credit debt",$C$2:$C$504) -> 3093 | I31: TRUE | J31: =IF(I31=TRUE,0,MAX(G31-H31,0)) -> 0
A32: 45872 | B32: Nước | C32: 26 | D32: Living expense | F32: Sum | G32: =SUM(G25:G31) -> 16662 | H32: =SUM(H25:H28) -> 12208 | J32: =SUM(J26:J31) -> 0
B33: Ăn tối | C33: 111 | D33: Living expense
B34: Cho ba má | C34: 2000 | D34: Parent
A35: 45873 | B35: Điện Trà Vinh | C35: 272 | D35: Parent
B36: Order cơm | C36: =99-34-34 -> 31 | D36: Living expense
B37: GS25 | C37: 23 | D37: Living expense
A38: 45874 | B38: GS25 | C38: 13 | D38: Living expense
B39: Nước | C39: 23 | D39: Living expense
B40: Ăn tối | C40: 25 | D40: Living expense
A41: 45875 | B41: Sữa | C41: 26 | D41: Living expense
B42: Đóng quỹ + party Rocket | C42: 300 | D42: Living expense
B43: Ăn tối | C43: 53 | D43: Living expense
A44: 45876 | B44: Nước | C44: 18 | D44: Living expense
B45: Order cơm | C45: =159-37-42-37 -> 43 | D45: Living expense
B46: Fahasha | C46: 519 | D46: Credit
B47: Ăn tối | C47: 53 | D47: Living expense
A48: 45877 | B48: Cầu lông | C48: 40 | D48: Living expense
B49: Cơm nước w/ team | C49: =247-20-46-59-44-47 -> 31 | D49: Living expense
B50: Texas | C50: 108 | D50: Credit
B51: The 80s | C51: 38 | D51: Living expense
A52: 45878 | B52: Ăn sáng | C52: 15 | D52: Living expense
B53: Cơm nước w/ team | C53: =194-71-54 -> 69 | D53: Living expense
B54: Toàn help | C54: -5 | D54: Living expense
B55: Pizza | C55: 229 | D55: Credit
B56: Order LEGO | C56: 368 | D56: Credit
A57: 45879 | B57: Hớt tóc | C57: 178 | D57: Living expense
B58: Ăn chiều | C58: 30 | D58: Living expense
B59: Circle K | C59: 48 | D59: Living expense
B60: Ăn tối | C60: 61 | D60: Living expense
A61: 45880 | B61: Sữa | C61: 26 | D61: Living expense
B62: Order cơm | C62: =114-30-35 -> 49 | D62: Living expense
B63: Gym | C63: 30 | D63: Living expense
A64: 45881 | B64: GS25 | C64: 11 | D64: Living expense
B65: Đặt cơm | C65: =115-30-30 -> 55 | D65: Living expense
B66: Ăn tối | C66: 76 | D66: Living expense
A67: 45882 | B67: YouTube Premium | C67: 54 | D67: Living expense
B68: Ăn tối | C68: 40 | D68: Living expense
B69: GS25 | C69: 11 | D69: Living expense
A70: 45883 | B70: GS25 | C70: 14 | D70: Living expense
B71: Ăn tối | C71: 40 | D71: Living expense
B72: Circle K | C72: 63 | D72: Living expense
A73: 45884 | B73: Gonsa T8 | C73: 5000 | D73: Gonsa
B74: Kim Anh trả | C74: -1000 | D74: Support
B75: Cơm nước w/ team | C75: =94+55-46-52 -> 51 | D75: Living expense
B76: Ăn tối | C76: 56 | D76: Living expense
B77: Eleven Labs | C77: 149 | D77: Credit
A78: 45885 | B78: Ăn trưa | C78: =28+18 -> 46 | D78: Living expense
B79: GS25 | C79: 18 | D79: Living expense
B80: LEGO | C80: 835 | D80: Credit
B81: Jolibee | C81: 70 | D81: Living expense
A82: 45886 | B82: Rửa xe | C82: 25 | D82: Living expense
B83: Ăn trưa | C83: 30 | D83: Living expense
B84: Coffee | C84: 38 | D84: Living expense
B85: Pizza | C85: 150 | D85: Living expense
A86: 45887 | B86: GS25 | C86: 14 | D86: Living expense
B87: Order cơm | C87: =110-35-35 -> 40 | D87: Living expense
B88: Circle K | C88: 55 | D88: Living expense
B89: Gym | C89: 30 | D89: Living expense
B90: LEGO | C90: 537 | D90: Credit
A91: 45888 | B91: GS25 | C91: 62 | D91: Living expense
B92: Ăn tối | C92: 30 | D92: Living expense
B93: Nước Trà Vinh | C93: 36 | D93: Parent
A94: 45889 | B94: LEGO Batman game | C94: 123 | D94: Credit
B95: Ăn sáng + cà phê | C95: 35 | D95: Living expense
B96: GS15 | C96: 14 | D96: Living expense
B97: Ăn trưa | C97: 40 | D97: Living expense
B98: Ăn tối | C98: 30 | D98: Living expense
B99: Movie | C99: =172+39 -> 211 | D99: Living expense
A100: 45890 | B100: GS25 | C100: 22 | D100: Living expense
...

Sheet T72025
A1: DATE | B1: SPENT FOR | C1: AMOUNT | D1: TYPE | F1: DATE | G1: EARN BY | H1: AMOUNT
A2: 45835 | B2: Ăn sáng | C2: 15 | D2: Living expense | F2: 45835 | G2: Cuối tháng 6 | H2: 257
B3: Ăn trưa | C3: 75 | D3: Living expense | G3: Lương tháng 6 | H3: 20000
B4: Gởi thư | C4: 22 | D4: Living expense | F4: 45838 | G4: Bảo góp Gonsa | H4: 1000
B5: Circle K | C5: 94 | D5: Credit | F5: 45841 | G5: JICA Bonus | H5: 4000
B6: Chơi w/ Kim Anh | C6: 300 | D6: Living expense | F6: 45854 | G6: Bảo góp Gonsa | H6: 1500
B7: Trả Kim Anh | C7: 500 | D7: Debt | G7: Khang support | H7: 4000
B8: Trả Credit Kienlongbank T6 | C8: 435 | D8: Debt
B9: Trả Credit Kienlongbank | C9: -94 | D9: Credit
A10: 45836 | B10: Trả Khang | C10: 2000 | D10: Debt
B11: Saigonopoly | C11: =3328 -> 3328 | D11: Credit
B12: Ăn sáng w/ Kim Anh | C12: 42 | D12: Living expense
B13: Đồ chiên | C13: 65 | D13: Living expense | F13: Total earn | G13: =SUM(H2:H12) -> 30757
B14: Cho ba má | C14: 4000 | D14: Parent | F14: Total spent | G14: =SUMIF(D2:D199, "<>Credit", C2:C507) + G15 -> 30711
A15: 45837 | B15: Ăn sáng | C15: 30 | D15: Living expense | F15: Untrack spent | G15: =903+133 -> 1036
B16: Cafe | C16: 28 | D16: Living expense | F16: Saving | G16: 0
B17: Net | C17: 25 | D17: Living expense
B18: Cơm trưa | C18: 25 | D18: Living expense | F18: Estimate remaining | G18: =G13-G14-J30 -> 46
A19: 45838 | B19: Ăn sáng | C19: 15 | D19: Living expense | F19: Remaining without cost | G19: =G13-G14 -> 46
B20: Nước ngọt | C20: 14 | D20: Living expense
B21: Gym | C21: 30 | D21: Living expense | F21: Category | G21: Estimated | H21: Actual
B22: Order cơm | C22: 78 | D22: Living expense | F22: Living expense | G22: 5000 | H22: =SUMIF(D2:D122, "=Living expense",C2:C140)+G15 -> 5748
B23: Circle K | C23: 31 | D23: Living expense
B24: Help Vương | C24: 500 | D24: Support | F24: Planned/actual spend per category of this month
B25: Đồ đi du lịch | C25: 237 | D25: Credit | F25: Category | G25: Estimated | H25: Actual | I25: Finalize | J25: Reserve
A26: 45839 | B26: Bò kho | C26: 70 | D26: Living expense | F26: Gonsa | G26: 3000 | H26: =SUMIF(D3:D232, "=Gonsa",C3:C232) -> 5000 | I26: TRUE | J26: =IF(I26=TRUE,0,MAX(G26-H26,0)) -> 0
B27: Circle K | C27: 94 | D27: Living expense | F27: Rent | G27: 4000 | H27: =SUMIF(D4:D233, "=Rent",C4:C233) -> 4070 | I27: TRUE | J27: =IF(I27=TRUE,0,MAX(G27-H27,0)) -> 0
B28: Tiền nhà | C28: 4070 | D28: Rent | F28: Parent | G28: 3000 | H28: =SUMIF(D5:D234, "=Parent",C5:C234) -> 4296 | I28: TRUE | J28: =IF(I28=TRUE,0,MAX(G28-H28,0)) -> 0
B29: Help Kim Anh | C29: 1000 | D29: Support | F29: Trip | G29: 1700 | H29: =SUMIF(D5:D234, "=Trip",C5:C234) -> 1634 | I29: TRUE | J29: =IF(I29=TRUE,0,MAX(G29-H29,0)) -> 0
B30: Netflix | C30: 260 | D30: Living expense | F30: Sum | G30: =SUM(G25:G29) -> 11700 | H30: =SUM(H25:H29) -> 15000 | J30: =SUM(J26:J29) -> 0
A31: 45840 | B31: Tiền sân cho KA | C31: 20 | D31: Living expense
B32: Tiền bún trả Toàn | C32: 38 | D32: Living expense
B33: Order cơm | C33: =80-14-22 -> 44 | D33: Living expense
B34: Fahasha | C34: 25 | D34: Living expense
B35: Thuốc | C35: 43 | D35: Living expense
B36: Tạp hóa | C36: 30 | D36: Living expense
A37: 45841 | B37: Ăn sáng | C37: 15 | D37: Living expense
B38: Kim Anh trả | C38: -1000 | D38: Support
B39: Sữa chua | C39: =33-9 -> 24 | D39: Living expense
B40: Ăn tối | C40: 107 | D40: Living expense
B41: Coffee | C41: 38 | D41: Living expense
B42: Bò kho | C42: 35 | D42: Living expense
A43: 45842 | B43: The 80s với Kim Anh | C43: 73 | D43: Living expense
B44: Tú Netflix | C44: -85 | D44: Living expense
A45: 45843 | B45: Trả anh Khoa tiền ăn | C45: 54 | D45: Living expense
B46: Trả KA tiền thuốc, ăn | C46: 115 | D46: Living expense
B47: Nam Cát Tiên | C47: 1000 | D47: Trip
B48: Ăn trưa | C48: 69 | D48: Living expense
B49: Ăn tối | C49: 55 | D49: Living expense
A50: 45844 | B50: Ăn trưa | C50: 60 | D50: Living expense
B51: Ăn tối | C51: 62 | D51: Living expense
A52: 45845 | B52: Bọc bài, bọc truyện | C52: =86+44 -> 130 | D52: Living expense
B53: Sữa chua | C53: 22 | D53: Credit
B54: Ăn tối | C54: 30 | D54: Living expense
B55: Gym card | C55: 300 | D55: Special
B56: Ăn khuya | C56: 69 | D56: Living expense
A57: 45846 | B57: Ăn sáng | C57: 22 | D57: Living expense
B58: Quỹ Rocket + party | C58: 200 | D58: Special
B59: Thuốc | C59: 90 | D59: Special
B60: Nước | C60: 12 | D60: Living expense
B61: Order cơm | C61: =147-30-30 -> 87 | D61: Living expense
B62: Điện Trà Vinh | C62: 251 | D62: Parent
B63: Help Bảo | C63: 1000 | D63: Support
B64: Steam game | C64: 95 | D64: Credit
A65: 45847 | B65: Ăn sáng | C65: 31 | D65: Living expense
B66: Nước ngọt | C66: 14 | D66: Living expense
B67: Đặt vé phim nhóm | C67: =422+84-85-85-85-85-85 -> 81 | D67: Living expense
B68: Ăn tối | C68: 60 | D68: Living expense
B69: Đổ xăng | C69: 40 | D69: Living expense
A70: 45848 | B70: Order cơm | C70: =172-37-49-51 -> 35 | D70: Living expense
B71: Nước rạp phim | C71: 39 | D71: Living expense
B72: Circle K | C72: 49 | D72: Living expense
B73: Vương trả | C73: -500 | D73: Support
A74: 45849 | B74: Trả cơm nước nhóm | C74: =175+132-61-59-75-59 -> 53 | D74: Living expense
B75: Đặt vé phim w/ KA | C75: 180 | D75: Living expense
B76: Mua đồ bv da | C76: 159 | D76: Special
B77: Thuốc | C77: 54 | D77: Special
B78: Circle K | C78: 72 | D78: Credit
B79: YouTube Premium | C79: 54 | D79: Living expense
A80: 45850 | B80: Nước ngọt | C80: 20 | D80: Trip
B81: Ăn vặt trạm dừng chân | C81: 80 | D81: Trip
A82: 45851 | B82: Ăn trưa w/ Kim Anh | C82: 75 | D82: Living expense
B83: Tiền đi NCT | C83: 459 | D83: Trip
B84: Ăn tối | C84: 69 | D84: Living expense
B85: Nước ngọt | C85: 10 | D85: Living expense
B86: KA trả tiền đi chơi | C86: -100 | D86: Living expense
A87: 45852 | B87: Ăn trưa | C87: 40 | D87: Living expense
B88: Nước ngọt | C88: 14 | D88: Living expense
B89: Tiền NCT | C89: =10+65 -> 75 | D89: Trip
B90: Order cơm chiều | C90: =100-35 -> 65 | D90: Living expense
B91: Tạp hóa | C91: 110 | D91: Living expense
A92: 45853 | B92: Gonsa | C92: 5000 | D92: Gonsa
B93: Order cơm | C93: =114-45-45 -> 24 | D93: Living expense
B94: Ăn tối | C94: 25 | D94: Living expense
A95: 45854 | B95: Tiền cầu cho KA | C95: 20 | D95: Living expense
B96: Ăn trưa | C96: 40 | D96: Living expense
B97: Nước ngọt | C97: 14 | D97: Living expense
B98: Trả FE cho Bảo | C98: 4000 | D98: Support
B99: Fahasha | C99: 128 | D99: Living expense
B100: Order cơm | C100: =89-48 -> 41 | D100: Living expense
...

Sheet T62025
A1: DATE | B1: SPENT FOR | C1: AMOUNT | D1: TYPE | F1: DATE | G1: EARN BY | H1: AMOUNT
A2: 45806 | B2: Ăn sáng | C2: 15 | D2: Living expense | F2: 45806 | G2: Cuối tháng 5 | H2: 68
B3: Shopee (air purifier) | C3: 1400 | D3: Buy | G3: Lương tháng 5 | H3: 20000
B4: Khang | C4: 1000 | D4: Debt | F4: 45823 | G4: Bảo GONSA | H4: 500
B5: Order cơm | C5: 155 | D5: Living expense | G5: Khang support | H5: 2000
B6: Khoa payback | C6: -41 | D6: Living expense | F6: 45832 | G6: Kim Anh support | H6: 500
B7: Thiên payback | C7: -73 | D7: Living expense
B8: Toàn payback | C8: -34 | D8: Living expense
A9: 45807 | B9: Ăn sáng | C9: 15 | D9: Living expense
B10: Ăn trưa | C10: 41 | D10: Living expense
B11: Winmart+ | C11: 72 | D11: Living expense
B12: Ăn tối | C12: 77 | D12: Living expense
A13: 45808 | B13: The 80s Coffee | C13: 38 | D13: Living expense | F13: Total earn | G13: =SUM(H2:H12) -> 23068
B14: Ăn trưa | C14: 42 | D14: Living expense | F14: Total spent | G14: =SUMIF(D2:D194, "<>Credit", C2:C502) + G15 -> 22811
B15: Ăn chiều | C15: 25 | D15: Living expense | F15: Minor spent | G15: =489 -> 489
B16: Cho ba má | C16: 4015 | D16: Parent | F16: Saving | G16: 0
A17: 45809 | B17: Ăn sáng | C17: 22 | D17: Living expense
B18: Ăn trưa | C18: 58 | D18: Living expense | F18: Estimate remaining | G18: =G13-G14-J29 -> 257
B19: Netflix | C19: 260 | D19: Living expense | F19: Remaining without cost | G19: =G13-G14 -> 257
B20: Winmart+ | C20: 50 | D20: Living expense
B21: Huy Netflix | C21: -65 | D21: Living expense | F21: Category | G21: Estimated | H21: Actual
B22: Tiền trọ | C22: 4182 | D22: Rent | F22: Living expense | G22: 5000 | H22: =SUMIF(D2:D117, "=Living expense",C2:C135)+G15 -> 4421
B23: Kim Anh Netflix | C23: -65 | D23: Living expense
A24: 45810 | B24: Ăn sáng | C24: 15 | D24: Living expense | F24: Planned/actual spend per category of this month
B25: Tú Netflix | C25: -65 | D25: Living expense | F25: Category | G25: Estimated | H25: Actual | I25: Finalize | J25: Reserve
B26: Ăn tối | C26: 62 | D26: Living expense | F26: Gonsa | G26: 5000 | H26: =SUMIF(D3:D227, "=Gonsa",C3:C227) -> 5000 | I26: TRUE | J26: =IF(I26=TRUE,0,MAX(G26-H26,0)) -> 0
A27: 45811 | B27: Winmart+ | C27: 31 | D27: Living expense | F27: Rent | G27: 4000 | H27: =SUMIF(D4:D228, "=Rent",C4:C228) -> 4182 | I27: TRUE | J27: =IF(I27=TRUE,0,MAX(G27-H27,0)) -> 0
B28: Trả Tú tiền nước | C28: 23 | D28: Living expense | F28: Parent | G28: 3000 | H28: =SUMIF(D5:D229, "=Parent",C5:C229) -> 5200 | I28: TRUE | J28: =IF(I28=TRUE,0,MAX(G28-H28,0)) -> 0
B29: Điện Trà Vinh | C29: 296 | D29: Parent | F29: Sum | G29: =SUM(G25:G28) -> 12000 | H29: =SUM(H25:H28) -> 14382 | J29: =SUM(J26:J28) -> 0
B30: Order cơm | C30: 102 | D30: Living expense
A31: 45812 | B31: Đánh cầu | C31: 15 | D31: Living expense
B32: Ăn trưa | C32: 35 | D32: Living expense
B33: Order Highlands | C33: 232 | D33: Living expense
B34: Team payback Highlands | C34: -201 | D34: Living expense
B35: Texas | C35: 119 | D35: Living expense
B36: Vớ | C36: 30 | D36: Living expense
B37: Fahasha | C37: 25 | D37: Living expense
B38: Bọc bài | C38: 90 | D38: Living expense
A39: 45813 | B39: Ăn sáng | C39: 15 | D39: Living expense
B40: Ăn trưa | C40: 40 | D40: Living expense
B41: Texas | C41: 94 | D41: Living expense
B42: Help Vương | C42: 1500 | D42: Support
A43: 45814 | B43: Ăn sáng | C43: 15 | D43: Living expense
B44: Cơm nước trưa | C44: 53 | D44: Living expense
B45: Ăn tối | C45: 59 | D45: Living expense
A46: 45815 | B46: Ăn sáng | C46: 15 | D46: Living expense
B47: Đổ xăng | C47: 45 | D47: Living expense
B48: Bún nước lèo | C48: 30 | D48: Living expense
B49: Fahasha | C49: 22 | D49: Living expense
B50: Pozza | C50: 32 | D50: Living expense
B51: Help Bảo | C51: 600 | D51: Support
B52: Bột chiên | C52: 30 | D52: Living expense
B53: Vương trả | C53: -1500 | D53: Support
A54: 45816 | B54: Ensure | C54: 889 | D54: Parent
B55: Giá đựng giày | C55: 73 | D55: Buy
B56: Jolibee | C56: 135 | D56: Living expense
B57: Đổ xăng | C57: 50 | D57: Living expense
B58: Fahasha (Superman) | C58: 179 | D58: Living expense
B59: Fahasha (Zodiac Rush) | C59: 439 | D59: Buy
B60: Ăn tối | C60: 75 | D60: Living expense
A61: 45817 | B61: Ăn sáng | C61: 15 | D61: Living expense
B62: Áo cầu lông | C62: 162 | D62: Buy
B63: Order cơm | C63: 105 | D63: Living expense
B64: Order cơm payback | C64: =-(34+18) -> -52 | D64: Living expense
A65: 45818 | B65: Phí cầu lông | C65: 100 | D65: Living expense
B66: Order cơm | C66: 103 | D66: Living expense
B67: Order cơm payback | C67: =-34-34 -> -68 | D67: Living expense
A68: 45819 | B68: Nước ngọt | C68: 14 | D68: Living expense
B69: Ăn chiều | C69: 47 | D69: Living expense
B70: Winmart+ | C70: 101 | D70: Living expense
B71: YouTube Premium | C71: 51 | D71: Living expense
A72: 45820 | B72: Ăn sáng | C72: 15 | D72: Living expense
B73: Ăn tối | C73: 47 | D73: Living expense
A74: 45821 | B74: Order cơm /nước | C74: =245+164 -> 409 | D74: Living expense
B75: Cơm/nước payback | C75: =-(26+54+70+50+53+54) -> -307 | D75: Living expense
B76: Ăn tối | C76: 51 | D76: Living expense
B77: Cầu lông | C77: 20 | D77: Living expense
B78: Trả a Khoa (cháo) | C78: 20 | D78: Living expense
A79: 45822 | B79: Ăn sáng | C79: 18 | D79: Living expense
B80: The 80 Coffee | C80: 38 | D80: Living expense
B81: Ăn trưa | C81: 51 | D81: Living expense
B82: Ăn chiều | C82: 30 | D82: Living expense
B83: Winmart+ | C83: 75 | D83: Living expense
B84: Vinaphone | C84: 50 | D84: Living expense
A85: 45823 | B85: Ăn trưa | C85: 47 | D85: Living expense
B86: Gonsa | C86: 5000 | D86: Gonsa
B87: Texas | C87: 124 | D87: Living expense
B88: The 80 Coffee | C88: 35 | D88: Living expense
A89: 45824 | B89: Ăn trưa | C89: 35 | D89: Living expense
B90: Nước ngọt | C90: 14 | D90: Living expense
B91: Thiên payback | C91: -39 | D91: Living expense
B92: Order cơm | C92: 44 | D92: Living expense
A93: 45825 | B93: Ăn sáng | C93: 15 | D93: Living expense
B94: Nước Trà Vinh | C94: 45 | D94: Living expense
B95: Order nước | C95: 24 | D95: Living expense
B96: Order cơm | C96: =46+49 -> 95 | D96: Living expense
B97: Game | C97: 24 | D97: Living expense
B98: Vé phim | C98: 46 | D98: Living expense
A99: 45826 | B99: Ăn sáng | C99: 22 | D99: Living expense
B100: Help Bảo | C100: 100 | D100: Support
...

Sheet T52025
A1: DATE | B1: SPENT FOR | C1: AMOUNT | D1: TYPE | F1: DATE | G1: EARN BY | H1: AMOUNT
A2: 45776 | B2: Ăn sáng | C2: 22 | D2: Living expense | F2: 45776 | G2: Cuối tháng 4 | H2: =4837+59 -> 4896
B3: Ăn tối | C3: 37 | D3: Living expense | G3: Lương tháng 4 | H3: 20000
B4: Shopee (Pay later) | C4: 265 | D4: Buy | G4: Bảo support | H4: 200
B5: Nước | C5: 28 | D5: Living expense | F5: 45800 | G5: Khang support | H5: 1000
A6: 45777 | B6: Ăn khuya | C6: 63 | D6: Living expense | F6: 45803 | G6: Bảo support | H6: 200
B7: Bún bò | C7: 30 | D7: Living expense
B8: Circle K | C8: 46 | D8: Living expense
B9: Ăn tối | C9: 83 | D9: Living expense
A10: 45778 | B10: Netflix | C10: 260 | D10: Living expense
B11: Bàn + giá đỡ laptop (shopee) | C11: 222 | D11: Buy
B12: Trả Khang | C12: 3000 | D12: Debt
B13: Ăn trưa | C13: 85 | D13: Living expense | F13: Total earn | G13: =SUM(H2:H12) -> 26296
B14: Đổ xăng | C14: 55 | D14: Living expense | F14: Total spent | G14: =SUM(C2:C206) + G15 -> 26228
B15: Tiền trọ | C15: 4305 | D15: Rent | F15: Minor spent | G15: =4+100+1+543+6+6+1-50 -> 611
B16: Tú Netflix | C16: -65 | D16: Living expense | F16: Saving | G16: 0
B17: Kim Anh Netflix | C17: -65 | D17: Living expense
B18: Kim Anh support tiền trọ | C18: -100 | D18: Living expense | F18: Estimate remaining | G18: =G13-G14-($G29-$H29) -> 68
B19: Ăn tối | C19: 61 | D19: Living expense | F19: Remaining without cost | G19: =G13-G14 -> 68
A20: 45779 | B20: Cơm trưa | C20: 32 | D20: Living expense
B21: Texas | C21: 134 | D21: Living expense | F21: Category | G21: Estimated | H21: Actual
B22: Circle K | C22: 28 | D22: Living expense | F22: Living expense | G22: 5000 | H22: =SUMIF(D2:D200, "=Living expense",C2:C200)+G15 -> 5541
A23: 45780 | B23: Cơm gà | C23: 40 | D23: Living expense
B24: Cho má | C24: 4000 | D24: Parent | F24: Planned/actual spend per category of this month
B25: Cơm chiều | C25: 45 | D25: Living expense | F25: Category | G25: Estimated | H25: Actual
B26: Winmart+ | C26: 33 | D26: Living expense | F26: Gonsa | G26: 5000 | H26: =SUMIF(D3:D216, "=Gonsa",C3:C216) -> 5000
B27: Thuốc | C27: 190 | D27: Living expense | F27: Rent | G27: 4305 | H27: =SUMIF(D4:D217, "=Rent",C4:C217) -> 4305
B28: Vé phim | C28: 77 | D28: Living expense | F28: Parent | G28: 5665 | H28: =SUMIF(D5:D218, "=Parent",C5:C218) -> 5665
A29: 45781 | B29: Bún bò | C29: 30 | D29: Living expense | F29: Sum | G29: =SUM(G25:G28) -> 14970 | H29: =SUM(H25:H28) -> 14970
B30: Nước ngọt | C30: 39 | D30: Living expense
B31: Tiền kết | C31: 10 | D31: Living expense
B32: Cơm chiều | C32: 25 | D32: Living expense
A33: 45782 | B33: Ăn sáng | C33: 20 | D33: Living expense
B34: GS25 | C34: 14 | D34: Living expense
B35: Thuốc | C35: 25 | D35: Living expense
B36: Bách hóa Xanh | C36: 76 | D36: Living expense
B37: Cơm chiều | C37: 60 | D37: Living expense
A38: 45783 | B38: Ăn trưa | C38: 35 | D38: Living expense
B39: Ăn chiều | C39: 35 | D39: Living expense
B40: Winmart+ | C40: 88 | D40: Living expense
B41: Headphone | C41: 1029 | D41: Buy
A42: 45784 | B42: GS25 | C42: 14 | D42: Living expense
B43: Cơm chiều | C43: 57 | D43: Living expense
B44: Help Vương | C44: 1500 | D44: Support
A45: 45785 | B45: GS25 | C45: 22 | D45: Living expense
B46: Cơm chiều | C46: 57 | D46: Living expense
B47: Blue Prince (Game) | C47: 395 | D47: Living expense
B48: Winmart+ | C48: 38 | D48: Living expense
A49: 45786 | B49: Ăn trưa | C49: 60 | D49: Living expense
B50: Ăn tối | C50: 57 | D50: Living expense
B51: Ăn tối (chờ hoàn tiền) | C51: 68 | D51: Living expense
A52: 45787 | B52: Ăn sáng | C52: 15 | D52: Living expense
B53: The 80 | C53: 38 | D53: Living expense
B54: Nước suối | C54: 6 | D54: Living expense
B55: Đổ xăng | C55: 50 | D55: Living expense
B56: Đồ chiên | C56: 62 | D56: Living expense
B57: Siêu thị GO! | C57: 915 | D57: Parent
B58: Winmart+ | C58: 18 | D58: Living expense
A59: 45788 | B59: Rửa xe | C59: 25 | D59: Living expense
B60: Cafe 24h | C60: 58 | D60: Living expense
B61: Bánh khoai | C61: 15 | D61: Living expense
B62: Bách hóa Xanh | C62: 54 | D62: Living expense
B63: Điện Trà Vinh | C63: 320 | D63: Parent
B64: Clair Obscur: Expedition 33 | C64: 780 | D64: Buy
B65: YouTube | C65: 52 | D65: Living expense
A66: 45789 | B66: Ngọc Yến 3 | C66: 72 | D66: Living expense
B67: Khám bệnh cho Má | C67: 430 | D67: Parent
B68: Ăn chiều | C68: 57 | D68: Living expense
A69: 45790 | B69: Ăn sáng | C69: 15 | D69: Living expense
B70: GS25 | C70: 33 | D70: Living expense
B71: Order cơm | C71: 161 | D71: Living expense
B72: Thiên payback | C72: -49 | D72: Living expense
B73: Grab | C73: 16 | D73: Living expense
A74: 45791 | B74: Grab | C74: 16 | D74: Living expense
B75: Khoa payback | C75: -32 | D75: Living expense
B76: Vương trả | C76: -1000 | D76: Support
B77: Help Kim Anh 3G | C77: 20 | D77: Support
B78: Toàn payback | C78: -50 | D78: Living expense
B79: Phí BIDV | C79: 52 | D79: Living expense
A80: 45792 | B80: Vương trả | C80: -500 | D80: Living expense
B81: Ăn sáng | C81: 15 | D81: Living expense
B82: VNPay hoàn tiền | C82: -68 | D82: Living expense
B83: Order food | C83: 71 | D83: Living expense
B84: Gonsa | C84: 5000 | D84: Gonsa
B85: Khoai mỡ | C85: 30 | D85: Living expense
B86: Help A Bảo | C86: -300 | D86: Support
A87: 45793 | B87: Cơm trưa nhóm | C87: 534 | D87: Living expense
B88: Cơm trưa payback | C88: =-313-76 -> -389 | D88: Living expense
B89: Order API | C89: 376 | D89: Support
B90: Thiên payback | C90: -155 | D90: Support
B91: Team payback | C91: -221 | D91: Living expense
B92: Texas | C92: 94 | D92: Living expense
A93: 45794 | B93: Cơm gà Kim | C93: 57 | D93: Living expense
B94: Winmart+ | C94: 48 | D94: Living expense
B95: Snack | C95: 25 | D95: Living expense
A96: 45795 | B96: Ăn sáng | C96: 15 | D96: Living expense
B97: Ăn trưa | C97: 59 | D97: Living expense
B98: 30Shine | C98: 190 | D98: Living expense
B99: Ăn tối | C99: 52 | D99: Living expense
B100: Kim Anh payback | C100: -20 | D100: Support
...

Sheet T42025
A1: DATE | B1: SPENT FOR | C1: AMOUNT | D1: TYPE | F1: DATE | G1: EARN BY | H1: AMOUNT
A2: 45744 | B2: Fahasha (Minecraft cards) | C2: 547 | D2: Living expense | F2: 45744 | G2: Cuối tháng 3 | H2: 8
B3: Thuốc | C3: 28 | D3: Living expense | F3: 45745 | G3: Lương tháng 3 | H3: 20000
B4: Circle K | C4: 54 | D4: Living expense | F4: 45751 | G4: Ba support | H4: 2000
B5: Trả Khang | C5: 2200 | D5: Debt | G5: Bảo trả | H5: 500
A6: 45745 | B6: Ăn sáng | C6: 20 | D6: Living expense | F6: 45754 | G6: Ba support | H6: 2000
B7: Nước suối | C7: 7 | D7: Living expense | F7: 45755 | G7: Hold for Khang | H7: 593
B8: Circle K | C8: 85 | D8: Living expense | F8: 45762 | G8: Khang support | H8: 3000
B9: Texas | C9: 159 | D9: Living expense | F9: 45764 | G9: Thầy trả thuế | H9: 3435
B10: Minecraft cards x4 | C10: 196 | D10: Buy | F10: 45767 | G10: Ba support | H10: 1000
B11: Help Khôi | C11: 1000 | D11: Support | F11: 45771 | G11: Bảo support | H11: 200
A12: 45746 | B12: Ăn sáng | C12: 60 | D12: Living expense | F12: 45772 | G12: JICA bonus | H12: 4000
B13: Movie | C13: 457 | D13: Living expense | F13: Total earn | G13: =SUM(H2:H12) -> 36736
B14: Ăn trưa | C14: 165 | D14: Living expense | F14: Total spent | G14: =SUM(C2:C201) + G15 -> 34710
B15: Bắp | C15: 83 | D15: Living expense | F15: Minor spent | G15: =240 -> 240
B16: Pizza | C16: 259 | D16: Living expense | F16: Saving | G16: 0
A17: 45747 | B17: Ăn sáng | C17: 20 | D17: Living expense
B18: GS25 | C18: 14 | D18: Living expense | F18: Estimate remaining | G18: =G13-G14-($G30-$H30) -> 2026
B19: Texas | C19: 98 | D19: Living expense | F19: Remaining without cost | G19: =G13-G14 -> 2026
B20: Su kem | C20: 40 | D20: Living expense
B21: Netflix | C21: 260 | D21: Living expense | F21: Category | G21: Estimated | H21: Actual
A22: 45748 | B22: GS25 | C22: 23 | D22: Living expense | F22: Living expense | G22: 5000 | H22: =SUMIF(D2:D100, "=Living expense",C2:C118) -> 5695
B23: Rocket fee | C23: 330 | D23: Living expense
B24: GS25 | C24: 42 | D24: Living expense | F24: Planned/actual spend per category of this month
B25: Tú Netflix | C25: -65 | D25: Living expense | F25: Category | G25: Estimated | H25: Actual
B26: Bún bò | C26: 60 | D26: Living expense | F26: Laptop | G26: 3221 | H26: =SUMIF(D3:D211, "=Laptop",C3:C211) -> 3221
B27: Snow White | C27: 128 | D27: Living expense | F27: Gonsa | G27: 5000 | H27: =SUMIF(D4:D212, "=Gonsa",C4:C212) -> 5000
B28: Nước rạp phim | C28: 78 | D28: Living expense | F28: Rent | G28: 4083 | H28: =SUMIF(D5:D213, "=Rent",C5:C213) -> 4083
B29: Circle K | C29: 35 | D29: Living expense | F29: Parent | G29: 2000 | H29: =SUMIF(D5:D213, "=Parent",C5:C213) -> 4667
B30: Tiền nhà | C30: 4083 | D30: Rent | F30: Tax | G30: 3435 | H30: =SUMIF(D5:D213, "=Tax",C5:C213) -> 3435
B31: Kim Anh Netflix | C31: -65 | D31: Living expense | F31: Sum | G31: =SUM(G25:G30) -> 17739 | H31: =SUM(H25:H30) -> 20406
B32: Kim Anh support | C32: -510 | D32: Living expense
A33: 45749 | B33: Laptop | C33: 3221 | D33: Laptop
B34: GS25 | C34: 48 | D34: Living expense
B35: Khoa payback | C35: -23 | D35: Living expense
B36: Ăn tối | C36: 72 | D36: Living expense
B37: Minecraft cards x4 | C37: 196 | D37: Buy
A38: 45750 | B38: Help Vương | C38: 1000 | D38: Support
B39: GS25 | C39: 26 | D39: Living expense
B40: Texas | C40: 301 | D40: Living expense
B41: GO | C41: 55 | D41: Living expense
B42: Nước ngọt | C42: 10 | D42: Living expense
B43: Điện lực Trà Vinh | C43: 200 | D43: Parent
A44: 45751 | B44: Gỏi cuốn | C44: 18 | D44: Living expense
B45: Đổ xăng | C45: 55 | D45: Living expense
B46: Ăn tối | C46: 60 | D46: Living expense
B47: Vương trả | C47: -1000 | D47: Support
A48: 45752 | B48: Vé một bộ phim Minecraft | C48: 314 | D48: Living expense
B49: Yame | C49: 448 | D49: Living expense
B50: Đám cưới Như 💍 | C50: 1000 | D50: Buy
B51: Hớt tóc | C51: 150 | D51: Living expense
B52: Bột chiên | C52: 64 | D52: Living expense
B53: Nhà thờ | C53: 20 | D53: Living expense
B54: GO | C54: 832 | D54: Parent
B55: Winmart+ | C55: 55 | D55: Living expense
B56: Minecraft cards x4 | C56: 196 | D56: Buy
A57: 45753 | B57: Cơm trưa | C57: 30 | D57: Living expense
B58: Trung Nguyên Legend | C58: 69 | D58: Living expense
B59: Help Vương | C59: 500 | D59: Support
B60: Phụ thu movie | C60: 10 | D60: Living expense
B61: Ăn tối | C61: 35 | D61: Living expense
A62: 45754 | B62: Ăn trưa | C62: 30 | D62: Living expense
B63: Pozza | C63: 39 | D63: Living expense
B64: Cho má | C64: 2000 | D64: Parent
B65: Texas | C65: 124 | D65: Living expense
B66: Đổ xăng | C66: 55 | D66: Living expense
B67: Xu kem | C67: 20 | D67: Living expense
B68: Help Khôi | C68: 250 | D68: Support
A69: 45755 | B69: GS25 | C69: 14 | D69: Living expense
B70: Texas | C70: 55 | D70: Living expense
B71: GS25 (Evening) | C71: 44 | D71: Living expense
B72: Help Bảo | C72: 500 | D72: Support
A73: 45756 | B73: Ăn sáng | C73: 40 | D73: Living expense
B74: Khang package | C74: 341 | D74: Living expense
B75: GS25 | C75: 26 | D75: Living expense
B76: Ăn chiều | C76: 61 | D76: Living expense
A77: 45757 | B77: GS25 | C77: 14 | D77: Living expense
B78: Texas | C78: 73 | D78: Living expense
B79: Vương trả | C79: -500 | D79: Living expense
B80: Vương vé phim | C80: -100 | D80: Living expense
A81: 45758 | B81: Circle K | C81: 21 | D81: Living expense
B82: Ăn tối | C82: 136 | D82: Living expense
B83: Toàn trả | C83: 65 | D83: Living expense
B84: Vinaphone | C84: 50 | D84: Living expense
B85: Youtube Premium | C85: 51 | D85: Living expense
A86: 45759 | B86: Ăn trưa | C86: 40 | D86: Living expense
B87: Circle K | C87: 65 | D87: Living expense
B88: Minecraft pack x4 | C88: 196 | D88: Buy
B89: Gift | C89: 159 | D89: Living expense
B90: Texas | C90: 55 | D90: Living expense
B91: Bánh papa | C91: 20 | D91: Living expense
A92: 45760 | B92: Gỏi cuốn | C92: 30 | D92: Living expense
B93: Circle K | C93: 60 | D93: Living expense
B94: Nhã thy | C94: 60 | D94: Living expense
B95: Đổ xăng | C95: 50 | D95: Living expense
B96: Pizza Hut | C96: 223 | D96: Living expense
B97: Ensure Gold | C97: 635 | D97: Parent
A98: 45761 | B98: GS25 | C98: 14 | D98: Living expense
B99: Circle K | C99: 31 | D99: Living expense
A100: 45762 | B100: Khôi trả | C100: -1000 | D100: Support
...

Sheet T32025
A1: DATE | B1: SPENT FOR | C1: AMOUNT | D1: TYPE | F1: DATE | G1: EARN BY | H1: AMOUNT
A2: 45715 | B2: GS25 | C2: 14 | D2: Living expense | F2: 45715 | G2: Cuối tháng 2 | H2: 40
B3: Lotte | C3: 50 | D3: Living expense | G3: Lương tháng 2 | H3: 20000
B4: Jolibee | C4: 70 | D4: Living expense | F4: 45716 | G4: JICA bonus | H4: 3000
A5: 45716 | B5: Sữa | C5: 26 | D5: Living expense | F5: 45731 | G5: Khang help | H5: 2000
B6: Ăn trưa | C6: 42 | D6: Living expense | G6: Kim Anh trả | H6: 500
B7: GS25 | C7: 14 | D7: Living expense | F7: 45731 | G7: Bảo support | H7: 200
B8: Texas | C8: 94 | D8: Living expense | F8: 45732 | G8: Kim Anh trả | H8: 300
A9: 45717 | B9: Netflix | C9: 260 | D9: Living expense | F9: 45738 | G9: Ba support | H9: 1000
B10: Ăn sáng | C10: 63 | D10: Living expense | F10: 45742 | G10: Bảo support | H10: 250
B11: Help Khôi | C11: 2500 | D11: Loan | F11: 45743 | G11: Bảo support | H11: 100
B12: Ăn chiều | C12: 30 | D12: Living expense
B13: Hồng trà | C13: 22 | D13: Living expense | F13: Total earn | G13: =SUM(H2:H12) -> 27390
B14: Ăn tối | C14: 64 | D14: Living expense | F14: Total spent | G14: =SUMIF(D2:D192, "<>Credit", C2:C192) + G15 -> 27382
B15: Tiền nhà | C15: 3873 | D15: Rent | F15: Minor spent | G15: =11+20+4-212 -> -177
A16: 45718 | B16: Bánh mì K | C16: 19 | D16: Living expense | F16: Saving | G16: 0
B17: Đổ xăng | C17: 42 | D17: Living expense
B18: Ăn bún | C18: 55 | D18: Living expense | F18: Estimate remaining | G18: =G13-G14-($G30-$H30) -> 22503
B19: Quán nước | C19: 32 | D19: Living expense | F19: Remaining without cost | G19: =G13-G14 -> 8
B20: Cho ba | C20: 1500 | D20: Parent
B21: Trả Khang | C21: 2000 | D21: Debt | F21: Category | G21: Estimated | H21: Actual
B22: Ăn tối | C22: 50 | D22: Living expense | F22: Living expense | G22: 5000 | H22: =SUMIF(D2:D95, "=Living expense",C2:C113) -> 5941
B23: Help Vương | C23: 500 | D23: Living expense
B24: Cho Má | C24: 1000 | D24: Parent | F24: Planned/actual spend per category of this month
A25: 45719 | B25: Pozza w/ Vương | C25: 71 | D25: Living expense | F25: Category | G25: Estimated | H25: Actual
B26: Ăn tối w/ Má | C26: 50 | D26: Living expense | F26: Laptop | G26: 3221 | H26: =SUMIF(D3:D202, "=Laptop",C3:C202) -> 3221
B27: Vương trả | C27: -500 | D27: Living expense | F27: Gonsa | G27: 5000 | H27: =SUMIF(D4:D203, "<>Credit",C4:C203) -> 27495
B28: Ăn tối | C28: 64 | D28: Living expense | F28: Rent | G28: 3873 | H28: =SUMIF(D5:D204, "=Rent",C5:C204) -> 3873
B29: Điện lực Trà Vinh | C29: 82 | D29: Living expense | F29: Parent | G29: 2800 | H29: =SUMIF(D5:D204, "=Parent",C5:C204) -> 2800
B30: Laptop | C30: 3221 | D30: Laptop | F30: Sum | G30: =SUM(G24:G29) -> 14894 | H30: =SUM(H24:H29) -> 37389
B31: Tú Netflix | C31: -65 | D31: Living expense
B32: Kim Anh Netflix | C32: -65 | D32: Living expense
A33: 45720 | B33: Ăn sáng | C33: 35 | D33: Living expense
B34: Huy Netflix | C34: -65 | D34: Living expense
B35: Ăn chiều | C35: 94 | D35: Living expense
A36: 45721 | B36: Ăn trưa | C36: 75 | D36: Living expense
B37: Đổ xăng | C37: 50 | D37: Living expense
A38: 45722 | B38: Ăn trưa | C38: 64 | D38: Living expense
B39: Lắp màn cửa | C39: 480 | D39: House
B40: Ăn tối | C40: 84 | D40: Living expense
B41: Cho ba | C41: 300 | D41: Parent
A42: 45723 | B42: Circle K | C42: 83 | D42: Living expense
B43: Gỏi cuốn | C43: 30 | D43: Living expense
B44: Pizza Hut | C44: 229 | D44: Living expense
A45: 45724 | B45: Ăn chiều | C45: 30 | D45: Living expense
B46: Popeyes | C46: 105 | D46: Living expense
A47: 45725 | B47: Circle K | C47: 63 | D47: Living expense
B48: Bánh kẹp | C48: 15 | D48: Living expense
B49: Texas | C49: 75 | D49: Living expense
B50: Mì trộn | C50: 64 | D50: Living expense
A51: 45726 | B51: Ăn sáng bánh ướt | C51: 20 | D51: Living expense
B52: Circle K | C52: 28 | D52: Living expense
B53: Bánh kẹp | C53: 15 | D53: Living expense
B54: Texas | C54: 104 | D54: Living expense
B55: Steam game | C55: 100 | D55: Living expense
A56: 45727 | B56: Circle K | C56: 140 | D56: Living expense
B57: Phí BIDV | C57: 52 | D57: Fee
B58: Ăn tối | C58: 50 | D58: Living expense
B59: Bánh cá | C59: 56 | D59: Living expense
B60: Overcooked 2 | C60: 110 | D60: Living expense
B61: Youtube Premium | C61: 51 | D61: Living expense
A62: 45728 | B62: GS25 | C62: 14 | D62: Living expense
B63: Texas | C63: 104 | D63: Living expense
A64: 45729 | B64: GS25 | C64: 24 | D64: Living expense
B65: Bún bò | C65: 30 | D65: Living expense
B66: Lotte Mart | C66: 150 | D66: Living expense
A67: 45730 | B67: Ăn trưa | C67: 30 | D67: Living expense
B68: Lotte Mart | C68: 1023 | D68: Living expense
B69: Ăn tối | C69: 63 | D69: Living expense
B70: One Piece DLC | C70: 120 | D70: Living expense
A71: 45731 | B71: Gonsa | C71: 5000 | D71: Gonsa
B72: Cơm | C72: 30 | D72: Living expense
B73: Rửa xe | C73: 25 | D73: Living expense
B74: Circle K | C74: 14 | D74: Living expense
B75: Texas | C75: 124 | D75: Living expense
A76: 45732 | B76: Circle K | C76: 63 | D76: Living expense
B77: Đổ xăng | C77: 50 | D77: Living expense
B78: Jolibee | C78: 90 | D78: Living expense
A79: 45733 | B79: Texas | C79: 84 | D79: Living expense
A80: 45734 | B80: Circle K (trưa) | C80: 86 | D80: Living expense
B81: Bún bò | C81: 30 | D81: Living expense
B82: Circle K (chiều) | C82: 81 | D82: Living expense
B83: Minecraft card pack x1 | C83: 49 | D83: Living expense
B84: Nước Trà Vinh | C84: 18 | D84: Living expense
A85: 45735 | B85: Cáp mạng | C85: 95 | D85: Living expense
B86: Circle K | C86: 63 | D86: Living expense
B87: Minecraft card pack x1 | C87: 49 | D87: Living expense
B88: Texas | C88: 74 | D88: Living expense
A89: 45736 | B89: Texas | C89: 104 | D89: Living expense
B90: Su kem | C90: 20 | D90: Living expense
A91: 45737 | B91: Circle K | C91: 28 | D91: Living expense
B92: Cơm gà | C92: 40 | D92: Living expense
B93: Heylo & Kiss | C93: 210 | D93: Living expense
B94: Ăn tối | C94: 69 | D94: Living expense
B95: Minecraft card pack x2 | C95: 98 | D95: Living expense
B96: Ăn khuya | C96: 67 | D96: Living expense
A97: 45738 | B97: Circle K | C97: 73 | D97: Living expense
B98: Đổ xăng | C98: 50 | D98: Living expense
B99: Winmart+ | C99: 24 | D99: Living expense
A100: 45739 | B100: Ăn sáng | C100: 60 | D100: Living expense
...

Sheet T22025
A1: DATE | B1: SPENT FOR | C1: AMOUNT | D1: TYPE | F1: DATE | G1: EARN BY | H1: AMOUNT
A2: 45689 | B2: Netflix | C2: 260 | D2: Living expense | F2: 45689 | G2: Initial from last month | H2: 12885
B3: Fshare | C3: 20 | D3: Living expense | F3: 45690 | G3: Vương trả (tháng trước) | H3: 1000
B4: Ăn sáng | C4: 40 | D4: Living expense | F4: 45691 | G4: Hoàn tiền Steam | H4: 257
B5: Nước ngọt | C5: 15 | D5: Living expense | F5: 45692 | G5: Kim Anh trả | H5: 2500
B6: Trà sữa | C6: 35 | D6: Living expense | F6: 45693 | G6: Lì xì | H6: 200
B7: Kim Anh Netflix | C7: -65 | D7: Living expense | F7: 45701 | G7: Khang support | H7: 2000
B8: Huy Netflix | C8: -65 | D8: Living expense | F8: 45704 | G8: Bảo support | H8: 500
B9: Game DLC | C9: 197 | D9: Living expense | G9: Kim Anh trả | H9: 500
B10: Cơm chiều | C10: 25 | D10: Living expense | F10: 45710 | G10: A Bảo help | H10: 500
B11: Bột chiên | C11: 60 | D11: Living expense | F11: 45712 | G11: Kim Anh trả | H11: 100
B12: Nước ngọt | C12: 11 | D12: Living expense | F12: 45713 | G12: Kim Anh trả | H12: 300
A13: 45690 | B13: Bún nước lèo | C13: 60 | D13: Living expense | F13: Total earn | G13: =SUM(H2:H12) -> 20742
B14: Pozza | C14: 35 | D14: Living expense | F14: Total spent | G14: =SUM(C2:C186) + G15 -> 20702
B15: Pozza | C15: 35 | D15: Living expense | F15: Minor spent | G15: =-10+1250-339-65+6+29+55 -> 926
B16: Tiền kết | C16: 10 | D16: Living expense | F16: Saving | G16: 0
B17: Help Vương | C17: 1000 | D17: Support
B18: Vương trả | C18: -1000 | D18: Support | F18: Estimate remaining | G18: =G13-G14-($G28-$H28) -> 40
B19: RedBull | C19: 13 | D19: Living expense
B20: Tiền nhà T2 | C20: 2418 | D20: Rent | F20: Category | G20: Estimated | H20: Actual
A21: 45691 | B21: Ăn sáng + nước | C21: 65 | D21: Living expense | F21: Living expense | G21: 5000 | H21: =SUMIF(D2:D108, "=Living expense",C2:C108) -> 6171
B22: Bắt xe ra bến | C22: 30 | D22: Living expense
B23: Nước ngọt | C23: 15 | D23: Living expense | F23: Planned/actual spend per category of this month
B24: Bắt xe về trọ | C24: 80 | D24: Living expense | F24: Category | G24: Estimated | H24: Actual
B25: Ăn trưa | C25: 70 | D25: Living expense | F25: Laptop | G25: 3224 | H25: =SUMIF(D3:D196, "=Laptop",C3:C196) -> 3224
B26: Đổ xăng | C26: 40 | D26: Living expense | F26: Gonsa | G26: 3000 | H26: =SUMIF(D4:D197, "=Gonsa",C4:C197) -> 3000
B27: Bơm xe | C27: 5 | D27: Living expense | F27: Rent | G27: 2418 | H27: =SUMIF(D5:D198, "=Rent",C5:C198) -> 2418
B28: Circle K Hoàn Mỹ | C28: 57 | D28: Living expense | F28: Sum | G28: =SUM(G23:G27) -> 8642 | H28: =SUM(H23:H27) -> 8642
B29: Massage | C29: 60 | D29: Living expense
B30: Vớ y khoa chống giãn TM | C30: 990 | D30: Parent
B31: Bò lá lốt | C31: 70 | D31: Living expense
B32: Help Má | C32: 300 | D32: Parent
B33: KFC | C33: 161 | D33: Living expense
B34: Bánh cá | C34: 54 | D34: Living expense
B35: Help Vương | C35: 1000 | D35: Support
B36: JackTheBus | C36: 85 | D36: Living expense
A37: 45692 | B37: Laptop | C37: 3224 | D37: Laptop
B38: 30Shine | C38: 800 | D38: Living expense
B39: Fahasha | C39: 50 | D39: Living expense
B40: Texas chicken | C40: 134 | D40: Living expense
B41: Circle K | C41: 28 | D41: Living expense
B42: NXB Kim Đồng | C42: 312 | D42: Living expense
B43: Tiền điện nhà | C43: 102 | D43: Living expense
A44: 45693 | B44: Ăn sáng | C44: 20 | D44: Living expense
B45: RedBull | C45: 14 | D45: Living expense
B46: Ăn tối | C46: 58 | D46: Living expense
B47: Circle K | C47: 73 | D47: Living expense
B48: Steam game | C48: 110 | D48: Living expense
A49: 45694 | B49: Ăn sáng | C49: 20 | D49: Living expense
B50: Nước | C50: 16 | D50: Living expense
B51: Ăn tối | C51: 35 | D51: Living expense
B52: Texas chicken | C52: 75 | D52: Living expense
A53: 45695 | B53: KFC | C53: 108 | D53: Living expense
B54: Bánh cá, bắp | C54: 54 | D54: Living expense
B55: Circle K | C55: 14 | D55: Living expense
A56: 45696 | B56: Cơm | C56: 30 | D56: Living expense
B57: Rửa xe | C57: 25 | D57: Living expense
B58: Circle K | C58: 14 | D58: Living expense
B59: Ăn chiều | C59: 67 | D59: Living expense
B60: Circle K | C60: 28 | D60: Living expense
A61: 45697 | B61: Texas chicken | C61: 120 | D61: Living expense
B62: Fahasha | C62: 51 | D62: Living expense
B63: Đổ xăng | C63: 50 | D63: Living expense
B64: Mua đt cho Má | C64: 1700 | D64: Parent
B65: Vương trả | C65: -1000 | D65: Support
A66: 45698 | B66: Ăn sáng | C66: 48 | D66: Living expense
B67: GS25 | C67: 14 | D67: Living expense
B68: Ăn tối | C68: 30 | D68: Living expense
B69: Fahasha | C69: 25 | D69: Living expense
B70: Grab | C70: 26 | D70: Living expense
B71: Dimsum | C71: 93 | D71: Living expense
A72: 45699 | B72: Grab | C72: 18 | D72: Living expense
B73: YouTube Premium | C73: 51 | D73: Living expense
B74: GS25 | C74: 14 | D74: Living expense
B75: Ăn tối | C75: 30 | D75: Living expense
B76: Circle K | C76: 28 | D76: Living expense
A77: 45700 | B77: ViettelPost | C77: 46 | D77: Living expense
B78: Tú Netflix | C78: -65 | D78: Living expense
B79: Cà phê | C79: 20 | D79: Living expense
B80: Ăn trưa | C80: 27 | D80: Living expense
B81: GS25 | C81: 24 | D81: Living expense
B82: Phí BIDV | C82: 51 | D82: Living expense
B83: Ăn chiều | C83: 48 | D83: Living expense
B84: Fahasha | C84: 55 | D84: Living expense
A85: 45701 | B85: Ăn sáng | C85: 27 | D85: Living expense
B86: Ăn trưa | C86: 22 | D86: Living expense
B87: GS25 | C87: 9 | D87: Living expense
B88: Texas chicken | C88: 143 | D88: Living expense
A89: 45702 | B89: Ăn sáng | C89: 20 | D89: Living expense
B90: GS25 | C90: 17 | D90: Living expense
B91: Ăn trưa | C91: 32 | D91: Living expense
B92: Cơm chiều | C92: 50 | D92: Living expense
B93: Gonsa | C93: 3000 | D93: Gonsa
B94: Đồ tiêu dùng Nhã Thy | C94: 339 | D94: Living expense
A95: 45703 | B95: Ăn sáng | C95: 20 | D95: Living expense
B96: CellphoneS bộ sạc | C96: 340 | D96: Living expense
B97: Rửa xe | C97: 25 | D97: Living expense
B98: Ăn trưa | C98: 30 | D98: Living expense
B99: Jolibee | C99: 115 | D99: Living expense
B100: Help Ly | C100: 200 | D100: Support
...

Sheet T12025
A1: DATE | B1: SPENT FOR | C1: AMOUNT | D1: TYPE | F1: DATE | G1: EARN BY | H1: AMOUNT
A2: 45656 | B2: Initial | C2: -706 | D2: Living expense | F2: 45656 | G2: Salary T12 | H2: 29863
B3: Ăn sáng | C3: 18 | D3: Living expense | F3: 45657 | G3: Bảo hiểm | H3: 2000
B4: Ăn trưa | C4: 35 | D4: Living expense | F4: 45670 | G4: Khang support | H4: 4000
B5: GS25 | C5: 52 | D5: Living expense | F5: 45672 | G5: Salary T13 | H5: 15015
B6: Trả party Rocket | C6: 350 | D6: Living expense | F6: 45680 | G6: Salary T1 | H6: 17107
B7: Trà sữa | C7: 28 | D7: Living expense | F7: 45682 | G7: Hoàn tiền cọc Ngô Gia | H7: 3710
B8: Ăn tối | C8: 95 | D8: Living expense | G8: JICA bonus | H8: 4000
B9: Trả ba | C9: 3500 | D9: Debt
B10: Help A Bảo | C10: 500 | D10: Living expense
A11: 45657 | B11: Ăn trưa | C11: 35 | D11: Living expense
B12: Circle K | C12: 20 | D12: Living expense
B13: Trả Khang | C13: 9000 | D13: Debt | F13: Total earn | G13: =SUM(H2:H12) -> 75695
B14: Ăn tối | C14: 49 | D14: Living expense | F14: Total spent | G14: =SUM(C2:C180) + G15 -> 62810
B15: Nhà sách | C15: 365 | D15: Living expense | F15: Minor spent | G15: =678+77 -> 755
B16: Bánh | C16: 40 | D16: Living expense | F16: Saving | G16: 0
A17: 45658 | B17: Ăn trưa | C17: 32 | D17: Living expense
B18: Trà sữa | C18: 27 | D18: Living expense | F18: Estimate remaining | G18: =G13-G14-G32+H32 -> 12885
B19: Yame | C19: 801 | D19: Living expense
B20: Tiền nhà T1 | C20: 4354 | D20: Rent | F20: Category | G20: Estimated | H20: Actual
B21: Hớt tóc | C21: 315 | D21: Living expense | F21: Living expense | G21: 5000 | H21: =SUMIF(D2:D105, "=Living expense",C2:C105) -> 20405
B22: Circle K | C22: 53 | D22: Living expense
B23: Laptop | C23: 3221 | D23: Laptop | F23: Planned/actual spend per category of this month
A24: 45659 | B24: GS25 | C24: 24 | D24: Living expense | F24: Category | G24: Estimated | H24: Actual
B25: Ăn chiều | C25: 71 | D25: Living expense | F25: Debt | G25: 12500 | H25: =SUMIF(D3:D190, "=Debt",C3:C190) -> 12500
B26: Nhà sách | C26: 50 | D26: Living expense | F26: Gonsa | G26: 3000 | H26: =SUMIF(D4:D191, "=Gonsa",C4:C191) -> 3000
B27: Circle K | C27: 72 | D27: Living expense | F27: Parent | G27: 3000 | H27: =SUMIF(D5:D192, "=Parent",C5:C192) -> 3000
B28: Help Kim Anh | C28: 200 | D28: Living expense | F28: Rent | G28: 4354 | H28: =SUMIF(D6:D193, "=Rent",C6:C193) -> 4354
B29: Circle K | C29: 28 | D29: Living expense | F29: Laptop | G29: 3221 | H29: =SUMIF(D7:D194, "=Laptop",C7:C194) -> 3221
A30: 45660 | B30: Ăn trưa | C30: 35 | D30: Living expense | F30: Book | G30: 462 | H30: =SUMIF(D8:D195, "=Book",C8:C195) -> 462
B31: GS25 | C31: 23 | D31: Living expense | F31: Family trip | G31: 1444 | H31: =SUMIF(D9:D196, "=Family trip",C9:C196) -> 1444
B32: Trả giùm nước Rocket | C32: 139 | D32: Living expense | F32: Sum | G32: =SUM(G27:G31) -> 12481 | H32: =SUM(H27:H31) -> 12481
B33: Ăn tối | C33: 95 | D33: Living expense
A34: 45661 | B34: Ăn trưa | C34: 25 | D34: Living expense
B35: Đổ xăng | C35: 50 | D35: Living expense
B36: Cho ba má | C36: 3000 | D36: Parent
B37: Hủ tiếu | C37: 54 | D37: Living expense
B38: Net Nhanh Thạch | C38: 33 | D38: Living expense
B39: Đồ chiên | C39: 39 | D39: Living expense
A40: 45662 | B40: Cà phê Nguyên 2 | C40: 30 | D40: Living expense
B41: Nhà sách Khai Trí | C41: 20 | D41: Living expense
B42: Fahasha | C42: 179 | D42: Living expense
B43: Máy sấy tóc | C43: 259 | D43: Living expense
B44: Thuốc cho má | C44: 48 | D44: Living expense
B45: Ăn bún | C45: 20 | D45: Living expense
B46: Winmart+ | C46: 35 | D46: Living expense
B47: Circle K | C47: 106 | D47: Living expense
B48: Help Kim Anh | C48: 1500 | D48: Living expense
B49: Tiền điện nhà T1 | C49: 102 | D49: Living expense
A50: 45663 | B50: GS25 | C50: 23 | D50: Living expense
B51: Ăn chiều | C51: 59 | D51: Living expense
B52: Cọc nhà trọ | C52: 2000 | D52: Living expense
B53: Tú trả | C53: -180 | D53: Living expense
A54: 45664 | B54: GS25 | C54: 14 | D54: Living expense
B55: Ăn tối | C55: =121-37-37 -> 47 | D55: Living expense
B56: Nhà sách | C56: 150 | D56: Living expense
B57: Đổ xăng | C57: 50 | D57: Living expense
B58: Đồ chiên | C58: 25 | D58: Living expense
B59: Circle K | C59: 20 | D59: Living expense
A60: 45665 | B60: GS25 | C60: 14 | D60: Living expense
B61: Ăn tối | C61: 37 | D61: Living expense
B62: Circle K | C62: 51 | D62: Living expense
A63: 45666 | B63: GS25 | C63: 14 | D63: Living expense
B64: Ăn tối | C64: 35 | D64: Living expense
B65: Truyện Én | C65: 179 | D65: Living expense
B66: Circle K | C66: 20 | D66: Living expense
A67: 45667 | B67: Ăn trưa | C67: 30 | D67: Living expense
A68: 45668 | B68: Ăn trưa | C68: 30 | D68: Living expense
B69: Circle K | C69: 70 | D69: Living expense
B70: Youtube Premium | C70: 52 | D70: Living expense
B71: The 80s | C71: 38 | D71: Living expense
B72: Circle K | C72: 34 | D72: Living expense
A73: 45669 | B73: Ăn trưa | C73: 38 | D73: Living expense
B74: The 80s | C74: 30 | D74: Living expense
B75: Circle K | C75: 28 | D75: Living expense
A76: 45670 | B76: Ăn sáng | C76: 18 | D76: Living expense
B77: GS25 | C77: 14 | D77: Living expense
B78: Ăn tối | C78: 66 | D78: Living expense
B79: Truyện tranh | C79: 50 | D79: Living expense
A80: 45671 | B80: GS25 | C80: 14 | D80: Living expense
B81: Gonsa | C81: 3000 | D81: Gonsa
B82: Help A Bảo | C82: 600 | D82: Living expense
A83: 45672 | B83: GS25 | C83: 14 | D83: Living expense
B84: Bún bò | C84: 52 | D84: Living expense
B85: Đổ xăng | C85: 50 | D85: Living expense
B86: Circle K | C86: 28 | D86: Living expense
A87: 45673 | B87: GS25 | C87: 14 | D87: Living expense
B88: Bún bò | C88: 30 | D88: Living expense
A89: 45674 | B89: Ăn sáng | C89: 18 | D89: Living expense
B90: Ăn trưa | C90: 35 | D90: Living expense
B91: GS25 | C91: 14 | D91: Living expense
B92: Ăn tối | C92: 66 | D92: Living expense
B93: Help A Bảo | C93: 2000 | D93: Living expense
B94: Cọc nhà trọ | C94: 1500 | D94: Living expense
B95: Fahasha | C95: 462 | D95: Book
B96: Circle K | C96: 60 | D96: Living expense
A97: 45675 | B97: Ăn cơm | C97: 22 | D97: Living expense
B98: Help Kim Anh | C98: 2500 | D98: Living expense
B99: Trả Khang | C99: 4000 | D99: Living expense
B100: Quà cho thầy Thái | C100: 228 | D100: Living expense
...
